Workbook
Name \0: #REF!
Name \0: #REF!
Name \a: #REF!
Name \c: #REF!
Name \g: [1]BP!#REF!
Name \k: [2]KP1590_E!#REF!
Name \L: #REF!
Name \L: #REF!
Name \O: #REF!
Name \O: #REF!
Name \p: '[3]7-2'!#REF!
Name \p: '[3]7-2'!#REF!
Name \r: #REF!
Name \r: #REF!
Name \u: #N/A
Name \V: #REF!
Name \V: #REF!
Name \x: [2]KP1590_E!#REF!
Name \x: [2]KP1590_E!#REF!
Name \z: #REF!
Name \z: #REF!
Name ____ig541: #REF!
Name ____ig541: #REF!
Name ___ann6: [4]!___ann6
Name ___ann6: [5]!___ann6
Name ___Dec1: #REF!
Name ___Dec1: #REF!
Name ___det1855: #REF!
Name ___det1855: #REF!
Name ___det2173: #REF!
Name ___det2173: #REF!
Name ___det2362: #REF!
Name ___det2403: #REF!
Name ___ig541: #REF!
Name ___KC139: #REF!
Name ___Nov02: #REF!
Name ___tp1855: #REF!
Name ___tp2362: #REF!
Name ___tp2403: #REF!
Name ___TR1: #REF!
Name __a5: [6]!Module1.UNITOK
Name __a6: [7]!UNITOK
Name __ann6: [4]!__ann6
Name __ann6: [5]!__ann6
Name __CHF1: #REF!
Name __CHF1: #REF!
Name __DAT18: #REF!
Name __DAT18: #REF!
Name __Dec1: #REF!
Name __Dec1: #REF!
Name __det1855: #REF!
Name __det2173: #REF!
Name __det2362: #REF!
Name __det2403: #REF!
Name __dim4: #REF!
Name __ig541: #REF!
Name __KC139: #REF!
Name __Nov02: #REF!
Name __OPT8: [8]!_xlbgnm.OPT8
Name __OPT9: [8]!_xlbgnm.OPT9

Sheet instructions
B2: Instructions:
B4: 1. | C4: "NPV PT" is the main sheet for the DCF calculations
B5: 2. | C5: Please open your own sheets (working sheet) for the detailed calculations (investment case, base case etc), but use the NPV PT sheet for the NPV/DCF calculations
B6: 3. | C6: The yellow cells are the ones which needs either direct inputs or inputs through linking to other (your) sheets. Grey lines do have formulas
B7: 4. | C7: Select you country from the drop down list in cell C2 in the "NPV PT" sheet
C8: (for European projects you can select "Euro area")
B9: 5. | C9: FX rates and inflation will be automatically populated from the blue book data (a hidden sheet) - please check the date - if there is new bluebook assumption please copy the new ones into the hidden sheets
B10: 6. | C10: Tax rates will aslo be populated. The rates for the major countries have been obtained from BP Global tax team, for the rest the rates were taken from the KPMG site.
C11: You can see the source in cell P15 in the "NPV PT" sheet. If it indicate "KPMG", then refer to local Tax team for reconfirmation.
B12: 7. | C12: Lines 16 to 22 are to be used if there is an incremantal volume /GM due to the project
B13: 8. | C13: Capex and Depr are in a separate sheet - "Capex&Depr"
B14: 9. | C14: Capex Creditors (line 53) need to be inserted by the use. Advise would be that Capex spend in Q4 is assumed to be cashed out the next year
B15: 10. | C15: Please add lines in case the headings in the sheet are not enough - both for P/L and Cash Flow
B16: 11. | C16: The outputs of the DCF are between lines 70-73
B17: 12. | C17: And there are some additional BP metrics between lines 86-96. In case new lines are added to the DCF, the BP metrics may need to be adjusted
B18: 13. | C18: The outputs are also visible in the Summary sheet - with an FM format. Please hide any lines which are not relevant
B19: 14. | C19: In the summary sheet, between lines 6-14 please hide the metrics which are not relevant
B20: 15. | C20: the NTE calculations are in sheet "NPV NTE". The sheet gets the numbers from sheet "NPV PT", the only difference is that it adds the NTE extra request as per the % in column D.
C21: In case this simple rule does not work please ammend the lines directly
B22: 16. | C22: The CashFlow sheet is automatically populated - but if any lines added to the DCF please check the links are correct
B23: 17. | C23: Length of the project is 10 years in the template, but it will change depending on the nature of the projectsi life of assets etc. Please deletete excess columns if less then 10 years,
C24: or add additional columns and copy formulas if need to be more then 15 years.
B25: 18. | C25: A sheet was added re frequently made mistakes - please analyze the sheet before starting or finalizing
B26: 19. | C26: Another sheet was added for the asset useful lives - the recent changes are seen in a separate column (column F)
B27: 20. | C27: The grey sheets are info sheets, the white sheets are working sheets, yellow sheets are the charts needed for the big FM's, and the green ones are the main DCF sheets
B28: 21. | C28: Signages:
C29: + : income / asset / cash-in
C30: – : expense / liability / cash-out

Sheet summary
B3: Expected Impact on External bp Metrics:
C5: bp Net @ central price | D5: ='NPV PT'!D10 -> 2025 | E5: ='NPV PT'!E10 -> 2026 | F5: ='NPV PT'!F10 -> 2027 | G5: ='NPV PT'!G10 -> 2028 | H5: ='NPV PT'!H10 -> 2029 | I5: ='NPV PT'!I10 -> 2030 | J5: TOTAL
C6: Cash Capex | D6: ='NPV PT'!D92/1000000 -> -0.29745902 | E6: ='NPV PT'!E92/1000000 -> 0 | F6: ='NPV PT'!F92/1000000 -> 0 | G6: ='NPV PT'!G92/1000000 -> 0 | H6: ='NPV PT'!H92/1000000 -> 0 | I6: ='NPV PT'!I92/1000000 -> 0 | J6: ='NPV PT'!O92/1000000 -> -0.29745902
C7: Revex | D7: ='NPV PT'!D93/1000000 -> 0 | E7: ='NPV PT'!E93/1000000 -> 0 | F7: ='NPV PT'!F93/1000000 -> 0 | G7: ='NPV PT'!G93/1000000 -> 0 | H7: ='NPV PT'!H93/1000000 -> 0 | I7: ='NPV PT'!I93/1000000 -> 0 | J7: ='NPV PT'!O93/1000000 -> 0
C8: Remediation | D8: ='NPV PT'!D94/1000000 -> 0 | E8: ='NPV PT'!E94/1000000 -> 0 | F8: ='NPV PT'!F94/1000000 -> 0 | G8: ='NPV PT'!G94/1000000 -> 0 | H8: ='NPV PT'!H94/1000000 -> 0 | I8: ='NPV PT'!I94/1000000 -> 0 | J8: ='NPV PT'!O94/1000000 -> 0
C9: Ratex | D9: ='NPV PT'!D95/1000000 -> 0 | E9: ='NPV PT'!E95/1000000 -> 0 | F9: ='NPV PT'!F95/1000000 -> 0 | G9: ='NPV PT'!G95/1000000 -> 0 | H9: ='NPV PT'!H95/1000000 -> 0 | I9: ='NPV PT'!I95/1000000 -> 0 | J9: ='NPV PT'!O95/1000000 -> 0
C10: Post tax free cash flow ($m) | D10: ='NPV PT'!D99/1000000 -> -0.36200255 | E10: ='NPV PT'!E99/1000000 -> 0.66762068 | F10: ='NPV PT'!F99/1000000 -> 0.66848631 | G10: ='NPV PT'!G99/1000000 -> 0.66906031 | H10: ='NPV PT'!H99/1000000 -> 0.66949466 | I10: ='NPV PT'!I99/1000000 -> 0.66985794 | J10: ='NPV PT'!O99/1000000 -> 2.9825174
C11: Underlying RCOP ($m) | D11: ='NPV PT'!D101/1000000 -> -0.053503185 | E11: ='NPV PT'!E101/1000000 -> 0.79013503 | F11: ='NPV PT'!F101/1000000 -> 0.78652822 | G11: ='NPV PT'!G101/1000000 -> 0.78413656 | H11: ='NPV PT'!H101/1000000 -> 0.78232675 | I11: ='NPV PT'!I101/1000000 -> 0.78081308 | J11: ='NPV PT'!O101/1000000 -> 3.8704365
C12: GHG S1 & S2 emissions (kt, CO2e)
C13: · A lease asset and liability will be reported on the balance sheet from the start of the lease in [date] of $[X]m with lease payments of $[X]m per annum.
C14: · [Enter business group specific metrics].
M17: Economics:
N19: Blue Book Price/Margin | O19: Sensitivity Case | P19: Financial Request $m | Q19: NPV | R19: IRR | S19: PI | T19: DP
Q20: $m | R20: % | S20: $/$ | T20: Years
N21: Central | O21: NTE | P21: =-('NPV NTE'!P92+'NPV NTE'!P93+'NPV NTE'!P94+'NPV NTE'!P95)/1000000 -> 0.30981826 | Q21: ='NPV NTE'!C75 -> 2.2918439 | R21: ='NPV NTE'!C76*100 -> 177.52775 | S21: ='NPV NTE'!C78 -> 2.2334567 | T21: ='NPV NTE'!C77 -> 1.5994358
O22: PT | P22: =-('NPV PT'!O92+'NPV PT'!O93+'NPV PT'!O94+'NPV PT'!O95)/1000000 -> 0.29745902 | Q22: ='NPV PT'!C75 -> 2.3011519 | R22: ='NPV PT'!C76*100 -> 183.5252 | S22: ='NPV PT'!C78 -> 2.2475294 | T22: ='NPV PT'!C77 -> 1.5801838

Sheet NPV PT
B2: Country | C2: Malaysia
B3: Cost of Capital | C3: 0.08 | F3: Project X
D8: 0 | E8: 1 | F8: 2 | G8: 3 | H8: 4 | I8: 5 | J8: 6 | K8: 7 | L8: 8 | M8: 9 | N8: 10
B9: Particulars | D9: Year 0 | E9: Year 1 | F9: Year 2 | G9: Year 3 | H9: Year 4 | I9: Year 5 | J9: Year 6 | K9: Year 7 | L9: Year 8 | M9: Year 9 | N9: Year 10
D10: 2025 | E10: =D10+1 -> 2026 | F10: =E10+1 -> 2027 | G10: =F10+1 -> 2028 | H10: =G10+1 -> 2029 | I10: =H10+1 -> 2030 | J10: =I10+1 -> 2031 | K10: =J10+1 -> 2032 | L10: =K10+1 -> 2033 | ... N10: =M10+1 -> 2035
B11: GIAAP
B12: FX rates | C12: =CONCATENATE(VLOOKUP($C$2,countries!C:F,4,0),"/USD") -> MYR/USD | D12: =IF(VLOOKUP($C$2,countries!$C:$D,2,0)="Euro area",1/VLOOKUP(VLOOKUP($C$2,countries!$C:$D,2,0),'BB FX'!$B:$AE,D8+4,0),VLOOKUP(VLOOKUP($C$2,countries!$C:$D,2,0),'BB FX'!$B:$AE,D8+4,0)) -> 4.71 | E12: =IF(VLOOKUP($C$2,countries!$C:$D,2,0)="Euro area",1/VLOOKUP(VLOOKUP($C$2,countries!$C:$D,2,0),'BB FX'!$B:$AE,E8+4,0),VLOOKUP(VLOOKUP($C$2,countries!$C:$D,2,0),'BB FX'!$B:$AE,E8+4,0)) -> 4.51 | F12: =IF(VLOOKUP($C$2,countries!$C:$D,2,0)="Euro area",1/VLOOKUP(VLOOKUP($C$2,countries!$C:$D,2,0),'BB FX'!$B:$AE,F8+4,0),VLOOKUP(VLOOKUP($C$2,countries!$C:$D,2,0),'BB FX'!$B:$AE,F8+4,0)) -> 4.28 | G12: =IF(VLOOKUP($C$2,countries!$C:$D,2,0)="Euro area",1/VLOOKUP(VLOOKUP($C$2,countries!$C:$D,2,0),'BB FX'!$B:$AE,G8+4,0),VLOOKUP(VLOOKUP($C$2,countries!$C:$D,2,0),'BB FX'!$B:$AE,G8+4,0)) -> 4.14 | H12: =IF(VLOOKUP($C$2,countries!$C:$D,2,0)="Euro area",1/VLOOKUP(VLOOKUP($C$2,countries!$C:$D,2,0),'BB FX'!$B:$AE,H8+4,0),VLOOKUP(VLOOKUP($C$2,countries!$C:$D,2,0),'BB FX'!$B:$AE,H8+4,0)) -> 4.04 | I12: =IF(VLOOKUP($C$2,countries!$C:$D,2,0)="Euro area",1/VLOOKUP(VLOOKUP($C$2,countries!$C:$D,2,0),'BB FX'!$B:$AE,I8+4,0),VLOOKUP(VLOOKUP($C$2,countries!$C:$D,2,0),'BB FX'!$B:$AE,I8+4,0)) -> 3.96 | J12: =IF(VLOOKUP($C$2,countries!$C:$D,2,0)="Euro area",1/VLOOKUP(VLOOKUP($C$2,countries!$C:$D,2,0),'BB FX'!$B:$AE,J8+4,0),VLOOKUP(VLOOKUP($C$2,countries!$C:$D,2,0),'BB FX'!$B:$AE,J8+4,0)) -> 3.91 | K12: =IF(VLOOKUP($C$2,countries!$C:$D,2,0)="Euro area",1/VLOOKUP(VLOOKUP($C$2,countries!$C:$D,2,0),'BB FX'!$B:$AE,K8+4,0),VLOOKUP(VLOOKUP($C$2,countries!$C:$D,2,0),'BB FX'!$B:$AE,K8+4,0)) -> 3.88 | ... N12: =IF(VLOOKUP($C$2,countries!$C:$D,2,0)="Euro area",1/VLOOKUP(VLOOKUP($C$2,countries!$C:$D,2,0),'BB FX'!$B:$AE,N8+4,0),VLOOKUP(VLOOKUP($C$2,countries!$C:$D,2,0),'BB FX'!$B:$AE,N8+4,0)) -> 3.83
B13: Inflation Rates | C13: % | D13: =VLOOKUP($C$2,'BB inflation'!$B:$AE,D8+4,0)/100 -> 0.02385 | E13: =VLOOKUP($C$2,'BB inflation'!$B:$AE,E8+4,0)/100 -> 0.0273 | F13: =VLOOKUP($C$2,'BB inflation'!$B:$AE,F8+4,0)/100 -> 0.0259 | G13: =VLOOKUP($C$2,'BB inflation'!$B:$AE,G8+4,0)/100 -> 0.02595 | H13: =VLOOKUP($C$2,'BB inflation'!$B:$AE,H8+4,0)/100 -> 0.0235 | I13: =VLOOKUP($C$2,'BB inflation'!$B:$AE,I8+4,0)/100 -> 0.024 | J13: =VLOOKUP($C$2,'BB inflation'!$B:$AE,J8+4,0)/100 -> 0.0243 | K13: =VLOOKUP($C$2,'BB inflation'!$B:$AE,K8+4,0)/100 -> 0.0243 | ... N13: =VLOOKUP($C$2,'BB inflation'!$B:$AE,N8+4,0)/100 -> 0.02355
B14: Cumm Inflation Rates | C14: % | E14: =(1+D14)*(1+D13)-1 -> 0.02385 | F14: =(1+E14)*(1+E13)-1 -> 0.051801105 | G14: =(1+F14)*(1+F13)-1 -> 0.079042754 | H14: =(1+G14)*(1+G13)-1 -> 0.10704391 | I14: =(1+H14)*(1+H13)-1 -> 0.13305945 | J14: =(1+I14)*(1+I13)-1 -> 0.16025287 | K14: =(1+J14)*(1+J13)-1 -> 0.18844702 | L14: =(1+K14)*(1+K13)-1 -> 0.21732628 | ... N14: =(1+M14)*(1+M13)-1 -> 0.2762098 | P14: tax info from:
B15: Tax rate | C15: % | D15: =VLOOKUP($C$2,'tax rates'!$B:$AE,D$8+4,0)/100 -> 0.24 | E15: =VLOOKUP($C$2,'tax rates'!$B:$AE,E$8+4,0)/100 -> 0.24 | F15: =VLOOKUP($C$2,'tax rates'!$B:$AE,F$8+4,0)/100 -> 0.24 | G15: =VLOOKUP($C$2,'tax rates'!$B:$AE,G$8+4,0)/100 -> 0.24 | H15: =VLOOKUP($C$2,'tax rates'!$B:$AE,H$8+4,0)/100 -> 0.24 | I15: =VLOOKUP($C$2,'tax rates'!$B:$AE,I$8+4,0)/100 -> 0.24 | J15: =VLOOKUP($C$2,'tax rates'!$B:$AE,J$8+4,0)/100 -> 0.24 | K15: =VLOOKUP($C$2,'tax rates'!$B:$AE,K$8+4,0)/100 -> 0.24 | ... N15: =VLOOKUP($C$2,'tax rates'!$B:$AE,N$8+4,0)/100 -> 0.24 | P15: =VLOOKUP(C2,'tax rates'!B:AF,31,0) -> BP tax - 2023 | Q15: -----> please check / reconfirm with your local tax also (especially if info is from KPMG source)
B16: Assumptions
B17: Additional Sales Volume | C17: lt | E17: ='Working - MY OU 5% Imrpovement'!E6 -> 1511910.2 | F17: ='Working - MY OU 5% Imrpovement'!F6 -> 1511910.2 | G17: ='Working - MY OU 5% Imrpovement'!G6 -> 1511910.2 | H17: ='Working - MY OU 5% Imrpovement'!H6 -> 1511910.2 | I17: ='Working - MY OU 5% Imrpovement'!I6 -> 1511910.2 | O17: -----> if there is additional sales volume
B18: Unit Margin | C18: =CONCATENATE(VLOOKUP($C$2,countries!C:F,4,0),"/lt") -> MYR/lt | E18: ='Working - MY OU 5% Imrpovement'!E7*E12 -> 4.059 | F18: ='Working - MY OU 5% Imrpovement'!F7*F12 -> 3.852 | G18: ='Working - MY OU 5% Imrpovement'!G7*G12 -> 3.726 | H18: ='Working - MY OU 5% Imrpovement'!H7*H12 -> 3.636 | I18: ='Working - MY OU 5% Imrpovement'!I7*I12 -> 3.564
B19: Unit COGS | C19: =CONCATENATE(VLOOKUP($C$2,countries!C:F,4,0),"/lt") -> MYR/lt
B20: Unit Margin | C20: =CONCATENATE(VLOOKUP($C$2,countries!C:F,4,0),"/lt") -> MYR/lt | D20: =D18+D19 -> 0 | E20: =E18+E19 -> 4.059 | F20: =F18+F19 -> 3.852 | G20: =G18+G19 -> 3.726 | H20: =H18+H19 -> 3.636 | I20: =I18+I19 -> 3.564 | J20: =J18+J19 -> 0 | K20: =K18+K19 -> 0 | ... N20: =N18+N19 -> 0
B21: Sales Turnover | C21: =VLOOKUP($C$2,countries!C:F,4,0) -> MYR | D21: =D17*D18 -> 0 | E21: =E17*E18 -> 6136843.5 | F21: =F17*F18 -> 5823878.1 | G21: =G17*G18 -> 5633377.4 | H21: =H17*H18 -> 5497305.5 | I21: =I17*I18 -> 5388448 | J21: =J17*J18 -> 0 | K21: =K17*K18 -> 0 | ... N21: =N17*N18 -> 0
B22: COGS | C22: =VLOOKUP($C$2,countries!C:F,4,0) -> MYR | D22: =D17*D19 -> 0 | E22: =E17*E19 -> 0 | F22: =F17*F19 -> 0 | G22: =G17*G19 -> 0 | H22: =H17*H19 -> 0 | I22: =I17*I19 -> 0 | J22: =J17*J19 -> 0 | K22: =K17*K19 -> 0 | ... N22: =N17*N19 -> 0
B23: Profit and Loss
B24: Topline Growth (GM - Additional volume profit) | C24: =VLOOKUP($C$2,countries!C:F,4,0) -> MYR | D24: =D20*D17 -> 0 | E24: =E20*E17 -> 6136843.5 | F24: =F20*F17 -> 5823878.1 | G24: =G20*G17 -> 5633377.4 | H24: =H20*H17 -> 5497305.5 | I24: =I20*I17 -> 5388448 | J24: =J20*J17 -> 0 | K24: =K20*K17 -> 0 | ... N24: =N20*N17 -> 0
B25: Secondary Logs Refund/Rebate (for Indirect channel) | C25: =VLOOKUP($C$2,countries!C:F,4,0) -> MYR
B26: Additional Volume Sec Distribution (TCC) | C26: =VLOOKUP($C$2,countries!C:F,4,0) -> MYR
B27: CFC (TCC) | C27: =VLOOKUP($C$2,countries!C:F,4,0) -> MYR
B28: Marketing costs (TCC) | C28: =VLOOKUP($C$2,countries!C:F,4,0) -> MYR | D28: -400000
B29: ASP | C29: =VLOOKUP($C$2,countries!C:F,4,0) -> MYR
B30: Write-offs (COGS - GM) | C30: =VLOOKUP($C$2,countries!C:F,4,0) -> MYR
B31: Other Income | C31: =VLOOKUP($C$2,countries!C:F,4,0) -> MYR
B32: GSC Savings/Costs (GM) - RM COGS | C32: =VLOOKUP($C$2,countries!C:F,4,0) -> MYR
B33: GSC Savings/Costs (TCC) - Manufacturing | C33: =VLOOKUP($C$2,countries!C:F,4,0) -> MYR
B34: GSC Savings/Costs (TCC) - BU Support | C34: =VLOOKUP($C$2,countries!C:F,4,0) -> MYR
B35: GSC Savings/Costs (ACC) - Primary Logistics | C35: =VLOOKUP($C$2,countries!C:F,4,0) -> MYR
B36: GSC Savings/Costs (ACC) - S&H | C36: =VLOOKUP($C$2,countries!C:F,4,0) -> MYR
B37: GSC Savings/Costs (TCC) - Sec Logistics | C37: =VLOOKUP($C$2,countries!C:F,4,0) -> MYR
B38: GBS cost savings (TCC) | C38: =VLOOKUP($C$2,countries!C:F,4,0) -> MYR
B39: Project Revex (Implementation costs) | C39: =VLOOKUP($C$2,countries!C:F,4,0) -> MYR
B40: Depreciation | C40: =VLOOKUP($C$2,countries!C:F,4,0) -> MYR | D40: =SUM('Capex&Depr'!F20:F29) -> 0 | E40: =SUM('Capex&Depr'!G20:G29) -> -480480 | F40: =SUM('Capex&Depr'!H20:H29) -> -480480 | G40: =SUM('Capex&Depr'!I20:I29) -> -480480 | H40: =SUM('Capex&Depr'!J20:J29) -> -480480 | I40: =SUM('Capex&Depr'!K20:K29) -> -480480 | J40: =SUM('Capex&Depr'!L20:L29) -> 0 | K40: =SUM('Capex&Depr'!M20:M29) -> 0 | ... M40: =SUM('Capex&Depr'!O20:O29) -> 0
B41: Impairment | C41: =VLOOKUP($C$2,countries!C:F,4,0) -> MYR
B42: Remediation & Dismantling Costs | C42: =VLOOKUP($C$2,countries!C:F,4,0) -> MYR
B43: Ratex accrued | C43: =VLOOKUP($C$2,countries!C:F,4,0) -> MYR
B44: Net Profit | C44: =VLOOKUP($C$2,countries!C:F,4,0) -> MYR | D44: =SUM(D23:D43) -> -400000 | E44: =SUM(E23:E43) -> 5656363.5 | F44: =SUM(F23:F43) -> 5343398.1 | G44: =SUM(G23:G43) -> 5152897.4 | H44: =SUM(H23:H43) -> 5016825.5 | I44: =SUM(I23:I43) -> 4907968 | J44: =SUM(J23:J43) -> 0 | K44: =SUM(K23:K43) -> 0 | ... N44: =SUM(N23:N43) -> 0
B45: Interest | C45: =VLOOKUP($C$2,countries!C:F,4,0) -> MYR | D45: 0 | E45: 0 | F45: 0 | G45: 0 | H45: 0 | I45: 0 | J45: 0 | K45: 0 | L45: 0 | M45: 0 | N45: 0
B46: Net Profit After interest | C46: =VLOOKUP($C$2,countries!C:F,4,0) -> MYR | D46: =+D45+D44 -> -400000 | E46: =SUM(E44:E45) -> 5656363.5 | F46: =SUM(F44:F45) -> 5343398.1 | G46: =SUM(G44:G45) -> 5152897.4 | H46: =SUM(H44:H45) -> 5016825.5 | I46: =SUM(I44:I45) -> 4907968 | J46: =SUM(J44:J45) -> 0 | K46: =SUM(K44:K45) -> 0 | L46: =SUM(L44:L45) -> 0 | ... N46: =SUM(N44:N45) -> 0
B47: Tax | C47: =VLOOKUP($C$2,countries!C:F,4,0) -> MYR | D47: =-D15*(D46+D57) -> 96000 | E47: =-E15*(E46+E57) -> -1357527.2 | F47: =-F15*(F46+F57) -> -1282415.5 | G47: =-G15*(G46+G57) -> -1236695.4 | H47: =-H15*(H46+H57) -> -1204038.1 | I47: =-I15*(I46+I57) -> -1177912.3 | J47: =-J15*(J46+J57) -> 0 | K47: =-K15*(K46+K57) -> 0 | ... N47: =-N15*(N46+N57) -> 0
B48: Net profit after tax | C48: =VLOOKUP($C$2,countries!C:F,4,0) -> MYR | D48: =+D47+D46 -> -304000 | E48: =SUM(E46:E47) -> 4298836.3 | F48: =SUM(F46:F47) -> 4060982.5 | G48: =SUM(G46:G47) -> 3916202 | H48: =SUM(H46:H47) -> 3812787.4 | I48: =SUM(I46:I47) -> 3730055.6 | J48: =SUM(J46:J47) -> 0 | K48: =SUM(K46:K47) -> 0 | L48: =SUM(L46:L47) -> 0 | ... N48: =SUM(N46:N47) -> 0
B49: Cashflow
B50: Net profit Before tax | C50: =VLOOKUP($C$2,countries!C:F,4,0) -> MYR | D50: =D46 -> -400000 | E50: =E46 -> 5656363.5 | F50: =F46 -> 5343398.1 | G50: =G46 -> 5152897.4 | H50: =H46 -> 5016825.5 | I50: =I46 -> 4907968 | J50: =J46 -> 0 | K50: =K46 -> 0 | ... N50: =N46 -> 0
B51: Add: Depreciation | C51: =VLOOKUP($C$2,countries!C:F,4,0) -> MYR | D51: =-D40-D41 -> 0 | E51: =-E40-E41 -> 480480 | F51: =-F40-F41 -> 480480 | G51: =-G40-G41 -> 480480 | H51: =-H40-H41 -> 480480 | I51: =-I40-I41 -> 480480 | J51: =-J40-J41 -> 0 | K51: =-K40-K41 -> 0 | ... N51: =-N40-N41 -> 0
B52: Less: Cash taxes | C52: =VLOOKUP($C$2,countries!C:F,4,0) -> MYR | D52: =D47 -> 96000 | E52: =E47 -> -1357527.2 | F52: =F47 -> -1282415.5 | G52: =G47 -> -1236695.4 | H52: =H47 -> -1204038.1 | I52: =I47 -> -1177912.3 | J52: =J47 -> 0 | K52: =K47 -> 0 | ... N52: =N47 -> 0
B53: Capex accrued | C53: =VLOOKUP($C$2,countries!C:F,4,0) -> MYR | D53: =SUM('Capex&Depr'!F4:F13) -> -2402400 | E53: =SUM('Capex&Depr'!G4:G13) -> 0 | F53: =SUM('Capex&Depr'!H4:H13) -> 0 | G53: =SUM('Capex&Depr'!I4:I13) -> 0 | H53: =SUM('Capex&Depr'!J4:J13) -> 0 | I53: =SUM('Capex&Depr'!K4:K13) -> 0 | J53: =SUM('Capex&Depr'!L4:L13) -> 0 | K53: =SUM('Capex&Depr'!M4:M13) -> 0 | ... N53: =SUM('Capex&Depr'!P4:P13) -> 0
B54: JV Interes | C54: =VLOOKUP($C$2,countries!C:F,4,0) -> MYR | D54: =-37%*SUM(D50:D53) -> 1001368 | E54: =-37%*SUM(E50:E53) -> -1768347 | F54: =-37%*SUM(F50:F53) -> -1680341.1 | G54: =-37%*SUM(G50:G53) -> -1626772.4 | H54: =-37%*SUM(H50:H53) -> -1588508.9 | I54: =-37%*SUM(I50:I53) -> -1557898.2 | J54: =-37%*SUM(J50:J53) -> 0 | K54: =-37%*SUM(K50:K53) -> 0 | ... N54: =-37%*SUM(N50:N53) -> 0
B55: Withholding Tax | C55: =VLOOKUP($C$2,countries!C:F,4,0) -> MYR
B56: Gain from Sale of Assets | C56: =VLOOKUP($C$2,countries!C:F,4,0) -> MYR
B57: Other Creditors (Ratex) | C57: =VLOOKUP($C$2,countries!C:F,4,0) -> MYR
B58: Other Creditors (Legal severence & indemnity provisions) | C58: =VLOOKUP($C$2,countries!C:F,4,0) -> MYR
B59: OWC - Other Creditors (Other) | C59: =VLOOKUP($C$2,countries!C:F,4,0) -> MYR
B60: OWC - Other Debtors (Other) | C60: =VLOOKUP($C$2,countries!C:F,4,0) -> MYR
B61: OWC - Stocks | C61: =VLOOKUP($C$2,countries!C:F,4,0) -> MYR
B62: OWC - Trade Debtors | C62: =VLOOKUP($C$2,countries!C:F,4,0) -> MYR
B63: OWC - Trade Creditors | C63: =VLOOKUP($C$2,countries!C:F,4,0) -> MYR
B64: Total Cash Flow | C64: =VLOOKUP($C$2,countries!C:F,4,0) -> MYR | D64: =SUM(D50:D63) -> -1705032 | E64: =SUM(E50:E63) -> 3010969.2 | F64: =SUM(F50:F63) -> 2861121.4 | G64: =SUM(G50:G63) -> 2769909.7 | H64: =SUM(H50:H63) -> 2704758.4 | I64: =SUM(I50:I63) -> 2652637.5 | J64: =SUM(J50:J63) -> 0 | K64: =SUM(K50:K63) -> 0 | ... N64: =SUM(N50:N63) -> 0
B65: Total Cash Flow | C65: =CONCATENATE(VLOOKUP($C$2,countries!C:F,4,0),"m") -> MYRm | D65: =+D64/1000000 -> -1.705032 | E65: =+E64/1000000 -> 3.0109692 | F65: =+F64/1000000 -> 2.8611214 | G65: =+G64/1000000 -> 2.7699097 | H65: =+H64/1000000 -> 2.7047584 | I65: =+I64/1000000 -> 2.6526375 | J65: =+J64/1000000 -> 0 | K65: =+K64/1000000 -> 0 | ... N65: =+N64/1000000 -> 0
B66: Total Cash Flow | C66: $m | D66: =+D65/D12 -> -0.36200255 | E66: =+E65/E12 -> 0.66762068 | F66: =+F65/F12 -> 0.66848631 | G66: =+G65/G12 -> 0.66906031 | H66: =+H65/H12 -> 0.66949466 | I66: =+I65/I12 -> 0.66985794 | J66: =+J65/J12 -> 0 | K66: =+K65/K12 -> 0 | ... N66: =+N65/N12 -> 0
B67: Discounted Cashflow | C67: $m | D67: =+D73*D66 -> -0.34996107 | E67: =+E73*E66 -> 0.60318997 | F67: =+F73*F66 -> 0.56445987 | G67: =+G73*G66 -> 0.52798556 | H67: =+H73*H66 -> 0.49376479 | I67: =+I73*I66 -> 0.46171282 | J67: =+J73*J66 -> 0 | K67: =+K73*K66 -> 0 | ... N67: =+N73*N66 -> 0
B68: Cummulative Cashflow | C68: $m | D68: =+D67 -> -0.34996107 | E68: =+D68+E67 -> 0.2532289 | F68: =+E68+F67 -> 0.81768877 | G68: =+F68+G67 -> 1.3456743 | H68: =+G68+H67 -> 1.8394391 | I68: =+H68+I67 -> 2.3011519 | J68: =+I68+J67 -> 2.3011519 | K68: =+J68+K67 -> 2.3011519 | L68: =+K68+L67 -> 2.3011519 | ... N68: =+M68+N67 -> 2.3011519
B69: Payback - Years | C69: Years | D69: =IF(AND(D68>0,C68<0)=TRUE,D8-C68/(D68-C68),"") | E69: =IF(AND(E68>0,D68<0)=TRUE,E8-D68/(E68-D68),"") -> 1.5801838 | F69: =IF(AND(F68>0,E68<0)=TRUE,F8-E68/(F68-E68),"") | G69: =IF(AND(G68>0,F68<0)=TRUE,G8-F68/(G68-F68),"") | H69: =IF(AND(H68>0,G68<0)=TRUE,H8-G68/(H68-G68),"") | I69: =IF(AND(I68>0,H68<0)=TRUE,I8-H68/(I68-H68),"") | J69: =IF(AND(J68>0,I68<0)=TRUE,J8-I68/(J68-I68),"") | K69: =IF(AND(K68>0,J68<0)=TRUE,K8-J68/(K68-J68),"") | ... N69: =IF(AND(N68>0,M68<0)=TRUE,N8-M68/(N68-M68),"")
E70: =IF(E68<0,"n/m",ABS(D68)/E65) -> 0.11622871 | F70: =IF(F68<0,"n/m",ABS(E68)/F65) -> 0.088506869 | G70: =IF(G68<0,"n/m",ABS(F68)/G65) -> 0.29520413 | H70: =IF(H68<0,"n/m",ABS(G68)/H65) -> 0.49752108 | I70: =IF(I68<0,"n/m",ABS(H68)/I65) -> 0.69343782 | J70: =IF(J68<0,"n/m",ABS(I68)/J65) -> #DIV/0! | K70: =IF(K68<0,"n/m",ABS(J68)/K65) -> #DIV/0! | L70: =IF(L68<0,"n/m",ABS(K68)/L65) -> #DIV/0! | ... N70: =IF(N68<0,"n/m",ABS(M68)/N65) -> #DIV/0!
B72: t | D72: 0.5 | E72: 1.5 | F72: 2.5 | G72: 3.5 | H72: 4.5 | I72: 5.5 | J72: 6.5 | K72: 7.5 | L72: 8.5 | M72: 9.5 | N72: 10.5
B73: Discount factor | C73: 0.07 | D73: =1/((1+$C$73)^D72) -> 0.96673649 | E73: =1/((1+$C$73)^E72) -> 0.90349205 | F73: =1/((1+$C$73)^F72) -> 0.84438509 | G73: =1/((1+$C$73)^G72) -> 0.78914494 | H73: =1/((1+$C$73)^H72) -> 0.73751864 | I73: =1/((1+$C$73)^I72) -> 0.68926976 | J73: =1/((1+$C$73)^J72) -> 0.64417734 | K73: =1/((1+$C$73)^K72) -> 0.6020349 | ... N73: =1/((1+$C$73)^N72) -> 0.49143981
B75: NPV - in $m | C75: =SUM(D67:N67) -> 2.3011519
B76: IRR | C76: =IRR(D66:N66,0.1) -> 1.835252
B77: Payback - in Years | C77: =+E77 -> 1.5801838 | D77: =IF(E70<0,"never",COUNTIF(E68:N68,"<0")) -> 0 | E77: =IF(SUM(D69:N69)>0,SUM(D69:N69),"10+") -> 1.5801838
B78: Profitability Index | C78: =-SUM(D83:N83)/SUM(D81:N81) -> 2.2475294 | D78: =INDEX(E70:N70,,COUNTIF(E68:N68,"<0")+1) -> 0.11622871
B80: Initial Investment | D80: =(D54+D53+D39+D43+D42)/D12 -> -297459.02 | E80: =(E54+E53+E39+E43+E42)/E12 -> -392094.68 | F80: =(F54+F53+F39+F43+F42)/F12 -> -392603.07 | G80: =(G54+G53+G39+G43+G42)/G12 -> -392940.18 | H80: =(H54+H53+H39+H43+H42)/H12 -> -393195.28 | I80: =(I54+I53+I39+I43+I42)/I12 -> -393408.63 | J80: =(J54+J53+J39+J43+J42)/J12 -> 0 | K80: =(K54+K53+K39+K43+K42)/K12 -> 0 | ... N80: =(N54+N53+N39+N43+N42)/N12 -> 0
B81: Initial Investment - PV | D81: =D80*D73 -> -287564.49 | E81: =E80*E73 -> -354254.43 | F81: =F80*F73 -> -331508.18 | G81: =G80*G73 -> -310086.76 | H81: =H80*H73 -> -289988.85 | I81: =I80*I73 -> -271164.67 | J81: =J80*J73 -> 0 | K81: =K80*K73 -> 0 | ... N81: =N80*N73 -> 0
B82: NPV | D82: =D64*D73/D12 -> -349961.07 | E82: =E64*E73/E12 -> 603189.97 | F82: =F64*F73/F12 -> 564459.87 | G82: =G64*G73/G12 -> 527985.56 | H82: =H64*H73/H12 -> 493764.79 | I82: =I64*I73/I12 -> 461712.82 | J82: =J64*J73/J12 -> 0 | K82: =K64*K73/K12 -> 0 | ... N82: =N64*N73/N12 -> 0
B83: PV (excl initial investment) | D83: =D82-D81 -> -62396.58 | E83: =E82-E81 -> 957444.4 | F83: =F82-F81 -> 895968.05 | G83: =G82-G81 -> 838072.32 | H83: =H82-H81 -> 783753.64 | I83: =I82-I81 -> 732877.49 | J83: =J82-J81 -> 0 | K83: =K82-K81 -> 0 | ... N83: =N82-N81 -> 0
B91: BP Metrics ($) | D91: =D10 -> 2025 | E91: =E10 -> 2026 | F91: =F10 -> 2027 | G91: =G10 -> 2028 | H91: =H10 -> 2029 | I91: =I10 -> 2030 | J91: =J10 -> 2031 | K91: =K10 -> 2032 | ... N91: =N10 -> 2035 | O91: Total
B92: Cash Capex | D92: =D53/D12+D54/D12 -> -297459.02 | E92: =E53/E12 -> 0 | F92: =F53/F12 -> 0 | G92: =G53/G12 -> 0 | H92: =H53/H12 -> 0 | I92: =I53/I12 -> 0 | J92: =J53/J12 -> 0 | K92: =K53/K12 -> 0 | L92: =L53/L12 -> 0 | ... N92: =N53/N12 -> 0 | O92: =SUM(D92:N92) -> -297459.02
B93: Revex | D93: =D39/D12 -> 0 | E93: =E39/E12 -> 0 | F93: =F39/F12 -> 0 | G93: =G39/G12 -> 0 | H93: =H39/H12 -> 0 | I93: =I39/I12 -> 0 | J93: =J39/J12 -> 0 | K93: =K39/K12 -> 0 | ... N93: =N39/N12 -> 0 | O93: =SUM(D93:N93) -> 0
B94: Remediation | D94: =D42/D12 -> 0 | E94: =E42/E12 -> 0 | F94: =F42/F12 -> 0 | G94: =G42/G12 -> 0 | H94: =H42/H12 -> 0 | I94: =I42/I12 -> 0 | J94: =J42/J12 -> 0 | K94: =K42/K12 -> 0 | ... N94: =N42/N12 -> 0 | O94: =SUM(D94:N94) -> 0
B95: Ratex | D95: =D43/D12 -> 0 | E95: =E43/E12 -> 0 | F95: =F43/F12 -> 0 | G95: =G43/G12 -> 0 | H95: =H43/H12 -> 0 | I95: =I43/I12 -> 0 | J95: =J43/J12 -> 0 | K95: =K43/K12 -> 0 | ... N95: =N43/N12 -> 0 | O95: =SUM(D95:N95) -> 0
B96: Impairment | D96: =D41/D12 -> 0 | E96: =E41/E12 -> 0 | F96: =F41/F12 -> 0 | G96: =G41/G12 -> 0 | H96: =H41/H12 -> 0 | I96: =I41/I12 -> 0 | J96: =J41/J12 -> 0 | K96: =K41/K12 -> 0 | ... N96: =N41/N12 -> 0 | O96: =SUM(D96:N96) -> 0
B97: GM | D97: =(D24+D32+D35+D36+D30+D31)/D12*(1-37%) -> 0 | E97: =(E24+E32+E35+E36+E30+E31)/E12*(1-37%) -> 857253.08 | F97: =(F24+F32+F35+F36+F30+F31)/F12*(1-37%) -> 857253.08 | G97: =(G24+G32+G35+G36+G30+G31)/G12*(1-37%) -> 857253.08 | H97: =(H24+H32+H35+H36+H30+H31)/H12*(1-37%) -> 857253.08 | I97: =(I24+I32+I35+I36+I30+I31)/I12*(1-37%) -> 857253.08 | J97: =(J24+J32+J35+J36+J30+J31)/J12*(1-37%) -> 0 | K97: =(K24+K32+K35+K36+K30+K31)/K12*(1-37%) -> 0 | ... N97: =(N24+N32+N35+N36+N30+N31)/N12*(1-37%) -> 0 | O97: =SUM(D97:N97) -> 4286265.4
B98: TCC | D98: =(D26+D33+D34+D37+D38+D25+D27+D28+D29)/D12*(1-37%) -> -53503.185 | E98: =(E26+E33+E34+E37+E38+E25+E27+E28+E29)/E12*(1-37%) -> 0 | F98: =(F26+F33+F34+F37+F38+F25+F27+F28+F29)/F12*(1-37%) -> 0 | G98: =(G26+G33+G34+G37+G38+G25+G27+G28+G29)/G12*(1-37%) -> 0 | H98: =(H26+H33+H34+H37+H38+H25+H27+H28+H29)/H12*(1-37%) -> 0 | I98: =(I26+I33+I34+I37+I38+I25+I27+I28+I29)/I12*(1-37%) -> 0 | J98: =(J26+J33+J34+J37+J38+J25+J27+J28+J29)/J12*(1-37%) -> 0 | K98: =(K26+K33+K34+K37+K38+K25+K27+K28+K29)/K12*(1-37%) -> 0 | ... N98: =(N26+N33+N34+N37+N38+N25+N27+N28+N29)/N12*(1-37%) -> 0 | O98: =SUM(D98:N98) -> -53503.185
B99: Post tax cash flow ($m) | D99: =D64/D12 -> -362002.55 | E99: =E64/E12 -> 667620.68 | F99: =F64/F12 -> 668486.31 | G99: =G64/G12 -> 669060.31 | H99: =H64/H12 -> 669494.66 | I99: =I64/I12 -> 669857.94 | J99: =J64/J12 -> 0 | K99: =K64/K12 -> 0 | ... N99: =N64/N12 -> 0 | O99: =SUM(D99:N99) -> 2982517.4
B100: RCOP pre tax ($m) | D100: =D46/D12*(1-37%) -> -53503.185 | E100: =E46/E12*(1-37%) -> 790135.03 | F100: =F46/F12*(1-37%) -> 786528.22 | G100: =G46/G12*(1-37%) -> 784136.56 | H100: =H46/H12*(1-37%) -> 782326.75 | I100: =I46/I12*(1-37%) -> 780813.08 | J100: =J46/J12*(1-37%) -> 0 | K100: =K46/K12*(1-37%) -> 0 | ... N100: =N46/N12*(1-37%) -> 0 | O100: =SUM(D100:N100) -> 3870436.5
B101: Underlying RCOP pre tax ($m) | D101: =D100-D95-D94-D96 -> -53503.185 | E101: =E100-E95-E94-E96 -> 790135.03 | F101: =F100-F95-F94-F96 -> 786528.22 | G101: =G100-G95-G94-G96 -> 784136.56 | H101: =H100-H95-H94-H96 -> 782326.75 | I101: =I100-I95-I94-I96 -> 780813.08 | J101: =J100-J95-J94-J96 -> 0 | K101: =K100-K95-K94-K96 -> 0 | ... N101: =N100-N95-N94-N96 -> 0 | O101: =SUM(D101:N101) -> 3870436.5

Sheet NPV NTE
B2: Country | C2: ='NPV PT'!C2 -> Malaysia
B3: Cost of Capital | C3: ='NPV PT'!C3 -> 0.08 | G3: Project X
E8: 0 | F8: 1 | G8: 2 | H8: 3 | I8: 4 | J8: 5 | K8: 6 | L8: 7 | M8: 8 | N8: 9 | O8: 10
B9: Particulars | D9: NTE extra request | E9: Year 0 | F9: Year 1 | G9: Year 2 | H9: Year 3 | I9: Year 4 | J9: Year 5 | K9: Year 6 | L9: Year 7 | M9: Year 8 | N9: Year 9 | O9: Year 10
E10: ='NPV PT'!D10 -> 2025 | F10: =E10+1 -> 2026 | G10: =F10+1 -> 2027 | H10: =G10+1 -> 2028 | I10: =H10+1 -> 2029 | J10: =I10+1 -> 2030 | K10: =J10+1 -> 2031 | L10: =K10+1 -> 2032 | M10: =L10+1 -> 2033 | ... O10: =N10+1 -> 2035
B11: GIAAP
B12: FX rates | C12: =CONCATENATE(VLOOKUP($C$2,countries!C:F,4,0),"/USD") -> MYR/USD | E12: ='NPV PT'!D12 -> 4.71 | F12: ='NPV PT'!E12 -> 4.51 | G12: ='NPV PT'!F12 -> 4.28 | H12: ='NPV PT'!G12 -> 4.14 | I12: ='NPV PT'!H12 -> 4.04 | J12: ='NPV PT'!I12 -> 3.96 | K12: ='NPV PT'!J12 -> 3.91 | L12: ='NPV PT'!K12 -> 3.88 | ... O12: ='NPV PT'!N12 -> 3.83
B13: Inflation Rates | C13: % | E13: ='NPV PT'!D13 -> 0.02385 | F13: ='NPV PT'!E13 -> 0.0273 | G13: ='NPV PT'!F13 -> 0.0259 | H13: ='NPV PT'!G13 -> 0.02595 | I13: ='NPV PT'!H13 -> 0.0235 | J13: ='NPV PT'!I13 -> 0.024 | K13: ='NPV PT'!J13 -> 0.0243 | L13: ='NPV PT'!K13 -> 0.0243 | ... O13: ='NPV PT'!N13 -> 0.02355
B14: Cumm Inflation Rates | C14: % | E14: ='NPV PT'!D14 -> 0 | F14: ='NPV PT'!E14 -> 0.02385 | G14: ='NPV PT'!F14 -> 0.051801105 | H14: ='NPV PT'!G14 -> 0.079042754 | I14: ='NPV PT'!H14 -> 0.10704391 | J14: ='NPV PT'!I14 -> 0.13305945 | K14: ='NPV PT'!J14 -> 0.16025287 | L14: ='NPV PT'!K14 -> 0.18844702 | ... O14: ='NPV PT'!N14 -> 0.2762098
B15: Tax rate | C15: % | E15: ='NPV PT'!D15 -> 0.24 | F15: ='NPV PT'!E15 -> 0.24 | G15: ='NPV PT'!F15 -> 0.24 | H15: ='NPV PT'!G15 -> 0.24 | I15: ='NPV PT'!H15 -> 0.24 | J15: ='NPV PT'!I15 -> 0.24 | K15: ='NPV PT'!J15 -> 0.24 | L15: ='NPV PT'!K15 -> 0.24 | ... O15: ='NPV PT'!N15 -> 0.24
B16: Assumptions
B17: Additional Volume | C17: lt | E17: =IF($D17="",'NPV PT'!D17,'NPV PT'!D17*(1+$D17)) -> 0 | F17: =IF($D17="",'NPV PT'!E17,'NPV PT'!E17*(1+$D17)) -> 1511910.2 | G17: =IF($D17="",'NPV PT'!F17,'NPV PT'!F17*(1+$D17)) -> 1511910.2 | H17: =IF($D17="",'NPV PT'!G17,'NPV PT'!G17*(1+$D17)) -> 1511910.2 | I17: =IF($D17="",'NPV PT'!H17,'NPV PT'!H17*(1+$D17)) -> 1511910.2 | J17: =IF($D17="",'NPV PT'!I17,'NPV PT'!I17*(1+$D17)) -> 1511910.2 | K17: =IF($D17="",'NPV PT'!J17,'NPV PT'!J17*(1+$D17)) -> 0 | L17: =IF($D17="",'NPV PT'!K17,'NPV PT'!K17*(1+$D17)) -> 0 | ... O17: =IF($D17="",'NPV PT'!N17,'NPV PT'!N17*(1+$D17)) -> 0
B18: Unit Turnover | C18: =CONCATENATE(VLOOKUP($C$2,countries!C:F,4,0),"/lt") -> MYR/lt | E18: =IF($D18="",'NPV PT'!D18,'NPV PT'!D18*(1+$D18)) -> 0 | F18: =IF($D18="",'NPV PT'!E18,'NPV PT'!E18*(1+$D18)) -> 4.059 | G18: =IF($D18="",'NPV PT'!F18,'NPV PT'!F18*(1+$D18)) -> 3.852 | H18: =IF($D18="",'NPV PT'!G18,'NPV PT'!G18*(1+$D18)) -> 3.726 | I18: =IF($D18="",'NPV PT'!H18,'NPV PT'!H18*(1+$D18)) -> 3.636 | J18: =IF($D18="",'NPV PT'!I18,'NPV PT'!I18*(1+$D18)) -> 3.564 | K18: =IF($D18="",'NPV PT'!J18,'NPV PT'!J18*(1+$D18)) -> 0 | L18: =IF($D18="",'NPV PT'!K18,'NPV PT'!K18*(1+$D18)) -> 0 | ... O18: =IF($D18="",'NPV PT'!N18,'NPV PT'!N18*(1+$D18)) -> 0
B19: Unit COGS | C19: =CONCATENATE(VLOOKUP($C$2,countries!C:F,4,0),"/lt") -> MYR/lt | E19: =IF($D19="",'NPV PT'!D19,'NPV PT'!D19*(1+$D19)) -> 0 | F19: =IF($D19="",'NPV PT'!E19,'NPV PT'!E19*(1+$D19)) -> 0 | G19: =IF($D19="",'NPV PT'!F19,'NPV PT'!F19*(1+$D19)) -> 0 | H19: =IF($D19="",'NPV PT'!G19,'NPV PT'!G19*(1+$D19)) -> 0 | I19: =IF($D19="",'NPV PT'!H19,'NPV PT'!H19*(1+$D19)) -> 0 | J19: =IF($D19="",'NPV PT'!I19,'NPV PT'!I19*(1+$D19)) -> 0 | K19: =IF($D19="",'NPV PT'!J19,'NPV PT'!J19*(1+$D19)) -> 0 | L19: =IF($D19="",'NPV PT'!K19,'NPV PT'!K19*(1+$D19)) -> 0 | ... O19: =IF($D19="",'NPV PT'!N19,'NPV PT'!N19*(1+$D19)) -> 0
B20: Unit Margin | C20: =CONCATENATE(VLOOKUP($C$2,countries!C:F,4,0),"/lt") -> MYR/lt | E20: =IF($D20="",'NPV PT'!D20,'NPV PT'!D20*(1+$D20)) -> 0 | F20: =IF($D20="",'NPV PT'!E20,'NPV PT'!E20*(1+$D20)) -> 4.059 | G20: =IF($D20="",'NPV PT'!F20,'NPV PT'!F20*(1+$D20)) -> 3.852 | H20: =IF($D20="",'NPV PT'!G20,'NPV PT'!G20*(1+$D20)) -> 3.726 | I20: =IF($D20="",'NPV PT'!H20,'NPV PT'!H20*(1+$D20)) -> 3.636 | J20: =IF($D20="",'NPV PT'!I20,'NPV PT'!I20*(1+$D20)) -> 3.564 | K20: =IF($D20="",'NPV PT'!J20,'NPV PT'!J20*(1+$D20)) -> 0 | L20: =IF($D20="",'NPV PT'!K20,'NPV PT'!K20*(1+$D20)) -> 0 | ... O20: =IF($D20="",'NPV PT'!N20,'NPV PT'!N20*(1+$D20)) -> 0
B21: Sales Turnover | C21: =VLOOKUP($C$2,countries!C:F,4,0) -> MYR | E21: =IF($D21="",'NPV PT'!D21,'NPV PT'!D21*(1+$D21)) -> 0 | F21: =IF($D21="",'NPV PT'!E21,'NPV PT'!E21*(1+$D21)) -> 6136843.5 | G21: =IF($D21="",'NPV PT'!F21,'NPV PT'!F21*(1+$D21)) -> 5823878.1 | H21: =IF($D21="",'NPV PT'!G21,'NPV PT'!G21*(1+$D21)) -> 5633377.4 | I21: =IF($D21="",'NPV PT'!H21,'NPV PT'!H21*(1+$D21)) -> 5497305.5 | J21: =IF($D21="",'NPV PT'!I21,'NPV PT'!I21*(1+$D21)) -> 5388448 | K21: =IF($D21="",'NPV PT'!J21,'NPV PT'!J21*(1+$D21)) -> 0 | L21: =IF($D21="",'NPV PT'!K21,'NPV PT'!K21*(1+$D21)) -> 0 | ... O21: =IF($D21="",'NPV PT'!N21,'NPV PT'!N21*(1+$D21)) -> 0
B22: COGS | C22: =VLOOKUP($C$2,countries!C:F,4,0) -> MYR | E22: =IF($D22="",'NPV PT'!D22,'NPV PT'!D22*(1+$D22)) -> 0 | F22: =IF($D22="",'NPV PT'!E22,'NPV PT'!E22*(1+$D22)) -> 0 | G22: =IF($D22="",'NPV PT'!F22,'NPV PT'!F22*(1+$D22)) -> 0 | H22: =IF($D22="",'NPV PT'!G22,'NPV PT'!G22*(1+$D22)) -> 0 | I22: =IF($D22="",'NPV PT'!H22,'NPV PT'!H22*(1+$D22)) -> 0 | J22: =IF($D22="",'NPV PT'!I22,'NPV PT'!I22*(1+$D22)) -> 0 | K22: =IF($D22="",'NPV PT'!J22,'NPV PT'!J22*(1+$D22)) -> 0 | L22: =IF($D22="",'NPV PT'!K22,'NPV PT'!K22*(1+$D22)) -> 0 | ... O22: =IF($D22="",'NPV PT'!N22,'NPV PT'!N22*(1+$D22)) -> 0
B23: Profit and Loss
B24: Topline Growth (GM - Additional volume profit) | C24: =VLOOKUP($C$2,countries!C:F,4,0) -> MYR | E24: =E20*E17 -> 0 | F24: =F20*F17 -> 6136843.5 | G24: =G20*G17 -> 5823878.1 | H24: =H20*H17 -> 5633377.4 | I24: =I20*I17 -> 5497305.5 | J24: =J20*J17 -> 5388448 | K24: =K20*K17 -> 0 | L24: =L20*L17 -> 0 | ... O24: =O20*O17 -> 0
B25: Secondary Logs Refund/Rebate (for Indirect channel) | C25: =VLOOKUP($C$2,countries!C:F,4,0) -> MYR | E25: =IF($D25="",'NPV PT'!D25,'NPV PT'!D25*(1+$D25)) -> 0 | F25: =IF($D25="",'NPV PT'!E25,'NPV PT'!E25*(1+$D25)) -> 0 | G25: =IF($D25="",'NPV PT'!F25,'NPV PT'!F25*(1+$D25)) -> 0 | H25: =IF($D25="",'NPV PT'!G25,'NPV PT'!G25*(1+$D25)) -> 0 | I25: =IF($D25="",'NPV PT'!H25,'NPV PT'!H25*(1+$D25)) -> 0 | J25: =IF($D25="",'NPV PT'!I25,'NPV PT'!I25*(1+$D25)) -> 0 | K25: =IF($D25="",'NPV PT'!J25,'NPV PT'!J25*(1+$D25)) -> 0 | L25: =IF($D25="",'NPV PT'!K25,'NPV PT'!K25*(1+$D25)) -> 0 | ... O25: =IF($D25="",'NPV PT'!N25,'NPV PT'!N25*(1+$D25)) -> 0
B26: Additional Volume Sec Distribution (TCC) | C26: =VLOOKUP($C$2,countries!C:F,4,0) -> MYR | E26: =IF($D26="",'NPV PT'!D26,'NPV PT'!D26*(1+$D26)) -> 0 | F26: =IF($D26="",'NPV PT'!E26,'NPV PT'!E26*(1+$D26)) -> 0 | G26: =IF($D26="",'NPV PT'!F26,'NPV PT'!F26*(1+$D26)) -> 0 | H26: =IF($D26="",'NPV PT'!G26,'NPV PT'!G26*(1+$D26)) -> 0 | I26: =IF($D26="",'NPV PT'!H26,'NPV PT'!H26*(1+$D26)) -> 0 | J26: =IF($D26="",'NPV PT'!I26,'NPV PT'!I26*(1+$D26)) -> 0 | K26: =IF($D26="",'NPV PT'!J26,'NPV PT'!J26*(1+$D26)) -> 0 | L26: =IF($D26="",'NPV PT'!K26,'NPV PT'!K26*(1+$D26)) -> 0 | ... O26: =IF($D26="",'NPV PT'!N26,'NPV PT'!N26*(1+$D26)) -> 0
B27: CFC (TCC) | C27: =VLOOKUP($C$2,countries!C:F,4,0) -> MYR | E27: =IF($D27="",'NPV PT'!D27,'NPV PT'!D27*(1+$D27)) -> 0 | F27: =IF($D27="",'NPV PT'!E27,'NPV PT'!E27*(1+$D27)) -> 0 | G27: =IF($D27="",'NPV PT'!F27,'NPV PT'!F27*(1+$D27)) -> 0 | H27: =IF($D27="",'NPV PT'!G27,'NPV PT'!G27*(1+$D27)) -> 0 | I27: =IF($D27="",'NPV PT'!H27,'NPV PT'!H27*(1+$D27)) -> 0 | J27: =IF($D27="",'NPV PT'!I27,'NPV PT'!I27*(1+$D27)) -> 0 | K27: =IF($D27="",'NPV PT'!J27,'NPV PT'!J27*(1+$D27)) -> 0 | L27: =IF($D27="",'NPV PT'!K27,'NPV PT'!K27*(1+$D27)) -> 0 | ... O27: =IF($D27="",'NPV PT'!N27,'NPV PT'!N27*(1+$D27)) -> 0
B28: Marketing costs (TCC) | C28: =VLOOKUP($C$2,countries!C:F,4,0) -> MYR | E28: =IF($D28="",'NPV PT'!D28,'NPV PT'!D28*(1+$D28)) -> -400000 | F28: =IF($D28="",'NPV PT'!E28,'NPV PT'!E28*(1+$D28)) -> 0 | G28: =IF($D28="",'NPV PT'!F28,'NPV PT'!F28*(1+$D28)) -> 0 | H28: =IF($D28="",'NPV PT'!G28,'NPV PT'!G28*(1+$D28)) -> 0 | I28: =IF($D28="",'NPV PT'!H28,'NPV PT'!H28*(1+$D28)) -> 0 | J28: =IF($D28="",'NPV PT'!I28,'NPV PT'!I28*(1+$D28)) -> 0 | K28: =IF($D28="",'NPV PT'!J28,'NPV PT'!J28*(1+$D28)) -> 0 | L28: =IF($D28="",'NPV PT'!K28,'NPV PT'!K28*(1+$D28)) -> 0 | ... O28: =IF($D28="",'NPV PT'!N28,'NPV PT'!N28*(1+$D28)) -> 0
B29: ASP | C29: =VLOOKUP($C$2,countries!C:F,4,0) -> MYR | E29: =IF($D29="",'NPV PT'!D29,'NPV PT'!D29*(1+$D29)) -> 0 | F29: =IF($D29="",'NPV PT'!E29,'NPV PT'!E29*(1+$D29)) -> 0 | G29: =IF($D29="",'NPV PT'!F29,'NPV PT'!F29*(1+$D29)) -> 0 | H29: =IF($D29="",'NPV PT'!G29,'NPV PT'!G29*(1+$D29)) -> 0 | I29: =IF($D29="",'NPV PT'!H29,'NPV PT'!H29*(1+$D29)) -> 0 | J29: =IF($D29="",'NPV PT'!I29,'NPV PT'!I29*(1+$D29)) -> 0 | K29: =IF($D29="",'NPV PT'!J29,'NPV PT'!J29*(1+$D29)) -> 0 | L29: =IF($D29="",'NPV PT'!K29,'NPV PT'!K29*(1+$D29)) -> 0 | ... O29: =IF($D29="",'NPV PT'!N29,'NPV PT'!N29*(1+$D29)) -> 0
B30: Write-offs (COGS - GM) | C30: =VLOOKUP($C$2,countries!C:F,4,0) -> MYR | E30: =IF($D30="",'NPV PT'!D30,'NPV PT'!D30*(1+$D30)) -> 0 | F30: =IF($D30="",'NPV PT'!E30,'NPV PT'!E30*(1+$D30)) -> 0 | G30: =IF($D30="",'NPV PT'!F30,'NPV PT'!F30*(1+$D30)) -> 0 | H30: =IF($D30="",'NPV PT'!G30,'NPV PT'!G30*(1+$D30)) -> 0 | I30: =IF($D30="",'NPV PT'!H30,'NPV PT'!H30*(1+$D30)) -> 0 | J30: =IF($D30="",'NPV PT'!I30,'NPV PT'!I30*(1+$D30)) -> 0 | K30: =IF($D30="",'NPV PT'!J30,'NPV PT'!J30*(1+$D30)) -> 0 | L30: =IF($D30="",'NPV PT'!K30,'NPV PT'!K30*(1+$D30)) -> 0 | ... O30: =IF($D30="",'NPV PT'!N30,'NPV PT'!N30*(1+$D30)) -> 0
B31: Other Income | C31: =VLOOKUP($C$2,countries!C:F,4,0) -> MYR | E31: =IF($D31="",'NPV PT'!D31,'NPV PT'!D31*(1+$D31)) -> 0 | F31: =IF($D31="",'NPV PT'!E31,'NPV PT'!E31*(1+$D31)) -> 0 | G31: =IF($D31="",'NPV PT'!F31,'NPV PT'!F31*(1+$D31)) -> 0 | H31: =IF($D31="",'NPV PT'!G31,'NPV PT'!G31*(1+$D31)) -> 0 | I31: =IF($D31="",'NPV PT'!H31,'NPV PT'!H31*(1+$D31)) -> 0 | J31: =IF($D31="",'NPV PT'!I31,'NPV PT'!I31*(1+$D31)) -> 0 | K31: =IF($D31="",'NPV PT'!J31,'NPV PT'!J31*(1+$D31)) -> 0 | L31: =IF($D31="",'NPV PT'!K31,'NPV PT'!K31*(1+$D31)) -> 0 | ... O31: =IF($D31="",'NPV PT'!N31,'NPV PT'!N31*(1+$D31)) -> 0
B32: GSC Savings/Costs (GM) - RM COGS | C32: =VLOOKUP($C$2,countries!C:F,4,0) -> MYR | E32: =IF($D32="",'NPV PT'!D32,'NPV PT'!D32*(1+$D32)) -> 0 | F32: =IF($D32="",'NPV PT'!E32,'NPV PT'!E32*(1+$D32)) -> 0 | G32: =IF($D32="",'NPV PT'!F32,'NPV PT'!F32*(1+$D32)) -> 0 | H32: =IF($D32="",'NPV PT'!G32,'NPV PT'!G32*(1+$D32)) -> 0 | I32: =IF($D32="",'NPV PT'!H32,'NPV PT'!H32*(1+$D32)) -> 0 | J32: =IF($D32="",'NPV PT'!I32,'NPV PT'!I32*(1+$D32)) -> 0 | K32: =IF($D32="",'NPV PT'!J32,'NPV PT'!J32*(1+$D32)) -> 0 | L32: =IF($D32="",'NPV PT'!K32,'NPV PT'!K32*(1+$D32)) -> 0 | ... O32: =IF($D32="",'NPV PT'!N32,'NPV PT'!N32*(1+$D32)) -> 0
B33: GSC Savings/Costs (TCC) - Manufacturing | C33: =VLOOKUP($C$2,countries!C:F,4,0) -> MYR | E33: =IF($D33="",'NPV PT'!D33,'NPV PT'!D33*(1+$D33)) -> 0 | F33: =IF($D33="",'NPV PT'!E33,'NPV PT'!E33*(1+$D33)) -> 0 | G33: =IF($D33="",'NPV PT'!F33,'NPV PT'!F33*(1+$D33)) -> 0 | H33: =IF($D33="",'NPV PT'!G33,'NPV PT'!G33*(1+$D33)) -> 0 | I33: =IF($D33="",'NPV PT'!H33,'NPV PT'!H33*(1+$D33)) -> 0 | J33: =IF($D33="",'NPV PT'!I33,'NPV PT'!I33*(1+$D33)) -> 0 | K33: =IF($D33="",'NPV PT'!J33,'NPV PT'!J33*(1+$D33)) -> 0 | L33: =IF($D33="",'NPV PT'!K33,'NPV PT'!K33*(1+$D33)) -> 0 | ... O33: =IF($D33="",'NPV PT'!N33,'NPV PT'!N33*(1+$D33)) -> 0
B34: GSC Savings/Costs (TCC) - BU Support | C34: =VLOOKUP($C$2,countries!C:F,4,0) -> MYR | E34: =IF($D34="",'NPV PT'!D34,'NPV PT'!D34*(1+$D34)) -> 0 | F34: =IF($D34="",'NPV PT'!E34,'NPV PT'!E34*(1+$D34)) -> 0 | G34: =IF($D34="",'NPV PT'!F34,'NPV PT'!F34*(1+$D34)) -> 0 | H34: =IF($D34="",'NPV PT'!G34,'NPV PT'!G34*(1+$D34)) -> 0 | I34: =IF($D34="",'NPV PT'!H34,'NPV PT'!H34*(1+$D34)) -> 0 | J34: =IF($D34="",'NPV PT'!I34,'NPV PT'!I34*(1+$D34)) -> 0 | K34: =IF($D34="",'NPV PT'!J34,'NPV PT'!J34*(1+$D34)) -> 0 | L34: =IF($D34="",'NPV PT'!K34,'NPV PT'!K34*(1+$D34)) -> 0 | ... O34: =IF($D34="",'NPV PT'!N34,'NPV PT'!N34*(1+$D34)) -> 0
B35: GSC Savings/Costs (ACC) - Primary Logistics | C35: =VLOOKUP($C$2,countries!C:F,4,0) -> MYR | E35: =IF($D35="",'NPV PT'!D35,'NPV PT'!D35*(1+$D35)) -> 0 | F35: =IF($D35="",'NPV PT'!E35,'NPV PT'!E35*(1+$D35)) -> 0 | G35: =IF($D35="",'NPV PT'!F35,'NPV PT'!F35*(1+$D35)) -> 0 | H35: =IF($D35="",'NPV PT'!G35,'NPV PT'!G35*(1+$D35)) -> 0 | I35: =IF($D35="",'NPV PT'!H35,'NPV PT'!H35*(1+$D35)) -> 0 | J35: =IF($D35="",'NPV PT'!I35,'NPV PT'!I35*(1+$D35)) -> 0 | K35: =IF($D35="",'NPV PT'!J35,'NPV PT'!J35*(1+$D35)) -> 0 | L35: =IF($D35="",'NPV PT'!K35,'NPV PT'!K35*(1+$D35)) -> 0 | ... O35: =IF($D35="",'NPV PT'!N35,'NPV PT'!N35*(1+$D35)) -> 0
B36: GSC Savings/Costs (ACC) - S&H | C36: =VLOOKUP($C$2,countries!C:F,4,0) -> MYR | E36: =IF($D36="",'NPV PT'!D36,'NPV PT'!D36*(1+$D36)) -> 0 | F36: =IF($D36="",'NPV PT'!E36,'NPV PT'!E36*(1+$D36)) -> 0 | G36: =IF($D36="",'NPV PT'!F36,'NPV PT'!F36*(1+$D36)) -> 0 | H36: =IF($D36="",'NPV PT'!G36,'NPV PT'!G36*(1+$D36)) -> 0 | I36: =IF($D36="",'NPV PT'!H36,'NPV PT'!H36*(1+$D36)) -> 0 | J36: =IF($D36="",'NPV PT'!I36,'NPV PT'!I36*(1+$D36)) -> 0 | K36: =IF($D36="",'NPV PT'!J36,'NPV PT'!J36*(1+$D36)) -> 0 | L36: =IF($D36="",'NPV PT'!K36,'NPV PT'!K36*(1+$D36)) -> 0 | ... O36: =IF($D36="",'NPV PT'!N36,'NPV PT'!N36*(1+$D36)) -> 0
... B38: GBS cost savings (TCC) | C38: =VLOOKUP($C$2,countries!C:F,4,0) -> MYR | E38: =IF($D38="",'NPV PT'!D38,'NPV PT'!D38*(1+$D38)) -> 0 | F38: =IF($D38="",'NPV PT'!E38,'NPV PT'!E38*(1+$D38)) -> 0 | G38: =IF($D38="",'NPV PT'!F38,'NPV PT'!F38*(1+$D38)) -> 0 | H38: =IF($D38="",'NPV PT'!G38,'NPV PT'!G38*(1+$D38)) -> 0 | I38: =IF($D38="",'NPV PT'!H38,'NPV PT'!H38*(1+$D38)) -> 0 | J38: =IF($D38="",'NPV PT'!I38,'NPV PT'!I38*(1+$D38)) -> 0 | K38: =IF($D38="",'NPV PT'!J38,'NPV PT'!J38*(1+$D38)) -> 0 | L38: =IF($D38="",'NPV PT'!K38,'NPV PT'!K38*(1+$D38)) -> 0 | ... O38: =IF($D38="",'NPV PT'!N38,'NPV PT'!N38*(1+$D38)) -> 0
B39: Project Revex (Implementation costs) | C39: =VLOOKUP($C$2,countries!C:F,4,0) -> MYR | D39: 0.1 | E39: =IF($D39="",'NPV PT'!D39,'NPV PT'!D39*(1+$D39)) -> 0 | F39: =IF($D39="",'NPV PT'!E39,'NPV PT'!E39*(1+$D39)) -> 0 | G39: =IF($D39="",'NPV PT'!F39,'NPV PT'!F39*(1+$D39)) -> 0 | H39: =IF($D39="",'NPV PT'!G39,'NPV PT'!G39*(1+$D39)) -> 0 | I39: =IF($D39="",'NPV PT'!H39,'NPV PT'!H39*(1+$D39)) -> 0 | J39: =IF($D39="",'NPV PT'!I39,'NPV PT'!I39*(1+$D39)) -> 0 | K39: =IF($D39="",'NPV PT'!J39,'NPV PT'!J39*(1+$D39)) -> 0 | L39: =IF($D39="",'NPV PT'!K39,'NPV PT'!K39*(1+$D39)) -> 0 | ... O39: =IF($D39="",'NPV PT'!N39,'NPV PT'!N39*(1+$D39)) -> 0
B40: Depreciation | C40: =VLOOKUP($C$2,countries!C:F,4,0) -> MYR | E40: =SUM('Capex&Depr'!F54:F63) -> 0 | F40: =SUM('Capex&Depr'!G54:G63) -> -498960 | G40: =SUM('Capex&Depr'!H54:H63) -> -498960 | H40: =SUM('Capex&Depr'!I54:I63) -> -498960 | I40: =SUM('Capex&Depr'!J54:J63) -> -498960 | J40: =SUM('Capex&Depr'!K54:K63) -> -498960 | K40: =SUM('Capex&Depr'!L54:L63) -> 0 | L40: =SUM('Capex&Depr'!M54:M63) -> 0 | ... O40: =SUM('Capex&Depr'!P54:P63) -> 0
B41: Impairment | C41: =VLOOKUP($C$2,countries!C:F,4,0) -> MYR | E41: =IF($D41="",'NPV PT'!D41,'NPV PT'!D41*(1+$D41)) -> 0 | F41: =IF($D41="",'NPV PT'!E41,'NPV PT'!E41*(1+$D41)) -> 0 | G41: =IF($D41="",'NPV PT'!F41,'NPV PT'!F41*(1+$D41)) -> 0 | H41: =IF($D41="",'NPV PT'!G41,'NPV PT'!G41*(1+$D41)) -> 0 | I41: =IF($D41="",'NPV PT'!H41,'NPV PT'!H41*(1+$D41)) -> 0 | J41: =IF($D41="",'NPV PT'!I41,'NPV PT'!I41*(1+$D41)) -> 0 | K41: =IF($D41="",'NPV PT'!J41,'NPV PT'!J41*(1+$D41)) -> 0 | L41: =IF($D41="",'NPV PT'!K41,'NPV PT'!K41*(1+$D41)) -> 0 | ... O41: =IF($D41="",'NPV PT'!N41,'NPV PT'!N41*(1+$D41)) -> 0
B42: Remediation & Dismantling Costs | C42: =VLOOKUP($C$2,countries!C:F,4,0) -> MYR | D42: 0.1 | E42: =IF($D42="",'NPV PT'!D42,'NPV PT'!D42*(1+$D42)) -> 0 | F42: =IF($D42="",'NPV PT'!E42,'NPV PT'!E42*(1+$D42)) -> 0 | G42: =IF($D42="",'NPV PT'!F42,'NPV PT'!F42*(1+$D42)) -> 0 | H42: =IF($D42="",'NPV PT'!G42,'NPV PT'!G42*(1+$D42)) -> 0 | I42: =IF($D42="",'NPV PT'!H42,'NPV PT'!H42*(1+$D42)) -> 0 | J42: =IF($D42="",'NPV PT'!I42,'NPV PT'!I42*(1+$D42)) -> 0 | K42: =IF($D42="",'NPV PT'!J42,'NPV PT'!J42*(1+$D42)) -> 0 | L42: =IF($D42="",'NPV PT'!K42,'NPV PT'!K42*(1+$D42)) -> 0 | ... O42: =IF($D42="",'NPV PT'!N42,'NPV PT'!N42*(1+$D42)) -> 0
B43: Ratex accrued | C43: =VLOOKUP($C$2,countries!C:F,4,0) -> MYR | D43: 0.1 | E43: =IF($D43="",'NPV PT'!D43,'NPV PT'!D43*(1+$D43)) -> 0 | F43: =IF($D43="",'NPV PT'!E43,'NPV PT'!E43*(1+$D43)) -> 0 | G43: =IF($D43="",'NPV PT'!F43,'NPV PT'!F43*(1+$D43)) -> 0 | H43: =IF($D43="",'NPV PT'!G43,'NPV PT'!G43*(1+$D43)) -> 0 | I43: =IF($D43="",'NPV PT'!H43,'NPV PT'!H43*(1+$D43)) -> 0 | J43: =IF($D43="",'NPV PT'!I43,'NPV PT'!I43*(1+$D43)) -> 0 | K43: =IF($D43="",'NPV PT'!J43,'NPV PT'!J43*(1+$D43)) -> 0 | L43: =IF($D43="",'NPV PT'!K43,'NPV PT'!K43*(1+$D43)) -> 0 | ... O43: =IF($D43="",'NPV PT'!N43,'NPV PT'!N43*(1+$D43)) -> 0
B44: Net Profit | C44: =VLOOKUP($C$2,countries!C:F,4,0) -> MYR | E44: =SUM(E23:E43) -> -400000 | F44: =SUM(F23:F43) -> 5637883.5 | G44: =SUM(G23:G43) -> 5324918.1 | H44: =SUM(H23:H43) -> 5134417.4 | I44: =SUM(I23:I43) -> 4998345.5 | J44: =SUM(J23:J43) -> 4889488 | K44: =SUM(K23:K43) -> 0 | L44: =SUM(L23:L43) -> 0 | ... O44: =SUM(O23:O43) -> 0
B45: Interest | C45: =VLOOKUP($C$2,countries!C:F,4,0) -> MYR | E45: 0 | F45: 0 | G45: 0 | H45: 0 | I45: 0 | J45: 0 | K45: 0 | L45: 0 | M45: 0 | N45: 0 | O45: 0
B46: Net Profit After interest | C46: =VLOOKUP($C$2,countries!C:F,4,0) -> MYR | E46: =+E45+E44 -> -400000 | F46: =SUM(F44:F45) -> 5637883.5 | G46: =SUM(G44:G45) -> 5324918.1 | H46: =SUM(H44:H45) -> 5134417.4 | I46: =SUM(I44:I45) -> 4998345.5 | J46: =SUM(J44:J45) -> 4889488 | K46: =SUM(K44:K45) -> 0 | L46: =SUM(L44:L45) -> 0 | M46: =SUM(M44:M45) -> 0 | ... O46: =SUM(O44:O45) -> 0
B47: Tax | C47: =VLOOKUP($C$2,countries!C:F,4,0) -> MYR | E47: =-E15*(E46+E57) -> 96000 | F47: =-F15*(F46+F57) -> -1353092 | G47: =-G15*(G46+G57) -> -1277980.3 | H47: =-H15*(H46+H57) -> -1232260.2 | I47: =-I15*(I46+I57) -> -1199602.9 | J47: =-J15*(J46+J57) -> -1173477.1 | K47: =-K15*(K46+K57) -> 0 | L47: =-L15*(L46+L57) -> 0 | ... O47: =-O15*(O46+O57) -> 0
B48: Net profit after tax | C48: =VLOOKUP($C$2,countries!C:F,4,0) -> MYR | E48: =+E47+E46 -> -304000 | F48: =SUM(F46:F47) -> 4284791.5 | G48: =SUM(G46:G47) -> 4046937.7 | H48: =SUM(H46:H47) -> 3902157.2 | I48: =SUM(I46:I47) -> 3798742.6 | J48: =SUM(J46:J47) -> 3716010.8 | K48: =SUM(K46:K47) -> 0 | L48: =SUM(L46:L47) -> 0 | M48: =SUM(M46:M47) -> 0 | ... O48: =SUM(O46:O47) -> 0
B49: Cashflow
B50: Net profit Before tax | C50: =VLOOKUP($C$2,countries!C:F,4,0) -> MYR | E50: =E46 -> -400000 | F50: =F46 -> 5637883.5 | G50: =G46 -> 5324918.1 | H50: =H46 -> 5134417.4 | I50: =I46 -> 4998345.5 | J50: =J46 -> 4889488 | K50: =K46 -> 0 | L50: =L46 -> 0 | ... O50: =O46 -> 0
B51: Add: Depreciation | C51: =VLOOKUP($C$2,countries!C:F,4,0) -> MYR | E51: =-E40-E41 -> 0 | F51: =-F40-F41 -> 498960 | G51: =-G40-G41 -> 498960 | H51: =-H40-H41 -> 498960 | I51: =-I40-I41 -> 498960 | J51: =-J40-J41 -> 498960 | K51: =-K40-K41 -> 0 | L51: =-L40-L41 -> 0 | ... O51: =-O40-O41 -> 0
B52: Less: Cash taxes | C52: =VLOOKUP($C$2,countries!C:F,4,0) -> MYR | E52: =E47 -> 96000 | F52: =F47 -> -1353092 | G52: =G47 -> -1277980.3 | H52: =H47 -> -1232260.2 | I52: =I47 -> -1199602.9 | J52: =J47 -> -1173477.1 | K52: =K47 -> 0 | L52: =L47 -> 0 | ... O52: =O47 -> 0
B53: Capex accrued | C53: =VLOOKUP($C$2,countries!C:F,4,0) -> MYR | D53: Capex&Depr sheet | E53: =SUM('Capex&Depr'!F38:F47) -> -2494800 | F53: =SUM('Capex&Depr'!G38:G47) -> 0 | G53: =SUM('Capex&Depr'!H38:H47) -> 0 | H53: =SUM('Capex&Depr'!I38:I47) -> 0 | I53: =SUM('Capex&Depr'!J38:J47) -> 0 | J53: =SUM('Capex&Depr'!K38:K47) -> 0 | K53: =SUM('Capex&Depr'!L38:L47) -> 0 | L53: =SUM('Capex&Depr'!M38:M47) -> 0 | ... O53: =SUM('Capex&Depr'!P38:P47) -> 0
B54: JV Interest @ 37% | C54: =VLOOKUP($C$2,countries!C:F,4,0) -> MYR | E54: =-0.37*SUM(E50:E53) -> 1035556 | F54: =-0.37*SUM(F50:F53) -> -1769988 | G54: =-0.37*SUM(G50:G53) -> -1681982.2 | H54: =-0.37*SUM(H50:H53) -> -1628413.4 | I54: =-0.37*SUM(I50:I53) -> -1590150 | J54: =-0.37*SUM(J50:J53) -> -1559539.2 | K54: =-0.37*SUM(K50:K53) -> 0 | L54: =-0.37*SUM(L50:L53) -> 0 | ... O54: =-0.37*SUM(O50:O53) -> 0
B55: Withholding Tax | C55: =VLOOKUP($C$2,countries!C:F,4,0) -> MYR
B56: Gain from Sale of Assets | C56: =VLOOKUP($C$2,countries!C:F,4,0) -> MYR | E56: =IF($D56="",'NPV PT'!D56,'NPV PT'!D56*(1+$D56)) -> 0 | F56: =IF($D56="",'NPV PT'!E56,'NPV PT'!E56*(1+$D56)) -> 0 | G56: =IF($D56="",'NPV PT'!F56,'NPV PT'!F56*(1+$D56)) -> 0 | H56: =IF($D56="",'NPV PT'!G56,'NPV PT'!G56*(1+$D56)) -> 0 | I56: =IF($D56="",'NPV PT'!H56,'NPV PT'!H56*(1+$D56)) -> 0 | J56: =IF($D56="",'NPV PT'!I56,'NPV PT'!I56*(1+$D56)) -> 0 | K56: =IF($D56="",'NPV PT'!J56,'NPV PT'!J56*(1+$D56)) -> 0 | L56: =IF($D56="",'NPV PT'!K56,'NPV PT'!K56*(1+$D56)) -> 0 | ... O56: =IF($D56="",'NPV PT'!N56,'NPV PT'!N56*(1+$D56)) -> 0
B57: Other Creditors (Ratex) | C57: =VLOOKUP($C$2,countries!C:F,4,0) -> MYR
B58: Other Creditors (Legal severence & indemnity provisions) | C58: =VLOOKUP($C$2,countries!C:F,4,0) -> MYR | E58: =IF($D58="",'NPV PT'!D58,'NPV PT'!D58*(1+$D58)) -> 0 | F58: =IF($D58="",'NPV PT'!E58,'NPV PT'!E58*(1+$D58)) -> 0 | G58: =IF($D58="",'NPV PT'!F58,'NPV PT'!F58*(1+$D58)) -> 0 | H58: =IF($D58="",'NPV PT'!G58,'NPV PT'!G58*(1+$D58)) -> 0 | I58: =IF($D58="",'NPV PT'!H58,'NPV PT'!H58*(1+$D58)) -> 0 | J58: =IF($D58="",'NPV PT'!I58,'NPV PT'!I58*(1+$D58)) -> 0 | K58: =IF($D58="",'NPV PT'!J58,'NPV PT'!J58*(1+$D58)) -> 0 | L58: =IF($D58="",'NPV PT'!K58,'NPV PT'!K58*(1+$D58)) -> 0 | ... O58: =IF($D58="",'NPV PT'!N58,'NPV PT'!N58*(1+$D58)) -> 0
B59: OWC - Other Creditors (Other) | C59: =VLOOKUP($C$2,countries!C:F,4,0) -> MYR | E59: =IF($D59="",'NPV PT'!D59,'NPV PT'!D59*(1+$D59)) -> 0 | F59: =IF($D59="",'NPV PT'!E59,'NPV PT'!E59*(1+$D59)) -> 0 | G59: =IF($D59="",'NPV PT'!F59,'NPV PT'!F59*(1+$D59)) -> 0 | H59: =IF($D59="",'NPV PT'!G59,'NPV PT'!G59*(1+$D59)) -> 0 | I59: =IF($D59="",'NPV PT'!H59,'NPV PT'!H59*(1+$D59)) -> 0 | J59: =IF($D59="",'NPV PT'!I59,'NPV PT'!I59*(1+$D59)) -> 0 | K59: =IF($D59="",'NPV PT'!J59,'NPV PT'!J59*(1+$D59)) -> 0 | L59: =IF($D59="",'NPV PT'!K59,'NPV PT'!K59*(1+$D59)) -> 0 | ... O59: =IF($D59="",'NPV PT'!N59,'NPV PT'!N59*(1+$D59)) -> 0
B60: OWC - Other Debtors (Other) | C60: =VLOOKUP($C$2,countries!C:F,4,0) -> MYR | E60: =IF($D60="",'NPV PT'!D60,'NPV PT'!D60*(1+$D60)) -> 0 | F60: =IF($D60="",'NPV PT'!E60,'NPV PT'!E60*(1+$D60)) -> 0 | G60: =IF($D60="",'NPV PT'!F60,'NPV PT'!F60*(1+$D60)) -> 0 | H60: =IF($D60="",'NPV PT'!G60,'NPV PT'!G60*(1+$D60)) -> 0 | I60: =IF($D60="",'NPV PT'!H60,'NPV PT'!H60*(1+$D60)) -> 0 | J60: =IF($D60="",'NPV PT'!I60,'NPV PT'!I60*(1+$D60)) -> 0 | K60: =IF($D60="",'NPV PT'!J60,'NPV PT'!J60*(1+$D60)) -> 0 | L60: =IF($D60="",'NPV PT'!K60,'NPV PT'!K60*(1+$D60)) -> 0 | ... O60: =IF($D60="",'NPV PT'!N60,'NPV PT'!N60*(1+$D60)) -> 0
B61: OWC - Stocks | C61: =VLOOKUP($C$2,countries!C:F,4,0) -> MYR | E61: =IF($D61="",'NPV PT'!D61,'NPV PT'!D61*(1+$D61)) -> 0 | F61: =IF($D61="",'NPV PT'!E61,'NPV PT'!E61*(1+$D61)) -> 0 | G61: =IF($D61="",'NPV PT'!F61,'NPV PT'!F61*(1+$D61)) -> 0 | H61: =IF($D61="",'NPV PT'!G61,'NPV PT'!G61*(1+$D61)) -> 0 | I61: =IF($D61="",'NPV PT'!H61,'NPV PT'!H61*(1+$D61)) -> 0 | J61: =IF($D61="",'NPV PT'!I61,'NPV PT'!I61*(1+$D61)) -> 0 | K61: =IF($D61="",'NPV PT'!J61,'NPV PT'!J61*(1+$D61)) -> 0 | L61: =IF($D61="",'NPV PT'!K61,'NPV PT'!K61*(1+$D61)) -> 0 | ... O61: =IF($D61="",'NPV PT'!N61,'NPV PT'!N61*(1+$D61)) -> 0
B62: OWC - Trade Debtors | C62: =VLOOKUP($C$2,countries!C:F,4,0) -> MYR | E62: =IF($D62="",'NPV PT'!D62,'NPV PT'!D62*(1+$D62)) -> 0 | F62: =IF($D62="",'NPV PT'!E62,'NPV PT'!E62*(1+$D62)) -> 0 | G62: =IF($D62="",'NPV PT'!F62,'NPV PT'!F62*(1+$D62)) -> 0 | H62: =IF($D62="",'NPV PT'!G62,'NPV PT'!G62*(1+$D62)) -> 0 | I62: =IF($D62="",'NPV PT'!H62,'NPV PT'!H62*(1+$D62)) -> 0 | J62: =IF($D62="",'NPV PT'!I62,'NPV PT'!I62*(1+$D62)) -> 0 | K62: =IF($D62="",'NPV PT'!J62,'NPV PT'!J62*(1+$D62)) -> 0 | L62: =IF($D62="",'NPV PT'!K62,'NPV PT'!K62*(1+$D62)) -> 0 | ... O62: =IF($D62="",'NPV PT'!N62,'NPV PT'!N62*(1+$D62)) -> 0
B63: OWC - Trade Creditors | C63: =VLOOKUP($C$2,countries!C:F,4,0) -> MYR | E63: =IF($D63="",'NPV PT'!D63,'NPV PT'!D63*(1+$D63)) -> 0 | F63: =IF($D63="",'NPV PT'!E63,'NPV PT'!E63*(1+$D63)) -> 0 | G63: =IF($D63="",'NPV PT'!F63,'NPV PT'!F63*(1+$D63)) -> 0 | H63: =IF($D63="",'NPV PT'!G63,'NPV PT'!G63*(1+$D63)) -> 0 | I63: =IF($D63="",'NPV PT'!H63,'NPV PT'!H63*(1+$D63)) -> 0 | J63: =IF($D63="",'NPV PT'!I63,'NPV PT'!I63*(1+$D63)) -> 0 | K63: =IF($D63="",'NPV PT'!J63,'NPV PT'!J63*(1+$D63)) -> 0 | L63: =IF($D63="",'NPV PT'!K63,'NPV PT'!K63*(1+$D63)) -> 0 | ... O63: =IF($D63="",'NPV PT'!N63,'NPV PT'!N63*(1+$D63)) -> 0
B64: Total Cash Flow | C64: =VLOOKUP($C$2,countries!C:F,4,0) -> MYR | E64: =SUM(E50:E63) -> -1763244 | F64: =SUM(F50:F63) -> 3013763.4 | G64: =SUM(G50:G63) -> 2863915.6 | H64: =SUM(H50:H63) -> 2772703.9 | I64: =SUM(I50:I63) -> 2707552.6 | J64: =SUM(J50:J63) -> 2655431.6 | K64: =SUM(K50:K63) -> 0 | L64: =SUM(L50:L63) -> 0 | ... O64: =SUM(O50:O63) -> 0
B65: Total Cash Flow | C65: =CONCATENATE(VLOOKUP($C$2,countries!C:F,4,0),"m") -> MYRm | E65: =+E64/1000000 -> -1.763244 | F65: =+F64/1000000 -> 3.0137634 | G65: =+G64/1000000 -> 2.8639156 | H65: =+H64/1000000 -> 2.7727039 | I65: =+I64/1000000 -> 2.7075526 | J65: =+J64/1000000 -> 2.6554316 | K65: =+K64/1000000 -> 0 | L65: =+L64/1000000 -> 0 | ... O65: =+O64/1000000 -> 0
B66: Total Cash Flow | C66: $m | E66: =+E65/E12 -> -0.37436178 | F66: =+F65/F12 -> 0.66824023 | G66: =+G65/G12 -> 0.66913915 | H66: =+H65/H12 -> 0.66973523 | I66: =+I65/I12 -> 0.67018629 | J66: =+J65/J12 -> 0.67056354 | K66: =+K65/K12 -> 0 | L66: =+L65/L12 -> 0 | ... O66: =+O65/O12 -> 0
B67: Discounted Cashflow | C67: $m | E67: =+E73*E66 -> -0.3619092 | F67: =+F73*F66 -> 0.60374973 | G67: =+G73*G66 -> 0.56501112 | H67: =+H73*H66 -> 0.52851817 | I67: =+I73*I66 -> 0.49427488 | J67: =+J73*J66 -> 0.46219917 | K67: =+K73*K66 -> 0 | L67: =+L73*L66 -> 0 | ... O67: =+O73*O66 -> 0
B68: Cummulative Cashflow | C68: $m | E68: =+E67 -> -0.3619092 | F68: =+E68+F67 -> 0.24184053 | G68: =+F68+G67 -> 0.80685166 | H68: =+G68+H67 -> 1.3353698 | I68: =+H68+I67 -> 1.8296447 | J68: =+I68+J67 -> 2.2918439 | K68: =+J68+K67 -> 2.2918439 | L68: =+K68+L67 -> 2.2918439 | M68: =+L68+M67 -> 2.2918439 | ... O68: =+N68+O67 -> 2.2918439
B69: Payback - Years | C69: Years | E69: =IF(AND(E68>0,C68<0)=TRUE,E8-C68/(E68-C68),"") | F69: =IF(AND(F68>0,E68<0)=TRUE,F8-E68/(F68-E68),"") -> 1.5994358 | G69: =IF(AND(G68>0,F68<0)=TRUE,G8-F68/(G68-F68),"") | H69: =IF(AND(H68>0,G68<0)=TRUE,H8-G68/(H68-G68),"") | I69: =IF(AND(I68>0,H68<0)=TRUE,I8-H68/(I68-H68),"") | J69: =IF(AND(J68>0,I68<0)=TRUE,J8-I68/(J68-I68),"") | K69: =IF(AND(K68>0,J68<0)=TRUE,K8-J68/(K68-J68),"") | L69: =IF(AND(L68>0,K68<0)=TRUE,L8-K68/(L68-K68),"") | M69: =IF(AND(M68>0,L68<0)=TRUE,M8-L68/(M68-L68),"") | ... O69: =IF(AND(O68>0,N68<0)=TRUE,O8-N68/(O68-N68),"")
F70: =IF(F68<0,"n/m",ABS(E68)/F65) -> 0.12008547 | G70: =IF(G68<0,"n/m",ABS(F68)/G65) -> 0.084444016 | H70: =IF(H68<0,"n/m",ABS(G68)/H65) -> 0.29099814 | I70: =IF(I68<0,"n/m",ABS(H68)/I65) -> 0.4932018 | J70: =IF(J68<0,"n/m",ABS(I68)/J65) -> 0.6890197 | K70: =IF(K68<0,"n/m",ABS(J68)/K65) -> #DIV/0! | L70: =IF(L68<0,"n/m",ABS(K68)/L65) -> #DIV/0! | M70: =IF(M68<0,"n/m",ABS(L68)/M65) -> #DIV/0! | ... O70: =IF(O68<0,"n/m",ABS(N68)/O65) -> #DIV/0!
B72: t | E72: 0.5 | F72: 1.5 | G72: 2.5 | H72: 3.5 | I72: 4.5 | J72: 5.5 | K72: 6.5 | L72: 7.5 | M72: 8.5 | N72: 9.5 | O72: 10.5
B73: Discount factor | C73: 0.07 | E73: =1/((1+$C$73)^E72) -> 0.96673649 | F73: =1/((1+$C$73)^F72) -> 0.90349205 | G73: =1/((1+$C$73)^G72) -> 0.84438509 | H73: =1/((1+$C$73)^H72) -> 0.78914494 | I73: =1/((1+$C$73)^I72) -> 0.73751864 | J73: =1/((1+$C$73)^J72) -> 0.68926976 | K73: =1/((1+$C$73)^K72) -> 0.64417734 | L73: =1/((1+$C$73)^L72) -> 0.6020349 | ... O73: =1/((1+$C$73)^O72) -> 0.49143981
B75: NPV - in $m | C75: =SUM(E67:O67) -> 2.2918439
B76: IRR | C76: =IRR(E66:O66,0.1) -> 1.7752775
B77: Payback - in Years | C77: =+F77 -> 1.5994358 | E77: =IF(F70<0,"never",COUNTIF(F68:O68,"<0")) -> 0 | F77: =IF(SUM(E69:O69)>0,SUM(E69:O69),"10+") -> 1.5994358
B78: Profitability Index | C78: =-SUM(E83:O83)/SUM(E81:O81) -> 2.2334567 | E78: =INDEX(F70:O70,,COUNTIF(F68:O68,"<0")+1) -> 0.12008547
B80: Initial Investment | E80: =(E54+E53+E39+E43+E42)/E12 -> -309818.26 | F80: =(F54+F53+F39+F43+F42)/F12 -> -392458.55 | G80: =(G54+G53+G39+G43+G42)/G12 -> -392986.49 | H80: =(H54+H53+H39+H43+H42)/H12 -> -393336.56 | I80: =(I54+I53+I39+I43+I42)/I12 -> -393601.47 | J80: =(J54+J53+J39+J43+J42)/J12 -> -393823.03 | K80: =(K54+K53+K39+K43+K42)/K12 -> 0 | L80: =(L54+L53+L39+L43+L42)/L12 -> 0 | ... O80: =(O54+O53+O39+O43+O42)/O12 -> 0
B81: Initial Investment - PV | E81: =E80*E73 -> -299512.62 | F81: =F80*F73 -> -354583.17 | G81: =G80*G73 -> -331831.93 | H81: =H80*H73 -> -310399.56 | I81: =I80*I73 -> -290288.42 | J81: =J80*J73 -> -271450.31 | K81: =K80*K73 -> 0 | L81: =L80*L73 -> 0 | ... O81: =O80*O73 -> 0
B82: NPV | E82: =E64*E73/E12 -> -361909.2 | F82: =F64*F73/F12 -> 603749.73 | G82: =G64*G73/G12 -> 565011.12 | H82: =H64*H73/H12 -> 528518.17 | I82: =I64*I73/I12 -> 494274.88 | J82: =J64*J73/J12 -> 462199.17 | K82: =K64*K73/K12 -> 0 | L82: =L64*L73/L12 -> 0 | ... O82: =O64*O73/O12 -> 0
B83: PV (excl initial investment) | E83: =E82-E81 -> -62396.58 | F83: =F82-F81 -> 958332.9 | G83: =G82-G81 -> 896843.06 | H83: =H82-H81 -> 838917.73 | I83: =I82-I81 -> 784563.3 | J83: =J82-J81 -> 733649.48 | K83: =K82-K81 -> 0 | L83: =L82-L81 -> 0 | ... O83: =O82-O81 -> 0
B91: BP Metrics ($) | E91: =E10 -> 2025 | F91: =F10 -> 2026 | G91: =G10 -> 2027 | H91: =H10 -> 2028 | I91: =I10 -> 2029 | J91: =J10 -> 2030 | K91: =K10 -> 2031 | L91: =L10 -> 2032 | ... O91: =O10 -> 2035 | P91: Total
B92: Cash Capex | E92: =E53/E12+E54/E12 -> -309818.26 | F92: =F53/F12 -> 0 | G92: =G53/G12 -> 0 | H92: =H53/H12 -> 0 | I92: =I53/I12 -> 0 | J92: =J53/J12 -> 0 | K92: =K53/K12 -> 0 | L92: =L53/L12 -> 0 | M92: =M53/M12 -> 0 | ... O92: =O53/O12 -> 0 | P92: =SUM(E92:O92) -> -309818.26
B93: Revex | E93: =E39/E12 -> 0 | F93: =F39/F12 -> 0 | G93: =G39/G12 -> 0 | H93: =H39/H12 -> 0 | I93: =I39/I12 -> 0 | J93: =J39/J12 -> 0 | K93: =K39/K12 -> 0 | L93: =L39/L12 -> 0 | ... O93: =O39/O12 -> 0 | P93: =SUM(E93:O93) -> 0
B94: Remediation | E94: =E42/E12 -> 0 | F94: =F42/F12 -> 0 | G94: =G42/G12 -> 0 | H94: =H42/H12 -> 0 | I94: =I42/I12 -> 0 | J94: =J42/J12 -> 0 | K94: =K42/K12 -> 0 | L94: =L42/L12 -> 0 | ... O94: =O42/O12 -> 0 | P94: =SUM(E94:O94) -> 0
B95: Ratex | E95: =E43/E12 -> 0 | F95: =F43/F12 -> 0 | G95: =G43/G12 -> 0 | H95: =H43/H12 -> 0 | I95: =I43/I12 -> 0 | J95: =J43/J12 -> 0 | K95: =K43/K12 -> 0 | L95: =L43/L12 -> 0 | ... O95: =O43/O12 -> 0 | P95: =SUM(E95:O95) -> 0
B96: Impairment | E96: =E41/E12 -> 0 | F96: =F41/F12 -> 0 | G96: =G41/G12 -> 0 | H96: =H41/H12 -> 0 | I96: =I41/I12 -> 0 | J96: =J41/J12 -> 0 | K96: =K41/K12 -> 0 | L96: =L41/L12 -> 0 | ... O96: =O41/O12 -> 0 | P96: =SUM(E96:O96) -> 0
B97: GM | E97: =(E24+E32+E35+E36+E30+E31)/E12 -> 0 | F97: =(F24+F32+F35+F36+F30+F31)/F12*(1-37%) -> 857253.08 | G97: =(G24+G32+G35+G36+G30+G31)/G12*(1-37%) -> 857253.08 | H97: =(H24+H32+H35+H36+H30+H31)/H12*(1-37%) -> 857253.08 | I97: =(I24+I32+I35+I36+I30+I31)/I12*(1-37%) -> 857253.08 | J97: =(J24+J32+J35+J36+J30+J31)/J12*(1-37%) -> 857253.08 | K97: =(K24+K32+K35+K36+K30+K31)/K12*(1-37%) -> 0 | L97: =(L24+L32+L35+L36+L30+L31)/L12*(1-37%) -> 0 | M97: =(M24+M32+M35+M36+M30+M31)/M12*(1-37%) -> 0 | ... O97: =(O24+O32+O35+O36+O30+O31)/O12*(1-37%) -> 0 | P97: =SUM(E97:O97) -> 4286265.4
B98: TCC | E98: =(E26+E33+E34+E37+E38+E25+E27+E28+E29)/E12*(1-37%) -> -53503.185 | F98: =(F26+F33+F34+F37+F38+F25+F27+F28+F29)/F12*(1-37%) -> 0 | G98: =(G26+G33+G34+G37+G38+G25+G27+G28+G29)/G12*(1-37%) -> 0 | H98: =(H26+H33+H34+H37+H38+H25+H27+H28+H29)/H12*(1-37%) -> 0 | I98: =(I26+I33+I34+I37+I38+I25+I27+I28+I29)/I12*(1-37%) -> 0 | J98: =(J26+J33+J34+J37+J38+J25+J27+J28+J29)/J12*(1-37%) -> 0 | K98: =(K26+K33+K34+K37+K38+K25+K27+K28+K29)/K12*(1-37%) -> 0 | L98: =(L26+L33+L34+L37+L38+L25+L27+L28+L29)/L12*(1-37%) -> 0 | ... O98: =(O26+O33+O34+O37+O38+O25+O27+O28+O29)/O12*(1-37%) -> 0 | P98: =SUM(E98:O98) -> -53503.185
B99: Post tax cash flow ($m) | E99: =E64/E12 -> -374361.78 | F99: =F64/F12 -> 668240.23 | G99: =G64/G12 -> 669139.15 | H99: =H64/H12 -> 669735.23 | I99: =I64/I12 -> 670186.29 | J99: =J64/J12 -> 670563.54 | K99: =K64/K12 -> 0 | L99: =L64/L12 -> 0 | ... O99: =O64/O12 -> 0 | P99: =SUM(E99:O99) -> 2973502.7
B100: RCOP pre tax ($m) | E100: =E46/E12*(1-37%) -> -53503.185 | F100: =F46/F12*(1-37%) -> 787553.57 | G100: =G46/G12*(1-37%) -> 783808.04 | H100: =H46/H12*(1-37%) -> 781324.39 | I100: =I46/I12*(1-37%) -> 779444.96 | J100: =J46/J12*(1-37%) -> 777873.08 | K100: =K46/K12*(1-37%) -> 0 | L100: =L46/L12*(1-37%) -> 0 | ... O100: =O46/O12*(1-37%) -> 0 | P100: =SUM(E100:O100) -> 3856500.9
B101: Underlying RCOP pre tax ($m) | E101: =E100-E95-E94-E96 -> -53503.185 | F101: =F100-F95-F94-F96 -> 787553.57 | G101: =G100-G95-G94-G96 -> 783808.04 | H101: =H100-H95-H94-H96 -> 781324.39 | I101: =I100-I95-I94-I96 -> 779444.96 | J101: =J100-J95-J94-J96 -> 777873.08 | K101: =K100-K95-K94-K96 -> 0 | L101: =L100-L95-L94-L96 -> 0 | ... O101: =O100-O95-O94-O96 -> 0 | P101: =SUM(E101:O101) -> 3856500.9

Sheet Chart1 CashFlow
A1: GIAAP Finance Charts Template | H1: How to use
A3: Chart 1 | B3: Cash Flow Components
A5: Parameter | B5: Annual $m
A7: Input Data | B7: Add, remove or modify rows as required to show cashflow.
A8: Year | B8: ='NPV PT'!D10 -> 2025 | C8: =B8+1 -> 2026 | D8: =C8+1 -> 2027 | E8: =D8+1 -> 2028 | F8: =E8+1 -> 2029 | G8: =F8+1 -> 2030 | H8: =G8+1 -> 2031 | I8: =H8+1 -> 2032 | J8: =I8+1 -> 2033 | ... Q8: =P8+1 -> 2040
A9: Cash Capex | B9: ='NPV PT'!D92/1000000 -> -0.29745902 | C9: ='NPV PT'!E92/1000000 -> 0 | D9: ='NPV PT'!F92/1000000 -> 0 | E9: ='NPV PT'!G92/1000000 -> 0 | F9: ='NPV PT'!H92/1000000 -> 0 | G9: ='NPV PT'!I92/1000000 -> 0 | H9: ='NPV PT'!J92/1000000 -> 0 | I9: ='NPV PT'!K92/1000000 -> 0 | ... L9: ='NPV PT'!N92/1000000 -> 0 | M9: =[64]NPV!O59 -> 0 | N9: =[64]NPV!P59 -> 0 | O9: =[64]NPV!Q59 -> 0 | P9: =[64]NPV!R59 -> 0 | Q9: =[64]NPV!S59 -> 0 | S9: Capex
A10: Ratex | B10: ='NPV PT'!D95/1000000 -> 0 | C10: ='NPV PT'!E95/1000000 -> 0 | D10: ='NPV PT'!F95/1000000 -> 0 | E10: ='NPV PT'!G95/1000000 -> 0 | F10: ='NPV PT'!H95/1000000 -> 0 | G10: ='NPV PT'!I95/1000000 -> 0 | H10: ='NPV PT'!J95/1000000 -> 0 | I10: ='NPV PT'!K95/1000000 -> 0 | ... L10: ='NPV PT'!N95/1000000 -> 0 | M10: =[64]NPV!O60 -> 0 | N10: =[64]NPV!P60 -> 0 | O10: =[64]NPV!Q60 -> 0 | P10: =[64]NPV!R60 -> 0 | Q10: =[64]NPV!S60 -> 0 | S10: Capex Creditors
A11: Revex (incl Remediation) | B11: =('NPV PT'!D94+'NPV PT'!D93)/1000000 -> 0 | C11: =('NPV PT'!E94+'NPV PT'!E93)/1000000 -> 0 | D11: =('NPV PT'!F94+'NPV PT'!F93)/1000000 -> 0 | E11: =('NPV PT'!G94+'NPV PT'!G93)/1000000 -> 0 | F11: =('NPV PT'!H94+'NPV PT'!H93)/1000000 -> 0 | G11: =('NPV PT'!I94+'NPV PT'!I93)/1000000 -> 0 | H11: =('NPV PT'!J94+'NPV PT'!J93)/1000000 -> 0 | I11: =('NPV PT'!K94+'NPV PT'!K93)/1000000 -> 0 | ... L11: =('NPV PT'!N94+'NPV PT'!N93)/1000000 -> 0 | M11: =[64]NPV!O61 -> 0 | N11: =[64]NPV!P61 -> 0 | O11: =[64]NPV!Q61 -> 0 | P11: =[64]NPV!R61 -> 0 | Q11: =[64]NPV!S61 -> 0 | S11: Ratex
A12: GM+TCC | B12: ='NPV PT'!D97/1000000+'NPV PT'!D98/1000000 -> -0.053503185 | C12: ='NPV PT'!E97/1000000+'NPV PT'!E98/1000000 -> 0.85725308 | D12: ='NPV PT'!F97/1000000+'NPV PT'!F98/1000000 -> 0.85725308 | E12: ='NPV PT'!G97/1000000+'NPV PT'!G98/1000000 -> 0.85725308 | F12: ='NPV PT'!H97/1000000+'NPV PT'!H98/1000000 -> 0.85725308 | G12: ='NPV PT'!I97/1000000+'NPV PT'!I98/1000000 -> 0.85725308 | H12: ='NPV PT'!J97/1000000+'NPV PT'!J98/1000000 -> 0 | I12: ='NPV PT'!K97/1000000+'NPV PT'!K98/1000000 -> 0 | ... L12: ='NPV PT'!N97/1000000+'NPV PT'!N98/1000000 -> 0 | M12: =[64]NPV!O62 -> 0 | N12: =[64]NPV!P62 -> 0 | O12: =[64]NPV!Q62 -> 0 | P12: =[64]NPV!R62 -> 0 | Q12: =[64]NPV!S62 -> 0 | S12: Ratex Creditors
A13: Tax | B13: =('NPV PT'!D47/'NPV PT'!D12+'NPV PT'!D55/'NPV PT'!D12)/1000000 -> 0.020382166 | C13: =('NPV PT'!E47/'NPV PT'!E12+'NPV PT'!E55/'NPV PT'!E12)/1000000 -> -0.30100382 | D13: =('NPV PT'!F47/'NPV PT'!F12+'NPV PT'!F55/'NPV PT'!F12)/1000000 -> -0.2996298 | E13: =('NPV PT'!G47/'NPV PT'!G12+'NPV PT'!G55/'NPV PT'!G12)/1000000 -> -0.29871869 | F13: =('NPV PT'!H47/'NPV PT'!H12+'NPV PT'!H55/'NPV PT'!H12)/1000000 -> -0.29802924 | G13: =('NPV PT'!I47/'NPV PT'!I12+'NPV PT'!I55/'NPV PT'!I12)/1000000 -> -0.2974526 | H13: =('NPV PT'!J47/'NPV PT'!J12+'NPV PT'!J55/'NPV PT'!J12)/1000000 -> 0 | I13: =('NPV PT'!K47/'NPV PT'!K12+'NPV PT'!K55/'NPV PT'!K12)/1000000 -> 0 | ... L13: =('NPV PT'!N47/'NPV PT'!N12+'NPV PT'!N55/'NPV PT'!N12)/1000000 -> 0 | M13: =[64]NPV!O63 -> 0 | N13: =[64]NPV!P63 -> 0 | O13: =[64]NPV!Q63 -> 0 | P13: =[64]NPV!R63 -> 0 | Q13: =[64]NPV!S63 -> 0 | S13: Revex (incl Remediation)
A14: Working Capital Change | B14: =(SUM('NPV PT'!D57:D63)/'NPV PT'!D12)/1000000 -> 0 | C14: =(SUM('NPV PT'!E57:E63)/'NPV PT'!E12)/1000000 -> 0 | D14: =(SUM('NPV PT'!F57:F63)/'NPV PT'!F12)/1000000 -> 0 | E14: =(SUM('NPV PT'!G57:G63)/'NPV PT'!G12)/1000000 -> 0 | F14: =(SUM('NPV PT'!H57:H63)/'NPV PT'!H12)/1000000 -> 0 | G14: =(SUM('NPV PT'!I57:I63)/'NPV PT'!I12)/1000000 -> 0 | H14: =(SUM('NPV PT'!J57:J63)/'NPV PT'!J12)/1000000 -> 0 | I14: =(SUM('NPV PT'!K57:K63)/'NPV PT'!K12)/1000000 -> 0 | ... L14: =(SUM('NPV PT'!N57:N63)/'NPV PT'!N12)/1000000 -> 0 | M14: -1.800926 | N14: -1.8474208 | O14: -1.8945361 | P14: -6.7976573 | Q14: =('[65]FM-usd'!U39)/1000000 -> 0 | S14: Tax
A15: Disp Gains & Other cash | B15: =B16-SUM(B9:B14) -> -0.031422505 | C15: =C16-SUM(C9:C14) -> 0.11137141 | D15: =D16-SUM(D9:D14) -> 0.11086303 | E15: =E16-SUM(E9:E14) -> 0.11052592 | F15: =F16-SUM(F9:F14) -> 0.11027082 | G15: =G16-SUM(G9:G14) -> 0.11005746 | H15: =H16-SUM(H9:H14) -> 0 | I15: =I16-SUM(I9:I14) -> 0 | ... L15: =L16-SUM(L9:L14) -> 0 | M15: =[64]NPV!O65 -> 0 | N15: =[64]NPV!P65 -> 0 | O15: =[64]NPV!Q65 -> 0 | P15: =[64]NPV!R65 -> 0 | Q15: =[64]NPV!S65 -> 0 | S15: Working Capital Change
A16: Cashflow | B16: ='NPV PT'!D66 -> -0.36200255 | C16: ='NPV PT'!E66 -> 0.66762068 | D16: ='NPV PT'!F66 -> 0.66848631 | E16: ='NPV PT'!G66 -> 0.66906031 | F16: ='NPV PT'!H66 -> 0.66949466 | G16: ='NPV PT'!I66 -> 0.66985794 | H16: ='NPV PT'!J66 -> 0 | I16: ='NPV PT'!K66 -> 0 | ... L16: ='NPV PT'!N66 -> 0 | M16: =[64]NPV!O66 -> 0 | N16: =[64]NPV!P66 -> 0 | O16: =[64]NPV!Q66 -> 0 | P16: =[64]NPV!R66 -> 0 | Q16: =[64]NPV!S66 -> 0
A17: Disc Cashflow | B17: ='NPV PT'!D67 -> -0.34996107 | C17: ='NPV PT'!E67 -> 0.60318997 | D17: ='NPV PT'!F67 -> 0.56445987 | E17: ='NPV PT'!G67 -> 0.52798556 | F17: ='NPV PT'!H67 -> 0.49376479 | G17: ='NPV PT'!I67 -> 0.46171282 | H17: ='NPV PT'!J67 -> 0 | I17: ='NPV PT'!K67 -> 0 | ... L17: ='NPV PT'!N67 -> 0 | M17: =[64]NPV!O67 -> 0 | N17: =[64]NPV!P67 -> 0 | O17: =[64]NPV!Q67 -> 0 | P17: =[64]NPV!R67 -> 0 | Q17: =[64]NPV!S67 -> 0
A18: Cum Cashflow | B18: =B17 -> -0.34996107 | C18: =B18+C17 -> 0.2532289 | D18: =C18+D17 -> 0.81768877 | E18: =D18+E17 -> 1.3456743 | F18: =E18+F17 -> 1.8394391 | G18: =F18+G17 -> 2.3011519 | H18: =G18+H17 -> 2.3011519 | I18: =H18+I17 -> 2.3011519 | J18: =I18+J17 -> 2.3011519 | ... L18: =K18+L17 -> 2.3011519 | M18: 23.272073 | N18: 25.110377 | O18: 26.97858 | P18: 26.643385 | Q18: =Q16+P18 -> 26.643385
A19: Cum DCF | B19: =B18 -> -0.34996107 | C19: =C18 -> 0.2532289 | D19: =D18 -> 0.81768877 | E19: =E18 -> 1.3456743 | F19: =F18 -> 1.8394391 | G19: =G18 -> 2.3011519 | H19: =H18 -> 2.3011519 | I19: =I18 -> 2.3011519 | ... L19: =L18 -> 2.3011519 | M19: 14.252951 | N19: 14.955409 | O19: 15.616412 | P19: 15.5066 | Q19: =Q17+P19 -> 15.5066
A21: Chart

Sheet Chart2 Tornado
A1: GIAAP Finance Charts Template | H1: How to use | O1: Inner workings
A3: Chart 2 | B3: Project Sensitivities | O3: ="Central Case NPV "&TEXT(B7,"$#")&"m, IRR "&TEXT(D7,"#%") -> Central Case NPV $1m, IRR 31%
A5: Input Data
A6: Parameter | B6: NPV $m | D6: IRR %
A7: Central Case | B7: 0.71 | D7: 0.31 | O7: Chart Data | V7: Chart Labels
A8: Sensitivity Cases | B8: Upside | C8: Downside | D8: Upside | E8: Downside | F8: Error Chk | O8: Series | P8: blank + | Q8: blank - | R8: red + | S8: green - | T8: red - | U8: green + | V8: red + | W8: green - | X8: red - | Y8: green +
A9: Volume growth @ 70% | F9: {=IF(AND(ISNUMBER(B9:C9)),IF(OR($B$7<C9,$D$7<E9),"Downside must be < Central",IF(OR($B$7>B9,$D$7>D9),"Upside must be > Central","OK")),"Enter numeric data")} -> Enter numeric data | O9: =A9 -> Volume growth @ 70% | P9: =MAX(MIN(B9:C9),0) -> 0 | Q9: =MIN(MAX(B9:C9),0) -> 0 | R9: =IF(C9,IF($B$7<0,,MIN($B$7-C9,$B$7)),) -> 0 | S9: =IF(B9,IF($B$7>0,,MAX($B$7-B9,$B$7)),) -> 0 | T9: =IF(C9,C9-$B$7+R9,) -> 0 | U9: =IF(B9,B9-$B$7+S9,) -> 0 | V9: =IF(T9,,IF(R9,TEXT(C9,"#")&IF(ISNUMBER(E9),TEXT(E9,", #%"),", "&E9),)) -> 0 | W9: =IF(U9,,IF(S9,TEXT(B9,"#")&TEXT(D9,", #%"),)) -> 0 | X9: =IF(T9,TEXT(C9,"#")&IF(ISNUMBER(E9),TEXT(E9,", #%"),", "&E9),) -> 0 | Y9: =IF(U9,TEXT(B9,"#")&TEXT(D9,", #%"),) -> 0
C10: 8 | F10: {=IF(AND(ISNUMBER(B10:C10)),IF(OR($B$7<C10,$D$7<E10),"Downside must be < Central",IF(OR($B$7>B10,$D$7>D10),"Upside must be > Central","OK")),"Enter numeric data")} -> Enter numeric data | O10: =A10 -> 0 | P10: =MAX(MIN(B10:C10),0) -> 8 | Q10: =MIN(MAX(B10:C10),0) -> 0 | R10: =IF(C10,IF($B$7<0,,MIN($B$7-C10,$B$7)),) -> -7.29 | S10: =IF(B10,IF($B$7>0,,MAX($B$7-B10,$B$7)),) -> 0 | T10: =IF(C10,C10-$B$7+R10,) -> 0 | U10: =IF(B10,B10-$B$7+S10,) -> 0 | V10: =IF(T10,,IF(R10,TEXT(C10,"#")&IF(ISNUMBER(E10),TEXT(E10,", #%"),", "&E10),)) -> 8, | W10: =IF(U10,,IF(S10,TEXT(B10,"#")&TEXT(D10,", #%"),)) -> 0 | X10: =IF(T10,TEXT(C10,"#")&IF(ISNUMBER(E10),TEXT(E10,", #%"),", "&E10),) -> 0 | Y10: =IF(U10,TEXT(B10,"#")&TEXT(D10,", #%"),) -> 0
C11: 7 | F11: {=IF(AND(ISNUMBER(B11:C11)),IF(OR($B$7<C11,$D$7<E11),"Downside must be < Central",IF(OR($B$7>B11,$D$7>D11),"Upside must be > Central","OK")),"Enter numeric data")} -> Enter numeric data | O11: =A11 -> 0 | P11: =MAX(MIN(B11:C11),0) -> 7 | Q11: =MIN(MAX(B11:C11),0) -> 0 | R11: =IF(C11,IF($B$7<0,,MIN($B$7-C11,$B$7)),) -> -6.29 | S11: =IF(B11,IF($B$7>0,,MAX($B$7-B11,$B$7)),) -> 0 | T11: =IF(C11,C11-$B$7+R11,) -> 0 | U11: =IF(B11,B11-$B$7+S11,) -> 0 | V11: =IF(T11,,IF(R11,TEXT(C11,"#")&IF(ISNUMBER(E11),TEXT(E11,", #%"),", "&E11),)) -> 7, | W11: =IF(U11,,IF(S11,TEXT(B11,"#")&TEXT(D11,", #%"),)) -> 0 | X11: =IF(T11,TEXT(C11,"#")&IF(ISNUMBER(E11),TEXT(E11,", #%"),", "&E11),) -> 0 | Y11: =IF(U11,TEXT(B11,"#")&TEXT(D11,", #%"),) -> 0
C12: 6 | F12: {=IF(AND(ISNUMBER(B12:C12)),IF(OR($B$7<C12,$D$7<E12),"Downside must be < Central",IF(OR($B$7>B12,$D$7>D12),"Upside must be > Central","OK")),"Enter numeric data")} -> Enter numeric data | O12: =A12 -> 0 | P12: =MAX(MIN(B12:C12),0) -> 6 | Q12: =MIN(MAX(B12:C12),0) -> 0 | R12: =IF(C12,IF($B$7<0,,MIN($B$7-C12,$B$7)),) -> -5.29 | S12: =IF(B12,IF($B$7>0,,MAX($B$7-B12,$B$7)),) -> 0 | T12: =IF(C12,C12-$B$7+R12,) -> 0 | U12: =IF(B12,B12-$B$7+S12,) -> 0 | V12: =IF(T12,,IF(R12,TEXT(C12,"#")&IF(ISNUMBER(E12),TEXT(E12,", #%"),", "&E12),)) -> 6, | W12: =IF(U12,,IF(S12,TEXT(B12,"#")&TEXT(D12,", #%"),)) -> 0 | X12: =IF(T12,TEXT(C12,"#")&IF(ISNUMBER(E12),TEXT(E12,", #%"),", "&E12),) -> 0 | Y12: =IF(U12,TEXT(B12,"#")&TEXT(D12,", #%"),) -> 0
C13: 7 | F13: {=IF(AND(ISNUMBER(B13:C13)),IF(OR($B$7<C13,$D$7<E13),"Downside must be < Central",IF(OR($B$7>B13,$D$7>D13),"Upside must be > Central","OK")),"Enter numeric data")} -> Enter numeric data | O13: =A13 -> 0 | P13: =MAX(MIN(B13:C13),0) -> 7 | Q13: =MIN(MAX(B13:C13),0) -> 0 | R13: =IF(C13,IF($B$7<0,,MIN($B$7-C13,$B$7)),) -> -6.29 | S13: =IF(B13,IF($B$7>0,,MAX($B$7-B13,$B$7)),) -> 0 | T13: =IF(C13,C13-$B$7+R13,) -> 0 | U13: =IF(B13,B13-$B$7+S13,) -> 0 | V13: =IF(T13,,IF(R13,TEXT(C13,"#")&IF(ISNUMBER(E13),TEXT(E13,", #%"),", "&E13),)) -> 7, | W13: =IF(U13,,IF(S13,TEXT(B13,"#")&TEXT(D13,", #%"),)) -> 0 | X13: =IF(T13,TEXT(C13,"#")&IF(ISNUMBER(E13),TEXT(E13,", #%"),", "&E13),) -> 0 | Y13: =IF(U13,TEXT(B13,"#")&TEXT(D13,", #%"),) -> 0
C14: 8 | F14: {=IF(AND(ISNUMBER(B14:C14)),IF(OR($B$7<C14,$D$7<E14),"Downside must be < Central",IF(OR($B$7>B14,$D$7>D14),"Upside must be > Central","OK")),"Enter numeric data")} -> Enter numeric data | O14: =A14 -> 0 | P14: =MAX(MIN(B14:C14),0) -> 8 | Q14: =MIN(MAX(B14:C14),0) -> 0 | R14: =IF(C14,IF($B$7<0,,MIN($B$7-C14,$B$7)),) -> -7.29 | S14: =IF(B14,IF($B$7>0,,MAX($B$7-B14,$B$7)),) -> 0 | T14: =IF(C14,C14-$B$7+R14,) -> 0 | U14: =IF(B14,B14-$B$7+S14,) -> 0 | V14: =IF(T14,,IF(R14,TEXT(C14,"#")&IF(ISNUMBER(E14),TEXT(E14,", #%"),", "&E14),)) -> 8, | W14: =IF(U14,,IF(S14,TEXT(B14,"#")&TEXT(D14,", #%"),)) -> 0 | X14: =IF(T14,TEXT(C14,"#")&IF(ISNUMBER(E14),TEXT(E14,", #%"),", "&E14),) -> 0 | Y14: =IF(U14,TEXT(B14,"#")&TEXT(D14,", #%"),) -> 0
C15: 9 | F15: {=IF(AND(ISNUMBER(B15:C15)),IF(OR($B$7<C15,$D$7<E15),"Downside must be < Central",IF(OR($B$7>B15,$D$7>D15),"Upside must be > Central","OK")),"Enter numeric data")} -> Enter numeric data | O15: =A15 -> 0 | P15: =MAX(MIN(B15:C15),0) -> 9 | Q15: =MIN(MAX(B15:C15),0) -> 0 | R15: =IF(C15,IF($B$7<0,,MIN($B$7-C15,$B$7)),) -> -8.29 | S15: =IF(B15,IF($B$7>0,,MAX($B$7-B15,$B$7)),) -> 0 | T15: =IF(C15,C15-$B$7+R15,) -> 0 | U15: =IF(B15,B15-$B$7+S15,) -> 0 | V15: =IF(T15,,IF(R15,TEXT(C15,"#")&IF(ISNUMBER(E15),TEXT(E15,", #%"),", "&E15),)) -> 9, | W15: =IF(U15,,IF(S15,TEXT(B15,"#")&TEXT(D15,", #%"),)) -> 0 | X15: =IF(T15,TEXT(C15,"#")&IF(ISNUMBER(E15),TEXT(E15,", #%"),", "&E15),) -> 0 | Y15: =IF(U15,TEXT(B15,"#")&TEXT(D15,", #%"),) -> 0
A16: Other down, up (units) | F16: {=IF(AND(ISNUMBER(B16:C16)),IF(OR($B$7<C16,$D$7<E16),"Downside must be < Central",IF(OR($B$7>B16,$D$7>D16),"Upside must be > Central","OK")),"Enter numeric data")} -> Enter numeric data | O16: =A16 -> Other down, up (units) | P16: =MAX(MIN(B16:C16),0) -> 0 | Q16: =MIN(MAX(B16:C16),0) -> 0 | R16: =IF(C16,IF($B$7<0,,MIN($B$7-C16,$B$7)),) -> 0 | S16: =IF(B16,IF($B$7>0,,MAX($B$7-B16,$B$7)),) -> 0 | T16: =IF(C16,C16-$B$7+R16,) -> 0 | U16: =IF(B16,B16-$B$7+S16,) -> 0 | V16: =IF(T16,,IF(R16,TEXT(C16,"#")&IF(ISNUMBER(E16),TEXT(E16,", #%"),", "&E16),)) -> 0 | W16: =IF(U16,,IF(S16,TEXT(B16,"#")&TEXT(D16,", #%"),)) -> 0 | X16: =IF(T16,TEXT(C16,"#")&IF(ISNUMBER(E16),TEXT(E16,", #%"),", "&E16),) -> 0 | Y16: =IF(U16,TEXT(B16,"#")&TEXT(D16,", #%"),) -> 0
A17: Other down, up (units) | B17: =B7 -> 0.71 | C17: =B7-0.721 -> -0.011 | D17: =D7 -> 0.31 | E17: =D7-23.6% -> 0.074 | F17: {=IF(AND(ISNUMBER(B17:C17)),IF(OR($B$7<C17,$D$7<E17),"Downside must be < Central",IF(OR($B$7>B17,$D$7>D17),"Upside must be > Central","OK")),"Enter numeric data")} -> OK | O17: =A17 -> Other down, up (units) | P17: =MAX(MIN(B17:C17),0) -> 0 | Q17: =MIN(MAX(B17:C17),0) -> 0 | R17: =IF(C17,IF($B$7<0,,MIN($B$7-C17,$B$7)),) -> 0.71 | S17: =IF(B17,IF($B$7>0,,MAX($B$7-B17,$B$7)),) -> 0 | T17: =IF(C17,C17-$B$7+R17,) -> -0.011 | U17: =IF(B17,B17-$B$7+S17,) -> 0 | V17: =IF(T17,,IF(R17,TEXT(C17,"#")&IF(ISNUMBER(E17),TEXT(E17,", #%"),", "&E17),)) -> 0 | W17: =IF(U17,,IF(S17,TEXT(B17,"#")&TEXT(D17,", #%"),)) -> 0 | X17: =IF(T17,TEXT(C17,"#")&IF(ISNUMBER(E17),TEXT(E17,", #%"),", "&E17),) -> , 7% | Y17: =IF(U17,TEXT(B17,"#")&TEXT(D17,", #%"),) -> 0
A19: Chart

Sheet BB inflation
B2: Inflation
B3: Last updated 03/04/2024
B6: % change on previous year/1 | C6: 2022 | D6: 2023 | E6: 2024 | F6: 2025 | G6: 2026 | H6: 2027 | I6: 2028 | J6: 2029 | K6: 2030 | L6: 2031 | M6: 2032 | N6: 2033 | O6: 2034 | P6: 2035 | Q6: 2036 | R6: 2037 | S6: 2038 | T6: 2039 | U6: 2040 | V6: 2041 | W6: 2042 | X6: 2043 | Y6: 2044 | Z6: 2045 | AA6: 2046 | AB6: 2047 | AC6: 2048 | AD6: 2049 | AE6: 2050
B8: Algeria | C8: 9.27 | D8: 9.3 | E8: 6.02 | F8: 5 | G8: 4.25 | H8: 4.18 | I8: 3.97 | J8: 3.81 | K8: 3.74 | L8: 3.78 | M8: 3.81 | N8: 3.8 | O8: 3.78 | P8: 3.73 | Q8: 3.69 | R8: 3.66 | S8: 3.62 | T8: 3.57 | U8: 3.53 | V8: 3.52 | W8: 3.5 | X8: 3.49 | Y8: 3.5 | Z8: 3.5 | AA8: 3.54 | AB8: 3.57 | AC8: 3.58 | AD8: 3.56 | AE8: 3.54
B9: Angola | C9: 21.74 | D9: 14.4 | E9: 18.84 | F9: 10.655 | G9: 8.92 | H9: 8.2 | I9: 8.31 | J9: 8.025 | K9: 7.53 | L9: 6.79 | M9: 6.945 | N9: 6.955 | O9: 7.205 | P9: 7.38 | Q9: 7.415 | R9: 7.28 | S9: 7.11 | T9: 7.04 | U9: 6.995 | V9: 7.05 | W9: 7.165 | X9: 7.245 | Y9: 7.285 | Z9: 7.3 | AA9: 7.275 | AB9: 7.285 | AC9: 7.355 | AD9: 7.405 | AE9: 7.44
B10: Argentina | C10: 73.13 | D10: 134.04 | E10: 295.04 | F10: 60.81 | G10: 20.22 | H10: 10.35 | I10: 2.23 | J10: 0.56 | K10: 0.22 | L10: 0.38 | M10: 0.56 | N10: 0.75 | O10: 0.73 | P10: 0.55 | Q10: 0.4 | R10: 0.27 | S10: 0.24 | T10: 0.29 | U10: 0.45 | V10: 0.66 | W10: 0.93 | X10: 1.23 | Y10: 1.53 | Z10: 1.83 | AA10: 2.12 | AB10: 2.45 | AC10: 2.81 | AD10: 3.19 | AE10: 3.5
B11: Australia | C11: 6.61 | D11: 5.59 | E11: 3.26 | F11: 2.82 | G11: 2.53 | H11: 2.605 | I11: 2.515 | J11: 2.515 | K11: 2.505 | L11: 2.485 | M11: 2.45 | N11: 2.445 | O11: 2.445 | P11: 2.425 | Q11: 2.405 | R11: 2.395 | S11: 2.39 | T11: 2.39 | U11: 2.385 | V11: 2.37 | W11: 2.365 | X11: 2.355 | Y11: 2.35 | Z11: 2.355 | AA11: 2.36 | AB11: 2.36 | AC11: 2.355 | AD11: 2.35 | AE11: 2.345
B12: Azerbaijan | C12: 13.85 | D12: 10.44 | E12: 3.16 | F12: 6.5 | G12: 5.595 | H12: 5.65 | I12: 5.43 | J12: 5.32 | K12: 5.2 | L12: 5.085 | M12: 4.99 | N12: 4.895 | O12: 4.805 | P12: 4.73 | Q12: 4.655 | R12: 4.59 | S12: 4.52 | T12: 4.465 | U12: 4.405 | V12: 4.355 | W12: 4.305 | X12: 4.255 | Y12: 4.215 | Z12: 4.17 | AA12: 4.13 | AB12: 4.09 | AC12: 4.06 | AD12: 4.02 | AE12: 3.99
B13: Bangladesh | C13: 7.7 | D13: 9.855 | E13: 7.56 | F13: 6.005 | G13: 6.005 | H13: 5.525 | I13: 5.475 | J13: 5.525 | K13: 5.545 | L13: 5.55 | M13: 5.545 | N13: 5.54 | O13: 5.525 | P13: 5.505 | Q13: 5.48 | R13: 5.46 | S13: 5.445 | T13: 5.435 | U13: 5.425 | V13: 5.415 | W13: 5.405 | X13: 5.39 | Y13: 5.38 | Z13: 5.37 | AA13: 5.36 | AB13: 5.345 | AC13: 5.335 | AD13: 5.32 | AE13: 5.31
B14: Brazil | C14: 9.28 | D14: 4.59 | E14: 4.03 | F14: 3.415 | G14: 3.35 | H14: 3.19 | I14: 3.17 | J14: 3.175 | K14: 3.18 | L14: 3.18 | M14: 3.19 | N14: 3.205 | O14: 3.175 | P14: 3.175 | Q14: 3.155 | R14: 3.16 | S14: 3.155 | T14: 3.14 | U14: 3.14 | V14: 3.13 | W14: 3.115 | X14: 3.11 | Y14: 3.1 | Z14: 3.105 | AA14: 3.11 | AB14: 3.115 | AC14: 3.105 | AD14: 3.11 | AE14: 3.12
B15: Canada | C15: 6.8 | D15: 3.88 | E15: 2.545 | F15: 2.06 | G15: 2.08 | H15: 2.12 | I15: 2.08 | J15: 2.055 | K15: 2.04 | L15: 1.985 | M15: 1.995 | N15: 1.97 | O15: 1.995 | P15: 1.995 | Q15: 1.985 | R15: 1.97 | S15: 1.975 | T15: 1.975 | U15: 2 | V15: 1.995 | W15: 1.98 | X15: 1.99 | Y15: 2.005 | Z15: 1.995 | AA15: 1.975 | AB15: 1.99 | AC15: 1.99 | AD15: 1.99 | AE15: 2
B16: China | C16: 1.96 | D16: 0.24 | E16: 0.68 | F16: 1.685 | G16: 2.04 | H16: 2.245 | I16: 2.215 | J16: 2.16 | K16: 2.19 | L16: 2.21 | M16: 2.225 | N16: 2.235 | O16: 2.25 | P16: 2.255 | Q16: 2.255 | R16: 2.255 | S16: 2.265 | T16: 2.28 | U16: 2.28 | V16: 2.28 | W16: 2.28 | X16: 2.285 | Y16: 2.3 | Z16: 2.3 | AA16: 2.295 | AB16: 2.3 | AC16: 2.3 | AD16: 2.3 | AE16: 2.3
B17: Colombia | C17: 10.18 | D17: 11.74 | E17: 6.705 | F17: 4 | G17: 3.11 | H17: 3.17 | I17: 3.28 | J17: 3.155 | K17: 3.065 | L17: 3.015 | M17: 2.97 | N17: 2.935 | O17: 2.91 | P17: 2.88 | Q17: 2.855 | R17: 2.83 | S17: 2.81 | T17: 2.795 | U17: 2.775 | V17: 2.77 | W17: 2.765 | X17: 2.76 | Y17: 2.75 | Z17: 2.74 | AA17: 2.74 | AB17: 2.735 | AC17: 2.73 | AD17: 2.73 | AE17: 2.725
B18: Czech Republic | C18: 14.955 | D18: 11.3 | E18: 2.475 | F18: 1.98 | G18: 2.15 | H18: 2.175 | I18: 2.135 | J18: 2.095 | K18: 2.08 | L18: 2.055 | M18: 2.08 | N18: 2.13 | O18: 2.1 | P18: 2.07 | Q18: 2.005 | R18: 2.01 | S18: 2.01 | T18: 1.98 | U18: 2.005 | V18: 2.015 | W18: 1.995 | X18: 2.01 | Y18: 1.995 | Z18: 2.005 | AA18: 2.015 | AB18: 2.04 | AC18: 2.005 | AD18: 1.99 | AE18: 2.04
... B66: Ghana | C66: 31.92 | D66: 39.24 | E66: 18.725 | F66: 12.5 | G66: 8.715 | H66: 8.565 | I66: 8.245 | J66: 8.22 | K66: 8.2 | L66: 8.195 | M66: 8.18 | N66: 8.165 | O66: 8.155 | P66: 8.145 | Q66: 8.14 | R66: 8.13 | S66: 8.12 | T66: 8.115 | U66: 8.105 | V66: 8.095 | W66: 8.09 | X66: 8.085 | Y66: 8.075 | Z66: 8.07 | AA66: 8.065 | AB66: 8.055 | AC66: 8.045 | AD66: 8.035 | AE66: 8.03
B67: Iceland | D67: 8.63 | E67: 4.355 | F67: 2.21 | G67: 2.295 | H67: 2.52 | I67: 2.5 | J67: 2.5 | K67: 2.515 | L67: 2.515 | M67: 2.515 | N67: 2.515 | O67: 2.515 | P67: 2.515 | Q67: 2.515 | R67: 2.515 | S67: 2.515 | T67: 2.515 | U67: 2.515 | V67: 2.515 | W67: 2.515 | X67: 2.515 | Y67: 2.515 | Z67: 2.515 | AA67: 2.515 | AB67: 2.515 | AC67: 2.515 | AD67: 2.515 | AE67: 2.515
B69: Austria | C69: 8.585 | D69: 7.76 | E69: 3.04 | F69: 1.615 | G69: 2.055 | H69: 2.16 | I69: 2.14 | J69: 2.13 | K69: 2.115 | L69: 2.14 | M69: 2.135 | N69: 2.18 | O69: 2.16 | P69: 2.155 | Q69: 2.145 | R69: 2.16 | S69: 2.175 | T69: 2.155 | U69: 2.165 | V69: 2.155 | W69: 2.13 | X69: 2.13 | Y69: 2.115 | Z69: 2.125 | AA69: 2.115 | AB69: 2.125 | AC69: 2.11 | AD69: 2.115 | AE69: 2.125
B70: Belgium | C70: 9.965 | D70: 3.165 | E70: 3.075 | F70: 2 | G70: 1.745 | H70: 1.905 | I70: 2.015 | J70: 2.03 | K70: 2.06 | L70: 2.01 | M70: 1.985 | N70: 1.995 | O70: 1.95 | P70: 1.985 | Q70: 1.97 | R70: 1.955 | S70: 1.945 | T70: 1.925 | U70: 1.92 | V70: 1.98 | W70: 1.975 | X70: 1.99 | Y70: 1.975 | Z70: 1.98 | AA70: 1.995 | AB70: 2 | AC70: 1.98 | AD70: 1.99 | AE70: 1.995
B71: Cyprus | C71: 8.25 | D71: 3.93 | E71: 2.345 | F71: 1.87 | G71: 2.035 | H71: 2.14 | I71: 2.155 | J71: 2.275 | K71: 2.31 | L71: 2.325 | M71: 2.32 | N71: 2.37 | O71: 2.305 | P71: 2.255 | Q71: 2.195 | R71: 2.18 | S71: 2.145 | T71: 2.11 | U71: 2.115 | V71: 2.11 | W71: 2.08 | X71: 2.09 | Y71: 2.07 | Z71: 2.065 | AA71: 2.07 | AB71: 2.08 | AC71: 2.05 | AD71: 2.045 | AE71: 2.065
B72: Finland | C72: 7.145 | D72: 5.295 | E72: 1.87 | F72: 1.965 | G72: 1.985 | H72: 2.075 | I72: 2.08 | J72: 2.14 | K72: 2.125 | L72: 2.04 | M72: 2.06 | N72: 2.125 | O72: 2.16 | P72: 2.12 | Q72: 2.185 | R72: 2.145 | S72: 2.21 | T72: 2.15 | U72: 2.13 | V72: 2.145 | W72: 2.065 | X72: 2.115 | Y72: 2.09 | Z72: 2.165 | AA72: 2.085 | AB72: 2.1 | AC72: 2.06 | AD72: 2.06 | AE72: 2.065
B73: France | C73: 5.565 | D73: 5.27 | E73: 2.73 | F73: 1.5 | G73: 1.57 | H73: 1.945 | I73: 1.965 | J73: 1.985 | K73: 1.955 | L73: 2.01 | M73: 2.025 | N73: 2.05 | O73: 2.04 | P73: 2.045 | Q73: 2.05 | R73: 2.06 | S73: 2.06 | T73: 2.055 | U73: 2.06 | V73: 2.065 | W73: 2.035 | X73: 2.04 | Y73: 2.03 | Z73: 2.02 | AA73: 2.025 | AB73: 2.035 | AC73: 2.02 | AD73: 2.025 | AE73: 2.04
B74: Germany | C74: 7.78 | D74: 5.975 | E74: 1.92 | F74: 1.315 | G74: 1.505 | H74: 1.795 | I74: 1.98 | J74: 2.05 | K74: 2.025 | L74: 2.1 | M74: 2.205 | N74: 2.375 | O74: 2.355 | P74: 2.33 | Q74: 2.29 | R74: 2.295 | S74: 2.285 | T74: 2.235 | U74: 2.22 | V74: 2.215 | W74: 2.15 | X74: 2.11 | Y74: 2.075 | Z74: 2.045 | AA74: 2.01 | AB74: 2.03 | AC74: 1.995 | AD74: 1.97 | AE74: 1.99
B75: Greece | C75: 9.475 | D75: 3.805 | E75: 2.525 | F75: 1.645 | G75: 1.815 | H75: 1.92 | I75: 1.97 | J75: 1.9 | K75: 1.9 | L75: 1.895 | M75: 1.875 | N75: 1.915 | O75: 1.92 | P75: 1.935 | Q75: 1.92 | R75: 1.925 | S75: 1.925 | T75: 1.92 | U75: 1.935 | V75: 1.94 | W75: 1.925 | X75: 1.925 | Y75: 1.915 | Z75: 1.92 | AA75: 1.925 | AB75: 1.94 | AC75: 1.935 | AD75: 1.93 | AE75: 1.945
B76: Ireland | C76: 7.94 | D76: 5.745 | E76: 1.955 | F76: 1.77 | G76: 1.78 | H76: 1.855 | I76: 1.825 | J76: 1.89 | K76: 1.915 | L76: 1.955 | M76: 1.985 | N76: 1.985 | O76: 1.985 | P76: 1.97 | Q76: 1.965 | R76: 1.95 | S76: 1.92 | T76: 1.92 | U76: 1.92 | V76: 1.92 | W76: 1.92 | X76: 1.92 | Y76: 1.92 | Z76: 1.92 | AA76: 1.92 | AB76: 1.92 | AC76: 1.92 | AD76: 1.92 | AE76: 1.92
B77: Italy | C77: 8.47 | D77: 5.76 | E77: 1.535 | F77: 1.865 | G77: 1.73 | H77: 1.775 | I77: 1.805 | J77: 1.795 | K77: 1.8 | L77: 1.825 | M77: 1.865 | N77: 1.9 | O77: 1.92 | P77: 1.945 | Q77: 1.945 | R77: 1.95 | S77: 1.95 | T77: 1.95 | U77: 1.955 | V77: 1.955 | W77: 1.96 | X77: 1.97 | Y77: 1.985 | Z77: 1.97 | AA77: 1.955 | AB77: 1.94 | AC77: 1.945 | AD77: 1.95 | AE77: 1.95
B78: Malta | C78: 6.13 | D78: 5.56 | E78: 2.78 | F78: 1.965 | G78: 1.9 | H78: 1.855 | I78: 1.89 | J78: 1.9 | K78: 1.905 | L78: 1.935 | M78: 1.94 | N78: 1.945 | O78: 1.94 | P78: 1.93 | Q78: 1.925 | R78: 1.925 | S78: 1.925 | T78: 1.92 | U78: 1.92 | V78: 1.925 | W78: 1.925 | X78: 1.925 | Y78: 1.925 | Z78: 1.925 | AA78: 1.93 | AB78: 1.935 | AC78: 1.935 | AD78: 1.935 | AE78: 1.94
B79: Netherlands | C79: 10.82 | D79: 3.97 | E79: 2.125 | F79: 1.825 | G79: 1.725 | H79: 1.86 | I79: 1.995 | J79: 2 | K79: 2.015 | L79: 2 | M79: 2.015 | N79: 2.055 | O79: 2.055 | P79: 2.06 | Q79: 2.065 | R79: 2.065 | S79: 2.06 | T79: 2.06 | U79: 2.06 | V79: 2.045 | W79: 2.02 | X79: 2.04 | Y79: 2 | Z79: 2.015 | AA79: 2.025 | AB79: 2.01 | AC79: 1.985 | AD79: 1.975 | AE79: 1.985
B80: Portugal | C80: 7.96 | D80: 4.79 | E80: 2.285 | F80: 1.93 | G80: 1.725 | H80: 1.795 | I80: 1.74 | J80: 1.765 | K80: 1.825 | L80: 1.85 | M80: 1.86 | N80: 1.89 | O80: 1.905 | P80: 1.915 | Q80: 1.905 | R80: 1.91 | S80: 1.925 | T80: 1.92 | U80: 1.915 | V80: 1.925 | W80: 1.935 | X80: 1.95 | Y80: 1.955 | Z80: 1.97 | AA80: 1.96 | AB80: 1.97 | AC80: 1.975 | AD80: 1.98 | AE80: 1.995
... B84: Luxembourg | C84: 7.25 | D84: 3.33 | E84: 2.195 | F84: 1.9 | G84: 2.005 | H84: 2.22 | I84: 2.245 | J84: 2.175 | K84: 2.07 | L84: 2.115 | M84: 2.135 | N84: 2.19 | O84: 2.15 | P84: 2.14 | Q84: 2.105 | R84: 2.065 | S84: 2.03 | T84: 2.01 | U84: 2.025 | V84: 2.01 | W84: 1.975 | X84: 1.975 | Y84: 1.975 | Z84: 1.97 | AA84: 1.98 | AB84: 1.995 | AC84: 1.985 | AD84: 1.985 | AE84: 1.995
B86: /1 Inflation is measured as the percentage change between the average level of the consumer price index in one year compared to the previous year.

Sheet BB FX
B2: Exchange Rates
B3: Last updated 29/03/2023
B6: Currency against the US$ | C6: 2022 | D6: 2023 | E6: 2024 | F6: 2025 | G6: 2026 | H6: 2027 | I6: 2028 | J6: 2029 | K6: 2030 | L6: 2031 | M6: 2032 | N6: 2033 | O6: 2034 | P6: 2035 | Q6: 2036 | R6: 2037 | S6: 2038 | T6: 2039 | U6: 2040 | V6: 2041 | W6: 2042 | X6: 2043 | Y6: 2044 | Z6: 2045 | AA6: 2046 | AB6: 2047 | AC6: 2048 | AD6: 2049 | AE6: 2050
B8: Algeria | C8: 142.01 | D8: 135.84 | E8: 137 | F8: 141.54 | G8: 146.17 | H8: 149.7 | I8: 151.42 | J8: 153.23 | K8: 154.36 | L8: 155.72 | M8: 157.08 | N8: 158.65 | O8: 160.26 | P8: 161.94 | Q8: 163.44 | R8: 164.84 | S8: 166.21 | T8: 167.53 | U8: 168.78 | V8: 169.94 | W8: 170.96 | X8: 171.76 | Y8: 172.36 | Z8: 172.83 | AA8: 173.25 | AB8: 173.65 | AC8: 174.08 | AD8: 174.55 | AE8: 175.1
B9: Angola | C9: 460.52 | D9: 684.96 | E9: 839.23 | F9: 859.49 | G9: 889.53 | H9: 924.17 | I9: 961.24 | J9: 1001.33 | K9: 1043.2 | L9: 1086.2 | M9: 1130.81 | N9: 1177.22 | O9: 1225.4 | P9: 1275.79 | Q9: 1326.3 | R9: 1376.4 | S9: 1427.12 | T9: 1478.75 | U9: 1531.72 | V9: 1586.32 | W9: 1642.8 | X9: 1701.35 | Y9: 1762.2 | Z9: 1825.54 | AA9: 1891.55 | AB9: 1960.38 | AC9: 2032.24 | AD9: 2107.28 | AE9: 2185.66
B10: Argentina | C10: 130.71 | D10: 296.52 | E10: 1300.83 | F10: 2102.32 | G10: 2469.75 | H10: 2634.49 | I10: 2619.77 | J10: 2529.02 | K10: 2433.57 | L10: 2355.59 | M10: 2301.7 | N10: 2263.18 | O10: 2230.27 | P10: 2202.11 | Q10: 2174.85 | R10: 2146.67 | S10: 2119.45 | T10: 2094.98 | U10: 2074.84 | V10: 2059.63 | W10: 2049.74 | X10: 2045.14 | Y10: 2045.66 | Z10: 2051.4 | AA10: 2062.72 | AB10: 2080.18 | AC10: 2103.98 | AD10: 2134.13 | AE10: 2169.77
B11: Australia | C11: 1.44 | D11: 1.51 | E11: 1.49 | F11: 1.42 | G11: 1.39 | H11: 1.37 | I11: 1.35 | J11: 1.35 | K11: 1.34 | L11: 1.34 | M11: 1.34 | N11: 1.34 | O11: 1.34 | P11: 1.35 | Q11: 1.35 | R11: 1.35 | S11: 1.35 | T11: 1.35 | U11: 1.35 | V11: 1.35 | W11: 1.35 | X11: 1.36 | Y11: 1.36 | Z11: 1.36 | AA11: 1.36 | AB11: 1.36 | AC11: 1.36 | AD11: 1.36 | AE11: 1.36
B12: Azerbaijan | C12: 1.7 | D12: 1.7 | E12: 1.7 | F12: 1.7 | G12: 1.84 | H12: 1.85 | I12: 1.86 | J12: 1.88 | K12: 1.92 | L12: 1.95 | M12: 1.97 | N12: 2 | O12: 2.03 | P12: 2.06 | Q12: 2.09 | R12: 2.12 | S12: 2.15 | T12: 2.18 | U12: 2.21 | V12: 2.25 | W12: 2.28 | X12: 2.32 | Y12: 2.35 | Z12: 2.39 | AA12: 2.43 | AB12: 2.46 | AC12: 2.5 | AD12: 2.53 | AE12: 2.57
B13: Bangladesh | C13: 92.19 | D13: 107.34 | E13: 111.47 | F13: 113.31 | G13: 117.02 | H13: 121.15 | I13: 125.17 | J13: 129.18 | K13: 133.15 | L13: 137.15 | M13: 141.21 | N13: 145.37 | O13: 149.63 | P13: 154.01 | Q13: 158.55 | R13: 163.23 | S13: 168.03 | T13: 172.97 | U13: 178.03 | V13: 183.21 | W13: 188.51 | X13: 193.94 | Y13: 199.51 | Z13: 205.2 | AA13: 211.03 | AB13: 217 | AC13: 223.11 | AD13: 229.36 | AE13: 235.76
B14: Brazil | C14: 5.17 | D14: 5 | E14: 5.02 | F14: 5.14 | G14: 5.21 | H14: 5.29 | I14: 5.36 | J14: 5.43 | K14: 5.5 | L14: 5.56 | M14: 5.63 | N14: 5.69 | O14: 5.75 | P14: 5.82 | Q14: 5.88 | R14: 5.94 | S14: 6.01 | T14: 6.07 | U14: 6.14 | V14: 6.2 | W14: 6.26 | X14: 6.33 | Y14: 6.39 | Z14: 6.45 | AA14: 6.51 | AB14: 6.58 | AC14: 6.64 | AD14: 6.7 | AE14: 6.77
B15: Canada | C15: 1.3 | D15: 1.35 | E15: 1.33 | F15: 1.28 | G15: 1.23 | H15: 1.22 | I15: 1.22 | J15: 1.22 | K15: 1.22 | L15: 1.21 | M15: 1.21 | N15: 1.21 | O15: 1.21 | P15: 1.21 | Q15: 1.21 | R15: 1.2 | S15: 1.2 | T15: 1.2 | U15: 1.2 | V15: 1.2 | W15: 1.2 | X15: 1.19 | Y15: 1.19 | Z15: 1.19 | AA15: 1.19 | AB15: 1.19 | AC15: 1.18 | AD15: 1.18 | AE15: 1.18
B16: China | C16: 6.73 | D16: 7.08 | E16: 7.1 | F16: 6.73 | G16: 6.47 | H16: 6.36 | I16: 6.27 | J16: 6.26 | K16: 6.29 | L16: 6.31 | M16: 6.32 | N16: 6.32 | O16: 6.32 | P16: 6.32 | Q16: 6.31 | R16: 6.31 | S16: 6.3 | T16: 6.29 | U16: 6.29 | V16: 6.28 | W16: 6.28 | X16: 6.27 | Y16: 6.27 | Z16: 6.27 | AA16: 6.28 | AB16: 6.28 | AC16: 6.28 | AD16: 6.29 | AE16: 6.29
B17: Colombia | C17: 4255.35 | D17: 4326.7 | E17: 4055.51 | F17: 4194.74 | G17: 4210.75 | H17: 4202.49 | I17: 4210.64 | J17: 4219.2 | K17: 4229.07 | L17: 4242.93 | M17: 4261.42 | N17: 4285.03 | O17: 4312.48 | P17: 4342.82 | Q17: 4374.27 | R17: 4407.19 | S17: 4441.23 | T17: 4476.14 | U17: 4512.45 | V17: 4550.05 | W17: 4589.49 | X17: 4629.53 | Y17: 4669.54 | Z17: 4710.08 | AA17: 4751.97 | AB17: 4794.28 | AC17: 4837.04 | AD17: 4880.27 | AE17: 4924.68
B18: Czech Republic | C18: 23.36 | D18: 22.2 | E18: 22.81 | F18: 21.99 | G18: 21.08 | H18: 20.41 | I18: 19.91 | J18: 19.48 | K18: 19.19 | L18: 19.02 | M18: 18.91 | N18: 18.82 | O18: 18.73 | P18: 18.66 | Q18: 18.58 | R18: 18.51 | S18: 18.45 | T18: 18.4 | U18: 18.35 | V18: 18.3 | W18: 18.25 | X18: 18.2 | Y18: 18.16 | Z18: 18.11 | AA18: 18.06 | AB18: 18.01 | AC18: 17.96 | AD18: 17.92 | AE18: 17.87
... B42: Romania | C42: 4.69 | D42: 4.57 | E42: 4.58 | F42: 4.55 | G42: 4.48 | H42: 4.37 | I42: 4.29 | J42: 4.21 | K42: 4.18 | L42: 4.16 | M42: 4.14 | N42: 4.13 | O42: 4.13 | P42: 4.12 | Q42: 4.12 | R42: 4.12 | S42: 4.12 | T42: 4.12 | U42: 4.12 | V42: 4.12 | W42: 4.12 | X42: 4.12 | Y42: 4.12 | Z42: 4.12 | AA42: 4.12 | AB42: 4.12 | AC42: 4.12 | AD42: 4.12 | AE42: 4.12
B43: Russia
B44: Saudi Arabia | C44: 3.75 | D44: 3.75 | E44: 3.75 | F44: 3.75 | G44: 3.75 | H44: 3.75 | I44: 3.75 | J44: 3.75 | K44: 3.75 | L44: 3.75 | M44: 3.75 | N44: 3.75 | O44: 3.75 | P44: 3.75 | Q44: 3.75 | R44: 3.75 | S44: 3.75 | T44: 3.75 | U44: 3.75 | V44: 3.75 | W44: 3.75 | X44: 3.75 | Y44: 3.75 | Z44: 3.75 | AA44: 3.75 | AB44: 3.75 | AC44: 3.75 | AD44: 3.75 | AE44: 3.75
B45: Singapore | C45: 1.38 | D45: 1.34 | E45: 1.34 | F45: 1.31 | G45: 1.31 | H45: 1.29 | I45: 1.28 | J45: 1.27 | K45: 1.26 | L45: 1.26 | M45: 1.25 | N45: 1.25 | O45: 1.24 | P45: 1.24 | Q45: 1.23 | R45: 1.23 | S45: 1.23 | T45: 1.22 | U45: 1.22 | V45: 1.22 | W45: 1.21 | X45: 1.21 | Y45: 1.21 | Z45: 1.2 | AA45: 1.2 | AB45: 1.19 | AC45: 1.19 | AD45: 1.19 | AE45: 1.18
B46: South Africa | C46: 16.37 | D46: 18.46 | E46: 18.81 | F46: 18.95 | G46: 19.37 | H46: 19.89 | I46: 20.44 | J46: 20.97 | K46: 21.5 | L46: 22.02 | M46: 22.44 | N46: 22.88 | O46: 23.38 | P46: 23.97 | Q46: 24.64 | R46: 25.34 | S46: 26.04 | T46: 26.72 | U46: 27.41 | V46: 28.09 | W46: 28.79 | X46: 29.49 | Y46: 30.21 | Z46: 30.94 | AA46: 31.68 | AB46: 32.44 | AC46: 33.21 | AD46: 34 | AE46: 34.81
B47: South Korea | C47: 1291.81 | D47: 1305.67 | E47: 1302.6 | F47: 1240.59 | G47: 1204.88 | H47: 1181.31 | I47: 1169.88 | J47: 1166.52 | K47: 1166.21 | L47: 1165.56 | M47: 1164.6 | N47: 1163.27 | O47: 1161.88 | P47: 1160.24 | Q47: 1158.41 | R47: 1156.42 | S47: 1154.26 | T47: 1151.98 | U47: 1149.34 | V47: 1146.2 | W47: 1143.1 | X47: 1139.88 | Y47: 1136.56 | Z47: 1133.21 | AA47: 1129.77 | AB47: 1126.38 | AC47: 1123.05 | AD47: 1119.8 | AE47: 1116.63
B48: Sweden | C48: 10.11 | D48: 10.61 | E48: 10.28 | F48: 9.9 | G48: 9.37 | H48: 8.83 | I48: 8.48 | J48: 8.31 | K48: 8.21 | L48: 8.16 | M48: 8.14 | N48: 8.12 | O48: 8.11 | P48: 8.11 | Q48: 8.1 | R48: 8.09 | S48: 8.09 | T48: 8.08 | U48: 8.08 | V48: 8.07 | W48: 8.07 | X48: 8.06 | Y48: 8.05 | Z48: 8.05 | AA48: 8.04 | AB48: 8.04 | AC48: 8.03 | AD48: 8.03 | AE48: 8.02
B49: Switzerland | C49: 0.96 | D49: 0.9 | E49: 0.88 | F49: 0.88 | G49: 0.87 | H49: 0.85 | I49: 0.84 | J49: 0.83 | K49: 0.82 | L49: 0.82 | M49: 0.81 | N49: 0.81 | O49: 0.8 | P49: 0.8 | Q49: 0.79 | R49: 0.79 | S49: 0.78 | T49: 0.78 | U49: 0.78 | V49: 0.77 | W49: 0.77 | X49: 0.76 | Y49: 0.76 | Z49: 0.75 | AA49: 0.75 | AB49: 0.75 | AC49: 0.74 | AD49: 0.74 | AE49: 0.73
B50: Taiwan | C50: 29.8 | D50: 31.16 | E50: 31.07 | F50: 29.66 | G50: 28.62 | H50: 28.01 | I50: 27.81 | J50: 27.68 | K50: 27.58 | L50: 27.49 | M50: 27.41 | N50: 27.34 | O50: 27.26 | P50: 27.18 | Q50: 27.11 | R50: 27.04 | S50: 26.97 | T50: 26.89 | U50: 26.82 | V50: 26.73 | W50: 26.65 | X50: 26.56 | Y50: 26.49 | Z50: 26.41 | AA50: 26.34 | AB50: 26.28 | AC50: 26.21 | AD50: 26.15 | AE50: 26.09
B51: Thailand | C51: 35.07 | D51: 34.81 | E51: 35.06 | F51: 34.25 | G51: 33.92 | H51: 33.58 | I51: 33.31 | J51: 33.07 | K51: 32.87 | L51: 32.71 | M51: 32.57 | N51: 32.44 | O51: 32.33 | P51: 32.22 | Q51: 32.12 | R51: 32.03 | S51: 31.95 | T51: 31.88 | U51: 31.83 | V51: 31.77 | W51: 31.73 | X51: 31.7 | Y51: 31.67 | Z51: 31.64 | AA51: 31.63 | AB51: 31.61 | AC51: 31.59 | AD51: 31.58 | AE51: 31.57
B52: Trinidad | C52: 6.76 | D52: 6.75 | E52: 6.75 | F52: 6.77 | G52: 6.81 | H52: 6.85 | I52: 6.89 | J52: 6.94 | K52: 6.98 | L52: 7.03 | M52: 7.09 | N52: 7.14 | O52: 7.19 | P52: 7.25 | Q52: 7.3 | R52: 7.35 | S52: 7.41 | T52: 7.47 | U52: 7.52 | V52: 7.58 | W52: 7.64 | X52: 7.69 | Y52: 7.75 | Z52: 7.81 | AA52: 7.87 | AB52: 7.93 | AC52: 7.99 | AD52: 8.05 | AE52: 8.11
B53: Turkey | C53: 16.57 | D53: 23.75 | E53: 32.91 | F53: 35.86 | G53: 38.05 | H53: 40.48 | I53: 43.12 | J53: 45.41 | K53: 47.18 | L53: 48.63 | M53: 50.15 | N53: 51.64 | O53: 53.12 | P53: 54.62 | Q53: 56.15 | R53: 57.63 | S53: 59.06 | T53: 60.54 | U53: 62.16 | V53: 63.93 | W53: 65.63 | X53: 67.17 | Y53: 68.62 | Z53: 70.06 | AA53: 71.57 | AB53: 73.12 | AC53: 74.66 | AD53: 76.14 | AE53: 77.62
B54: Ukraine | C54: 32.32 | D54: 36.57 | E54: 38.98 | F54: 40.56 | G54: 40.73 | H54: 40.52 | I54: 39.53 | J54: 38.72 | K54: 38.32 | L54: 38.19 | M54: 37.95 | N54: 38.16 | O54: 38.49 | P54: 38.89 | Q54: 39.29 | R54: 39.59 | S54: 40.11 | T54: 40.84 | U54: 41.71 | V54: 42.55 | W54: 43.25 | X54: 43.98 | Y54: 44.68 | Z54: 45.37 | AA54: 45.99 | AB54: 46.62 | AC54: 47.23 | AD54: 47.89 | AE54: 48.59
B55: United Arab Emirates | C55: 3.67 | D55: 3.67 | E55: 3.67 | F55: 3.67 | G55: 3.67 | H55: 3.67 | I55: 3.67 | J55: 3.67 | K55: 3.67 | L55: 3.67 | M55: 3.67 | N55: 3.67 | O55: 3.67 | P55: 3.67 | Q55: 3.67 | R55: 3.67 | S55: 3.67 | T55: 3.67 | U55: 3.67 | V55: 3.67 | W55: 3.67 | X55: 3.67 | Y55: 3.67 | Z55: 3.67 | AA55: 3.67 | AB55: 3.67 | AC55: 3.67 | AD55: 3.67 | AE55: 3.67
... B66: Senegal | C66: 623.77 | D66: 606.61 | E66: 597.73 | F66: 586.29 | G66: 572.83 | H66: 562.53 | I66: 554.92 | J66: 548.02 | K66: 543.39 | L66: 541.36 | M66: 540.71 | N66: 540.47 | O66: 540.33 | P66: 540.24 | Q66: 540.17 | R66: 540.11 | S66: 540.04 | T66: 539.97 | U66: 539.93 | V66: 539.89 | W66: 539.86 | X66: 539.83 | Y66: 539.79 | Z66: 539.76 | AA66: 539.73 | AB66: 539.69 | AC66: 539.66 | AD66: 539.63 | AE66: 539.59
B67: Iceland | D67: 137.09 | E67: 133.09 | F67: 131.47 | G67: 129.54 | H67: 127.73 | I67: 125.93 | J67: 124 | K67: 122.55 | L67: 122.48 | M67: 122.42 | N67: 122.35 | O67: 122.29 | P67: 122.23 | Q67: 122.16 | R67: 122.1 | S67: 122.04 | T67: 121.97 | U67: 121.91 | V67: 121.85 | W67: 121.78 | X67: 121.72 | Y67: 121.66 | Z67: 121.59 | AA67: 121.53 | AB67: 121.47 | AC67: 121.4 | AD67: 121.34 | AE67: 121.28
B69: Note: Due to current sanctions there is no meaningful exchange rate for the Russian Rouble. Contact Victoria Barthelmess for more information.

Sheet countries
C1: country1 | D1: country2 | E1: Currency | F1: Currency Code
C2: Albania | D2: Albania | E2: Albanian lek | F2: ALL
C3: Algeria | D3: Algeria | E3: Algerian dinar | F3: DZD
C4: Angola | D4: Angola | E4: Angolan kwanza | F4: AOA
C5: Argentina | D5: Argentina | E5: Argentine peso | F5: ARS
C6: Australia | D6: Australia | E6: Australian dollar | F6: AUD
C7: Austria | D7: Euro area | E7: Euro | F7: EUR
C8: Azerbaijan | D8: Azerbaijan | E8: Azerbaijani manat | F8: AZN
C9: Bangladesh | D9: Bangladesh | E9: Bangladeshi taka | F9: BDT
C10: Belgium | D10: Euro area | E10: Euro | F10: EUR
C11: Brazil | D11: Brazil | E11: Brazilian real | F11: BRL
C12: Canada | D12: Canada | E12: Canadian dollar | F12: CAD
... C75: Vietnam | D75: Vietnam | E75: Vietnamese dong | F75: VND

Sheet tax rates
B2: Tax rates
B6: % change on previous year/1 | C6: 2022 | D6: 2023 | E6: 2024 | F6: 2025 | G6: 2026 | H6: 2027 | I6: 2028 | J6: 2029 | K6: 2030 | L6: 2031 | M6: 2032 | N6: 2033 | O6: 2034 | P6: 2035 | Q6: 2036 | R6: 2037 | S6: 2038 | T6: 2039 | U6: 2040 | V6: 2041 | W6: 2042 | X6: 2043 | Y6: 2044 | Z6: 2045 | AA6: 2046 | AB6: 2047 | AC6: 2048 | AD6: 2049 | AE6: 2050 | AF6: info
B7: Algeria | C7: 26 | D7: =C7 -> 26 | E7: =D7 -> 26 | F7: =E7 -> 26 | G7: =F7 -> 26 | H7: =G7 -> 26 | I7: =H7 -> 26 | J7: =I7 -> 26 | K7: =J7 -> 26 | ... AE7: =AD7 -> 26 | AF7: KPMG
B8: Australia | C8: 30 | D8: 30 | E8: 30 | F8: 30 | G8: 30 | H8: 30 | I8: 30 | J8: 30 | K8: 30 | L8: 30 | M8: 30 | N8: 30 | O8: 30 | P8: 30 | Q8: 30 | R8: 30 | S8: 30 | T8: 30 | U8: 30 | V8: 30 | W8: 30 | X8: 30 | Y8: 30 | Z8: 30 | AA8: 30 | AB8: 30 | AC8: 30 | AD8: 30 | AE8: 30 | AF8: BP tax - 2023
B9: Azerbaijan | C9: 20 | D9: =C9 -> 20 | E9: =D9 -> 20 | F9: =E9 -> 20 | G9: =F9 -> 20 | H9: =G9 -> 20 | I9: =H9 -> 20 | J9: =I9 -> 20 | K9: =J9 -> 20 | ... AE9: =AD9 -> 20 | AF9: KPMG
B10: Brazil | C10: 34 | D10: =C10 -> 34 | E10: =D10 -> 34 | F10: =E10 -> 34 | G10: =F10 -> 34 | H10: =G10 -> 34 | I10: =H10 -> 34 | J10: =I10 -> 34 | K10: =J10 -> 34 | ... AE10: =AD10 -> 34 | AF10: KPMG
B11: Canada | C11: 26.21 | D11: =C11 -> 26.21 | E11: =D11 -> 26.21 | F11: =E11 -> 26.21 | G11: =F11 -> 26.21 | H11: =G11 -> 26.21 | I11: =H11 -> 26.21 | J11: =I11 -> 26.21 | K11: =J11 -> 26.21 | ... AE11: =AD11 -> 26.21 | AF11: KPMG
B12: China | C12: 25 | D12: =C12 -> 25 | E12: =D12 -> 25 | F12: =E12 -> 25 | G12: =F12 -> 25 | H12: =G12 -> 25 | I12: =H12 -> 25 | J12: =I12 -> 25 | K12: =J12 -> 25 | ... AE12: =AD12 -> 25 | AF12: KPMG
B13: Czech Republic | C13: 19 | D13: =C13 -> 19 | E13: =D13 -> 19 | F13: =E13 -> 19 | G13: =F13 -> 19 | H13: =G13 -> 19 | I13: =H13 -> 19 | J13: =I13 -> 19 | K13: =J13 -> 19 | ... AE13: =AD13 -> 19 | AF13: KPMG
B14: Denmark | C14: 22 | D14: =C14 -> 22 | E14: =D14 -> 22 | F14: =E14 -> 22 | G14: =F14 -> 22 | H14: =G14 -> 22 | I14: =H14 -> 22 | J14: =I14 -> 22 | K14: =J14 -> 22 | ... AE14: =AD14 -> 22 | AF14: KPMG
B15: Egypt | C15: 22.5 | D15: =C15 -> 22.5 | E15: =D15 -> 22.5 | F15: =E15 -> 22.5 | G15: =F15 -> 22.5 | H15: =G15 -> 22.5 | I15: =H15 -> 22.5 | J15: =I15 -> 22.5 | K15: =J15 -> 22.5 | ... AE15: =AD15 -> 22.5 | AF15: KPMG
B16: Euro area | C16: 25 | D16: 25 | E16: 25 | F16: 25 | G16: 25 | H16: 25 | I16: 25 | J16: 25 | K16: 25 | L16: 25 | M16: 25 | N16: 25 | O16: 25 | P16: 25 | Q16: 25 | R16: 25 | S16: 25 | T16: 25 | U16: 25 | V16: 25 | W16: 25 | X16: 25 | Y16: 25 | Z16: 25 | AA16: 25 | AB16: 25 | AC16: 25 | AD16: 25 | AE16: 25 | AF16: BP tax - 2023
B17: Georgia | C17: 15 | D17: =C17 -> 15 | E17: =D17 -> 15 | F17: =E17 -> 15 | G17: =F17 -> 15 | H17: =G17 -> 15 | I17: =H17 -> 15 | J17: =I17 -> 15 | K17: =J17 -> 15 | ... AE17: =AD17 -> 15 | AF17: KPMG
B18: Hungary | C18: 9 | D18: 9 | E18: 15 | F18: 15 | G18: 15 | H18: 15 | I18: 15 | J18: 15 | K18: 15 | L18: 15 | M18: 15 | N18: 15 | O18: 15 | P18: 15 | Q18: 15 | R18: 15 | S18: 15 | T18: 15 | U18: 15 | V18: 15 | W18: 15 | X18: 15 | Y18: 15 | Z18: 15 | AA18: 15 | AB18: 15 | AC18: 15 | AD18: 15 | AE18: 15 | AF18: BP tax - 2023
B19: India | C19: 25.17 | D19: 25.17 | E19: 25.17 | F19: 25.17 | G19: 25.17 | H19: 25.17 | I19: 25.17 | J19: 25.17 | K19: 25.17 | L19: 25.17 | M19: 25.17 | N19: 25.17 | O19: 25.17 | P19: 25.17 | Q19: 25.17 | R19: 25.17 | S19: 25.17 | T19: 25.17 | U19: 25.17 | V19: 25.17 | W19: 25.17 | X19: 25.17 | Y19: 25.17 | Z19: 25.17 | AA19: 25.17 | AB19: 25.17 | AC19: 25.17 | AD19: 25.17 | AE19: 25.17 | AF19: BP tax - 2023
B20: Indonesia | C20: 22 | D20: =C20 -> 22 | E20: =D20 -> 22 | F20: =E20 -> 22 | G20: =F20 -> 22 | H20: =G20 -> 22 | I20: =H20 -> 22 | J20: =I20 -> 22 | K20: =J20 -> 22 | ... AE20: =AD20 -> 22 | AF20: KPMG
B21: Iraq | C21: 15 | D21: =C21 -> 15 | E21: =D21 -> 15 | F21: =E21 -> 15 | G21: =F21 -> 15 | H21: =G21 -> 15 | I21: =H21 -> 15 | J21: =I21 -> 15 | K21: =J21 -> 15 | ... AE21: =AD21 -> 15 | AF21: KPMG
B22: Japan | C22: 30.62 | D22: =C22 -> 30.62 | E22: =D22 -> 30.62 | F22: =E22 -> 30.62 | G22: =F22 -> 30.62 | H22: =G22 -> 30.62 | I22: =H22 -> 30.62 | J22: =I22 -> 30.62 | K22: =J22 -> 30.62 | ... AE22: =AD22 -> 30.62 | AF22: KPMG
B23: Jordan | C23: 20 | D23: =C23 -> 20 | E23: =D23 -> 20 | F23: =E23 -> 20 | G23: =F23 -> 20 | H23: =G23 -> 20 | I23: =H23 -> 20 | J23: =I23 -> 20 | K23: =J23 -> 20 | ... AE23: =AD23 -> 20 | AF23: KPMG
B24: Kazakhstan | C24: 20 | D24: =C24 -> 20 | E24: =D24 -> 20 | F24: =E24 -> 20 | G24: =F24 -> 20 | H24: =G24 -> 20 | I24: =H24 -> 20 | J24: =I24 -> 20 | K24: =J24 -> 20 | ... AE24: =AD24 -> 20 | AF24: KPMG
B25: Kuwait | C25: 15 | D25: =C25 -> 15 | E25: =D25 -> 15 | F25: =E25 -> 15 | G25: =F25 -> 15 | H25: =G25 -> 15 | I25: =H25 -> 15 | J25: =I25 -> 15 | K25: =J25 -> 15 | ... AE25: =AD25 -> 15 | AF25: KPMG
B26: Libya | C26: 20 | D26: =C26 -> 20 | E26: =D26 -> 20 | F26: =E26 -> 20 | G26: =F26 -> 20 | H26: =G26 -> 20 | I26: =H26 -> 20 | J26: =I26 -> 20 | K26: =J26 -> 20 | ... AE26: =AD26 -> 20 | AF26: KPMG
B27: Malaysia | C27: 24 | D27: 24 | E27: 24 | F27: 24 | G27: 24 | H27: 24 | I27: 24 | J27: 24 | K27: 24 | L27: 24 | M27: 24 | N27: 24 | O27: 24 | P27: 24 | Q27: 24 | R27: 24 | S27: 24 | T27: 24 | U27: 24 | V27: 24 | W27: 24 | X27: 24 | Y27: 24 | Z27: 24 | AA27: 24 | AB27: 24 | AC27: 24 | AD27: 24 | AE27: 24 | AF27: BP tax - 2023
B28: Mexico | C28: 30 | D28: =C28 -> 30 | E28: =D28 -> 30 | F28: =E28 -> 30 | G28: =F28 -> 30 | H28: =G28 -> 30 | I28: =H28 -> 30 | J28: =I28 -> 30 | K28: =J28 -> 30 | ... AE28: =AD28 -> 30 | AF28: KPMG
B29: Mozambique | C29: 32 | D29: =C29 -> 32 | E29: =D29 -> 32 | F29: =E29 -> 32 | G29: =F29 -> 32 | H29: =G29 -> 32 | I29: =H29 -> 32 | J29: =I29 -> 32 | K29: =J29 -> 32 | ... AE29: =AD29 -> 32 | AF29: KPMG
B30: New Zealand | C30: 28 | D30: 28 | E30: 28 | F30: 28 | G30: 28 | H30: 28 | I30: 28 | J30: 28 | K30: 28 | L30: 28 | M30: 28 | N30: 28 | O30: 28 | P30: 28 | Q30: 28 | R30: 28 | S30: 28 | T30: 28 | U30: 28 | V30: 28 | W30: 28 | X30: 28 | Y30: 28 | Z30: 28 | AA30: 28 | AB30: 28 | AC30: 28 | AD30: 28 | AE30: 28 | AF30: BP tax - 2023
B31: Nigeria | C31: 30 | D31: =C31 -> 30 | E31: =D31 -> 30 | F31: =E31 -> 30 | G31: =F31 -> 30 | H31: =G31 -> 30 | I31: =H31 -> 30 | J31: =I31 -> 30 | K31: =J31 -> 30 | ... AE31: =AD31 -> 30 | AF31: KPMG
B32: Norway | C32: 22 | D32: =C32 -> 22 | E32: =D32 -> 22 | F32: =E32 -> 22 | G32: =F32 -> 22 | H32: =G32 -> 22 | I32: =H32 -> 22 | J32: =I32 -> 22 | K32: =J32 -> 22 | ... AE32: =AD32 -> 22 | AF32: KPMG
B33: Oman | C33: 15 | D33: =C33 -> 15 | E33: =D33 -> 15 | F33: =E33 -> 15 | G33: =F33 -> 15 | H33: =G33 -> 15 | I33: =H33 -> 15 | J33: =I33 -> 15 | K33: =J33 -> 15 | ... AE33: =AD33 -> 15 | AF33: KPMG
B34: Philippines | C34: 25 | D34: =C34 -> 25 | E34: =D34 -> 25 | F34: =E34 -> 25 | G34: =F34 -> 25 | H34: =G34 -> 25 | I34: =H34 -> 25 | J34: =I34 -> 25 | K34: =J34 -> 25 | ... AE34: =AD34 -> 25 | AF34: KPMG
B35: Poland | C35: 19 | D35: 19 | E35: 19 | F35: 19 | G35: 19 | H35: 19 | I35: 19 | J35: 19 | K35: 19 | L35: 19 | M35: 19 | N35: 19 | O35: 19 | P35: 19 | Q35: 19 | R35: 19 | S35: 19 | T35: 19 | U35: 19 | V35: 19 | W35: 19 | X35: 19 | Y35: 19 | Z35: 19 | AA35: 19 | AB35: 19 | AC35: 19 | AD35: 19 | AE35: 19 | AF35: BP tax - 2023
B36: Romania | C36: 16 | D36: =C36 -> 16 | E36: =D36 -> 16 | F36: =E36 -> 16 | G36: =F36 -> 16 | H36: =G36 -> 16 | I36: =H36 -> 16 | J36: =I36 -> 16 | K36: =J36 -> 16 | ... AE36: =AD36 -> 16 | AF36: KPMG
B37: Russia | C37: 20 | D37: =C37 -> 20 | E37: =D37 -> 20 | F37: =E37 -> 20 | G37: =F37 -> 20 | H37: =G37 -> 20 | I37: =H37 -> 20 | J37: =I37 -> 20 | K37: =J37 -> 20 | ... AE37: =AD37 -> 20 | AF37: KPMG
B38: Saudi Arabia | C38: 20 | D38: =C38 -> 20 | E38: =D38 -> 20 | F38: =E38 -> 20 | G38: =F38 -> 20 | H38: =G38 -> 20 | I38: =H38 -> 20 | J38: =I38 -> 20 | K38: =J38 -> 20 | ... AE38: =AD38 -> 20 | AF38: KPMG
B39: Singapore | C39: 17 | D39: =C39 -> 17 | E39: =D39 -> 17 | F39: =E39 -> 17 | G39: =F39 -> 17 | H39: =G39 -> 17 | I39: =H39 -> 17 | J39: =I39 -> 17 | K39: =J39 -> 17 | ... AE39: =AD39 -> 17 | AF39: KPMG
B40: South Africa | C40: 28 | D40: =C40 -> 28 | E40: =D40 -> 28 | F40: =E40 -> 28 | G40: =F40 -> 28 | H40: =G40 -> 28 | I40: =H40 -> 28 | J40: =I40 -> 28 | K40: =J40 -> 28 | ... AE40: =AD40 -> 28 | AF40: KPMG
B41: Sweden | C41: 20.6 | D41: =C41 -> 20.6 | E41: =D41 -> 20.6 | F41: =E41 -> 20.6 | G41: =F41 -> 20.6 | H41: =G41 -> 20.6 | I41: =H41 -> 20.6 | J41: =I41 -> 20.6 | K41: =J41 -> 20.6 | ... AE41: =AD41 -> 20.6 | AF41: KPMG
B42: Switzerland | C42: 12 | D42: 12 | E42: 15 | F42: 15 | G42: 15 | H42: 15 | I42: 15 | J42: 15 | K42: 15 | L42: 15 | M42: 15 | N42: 15 | O42: 15 | P42: 15 | Q42: 15 | R42: 15 | S42: 15 | T42: 15 | U42: 15 | V42: 15 | W42: 15 | X42: 15 | Y42: 15 | Z42: 15 | AA42: 15 | AB42: 15 | AC42: 15 | AD42: 15 | AE42: 15 | AF42: BP tax - 2023
B43: Taiwan | C43: 20 | D43: =C43 -> 20 | E43: =D43 -> 20 | F43: =E43 -> 20 | G43: =F43 -> 20 | H43: =G43 -> 20 | I43: =H43 -> 20 | J43: =I43 -> 20 | K43: =J43 -> 20 | ... AE43: =AD43 -> 20 | AF43: KPMG
B44: Thailand | C44: 20 | D44: =C44 -> 20 | E44: =D44 -> 20 | F44: =E44 -> 20 | G44: =F44 -> 20 | H44: =G44 -> 20 | I44: =H44 -> 20 | J44: =I44 -> 20 | K44: =J44 -> 20 | ... AE44: =AD44 -> 20 | AF44: KPMG
B45: Turkey | C45: 20 | D45: 25 | E45: =D45 -> 25 | F45: =E45 -> 25 | G45: =F45 -> 25 | H45: =G45 -> 25 | I45: =H45 -> 25 | J45: =I45 -> 25 | K45: =J45 -> 25 | L45: =K45 -> 25 | ... AE45: =AD45 -> 25 | AF45: KPMG
B46: Ukraine | C46: 18 | D46: =C46 -> 18 | E46: =D46 -> 18 | F46: =E46 -> 18 | G46: =F46 -> 18 | H46: =G46 -> 18 | I46: =H46 -> 18 | J46: =I46 -> 18 | K46: =J46 -> 18 | ... AE46: =AD46 -> 18 | AF46: KPMG
B47: United Arab Emirates | C47: 9 | D47: =C47 -> 9 | E47: =D47 -> 9 | F47: =E47 -> 9 | G47: =F47 -> 9 | H47: =G47 -> 9 | I47: =H47 -> 9 | J47: =I47 -> 9 | K47: =J47 -> 9 | ... AE47: =AD47 -> 9 | AF47: KPMG
B48: United Kingdom | C48: 19 | D48: 23.5 | E48: 25 | F48: 25 | G48: 25 | H48: 25 | I48: 25 | J48: 25 | K48: 25 | L48: 25 | M48: 25 | N48: 25 | O48: 25 | P48: 25 | Q48: 25 | R48: 25 | S48: 25 | T48: 25 | U48: 25 | V48: 25 | W48: 25 | X48: 25 | Y48: 25 | Z48: 25 | AA48: 25 | AB48: 25 | AC48: 25 | AD48: 25 | AE48: 25 | AF48: KPMG
B49: United States | C49: 23.43 | D49: 23.43 | E49: 23.43 | F49: 23.43 | G49: 23.43 | H49: 23.43 | I49: 23.43 | J49: 23.43 | K49: 23.43 | L49: 23.43 | M49: 23.43 | N49: 23.43 | O49: 23.43 | P49: 23.43 | Q49: 23.43 | R49: 23.43 | S49: 23.43 | T49: 23.43 | U49: 23.43 | V49: 23.43 | W49: 23.43 | X49: 23.43 | Y49: 23.43 | Z49: 23.43 | AA49: 23.43 | AB49: 23.43 | AC49: 23.43 | AD49: 23.43 | AE49: 23.43 | AF49: KPMG
B50: Venezuela | C50: 34 | D50: =C50 -> 34 | E50: =D50 -> 34 | F50: =E50 -> 34 | G50: =F50 -> 34 | H50: =G50 -> 34 | I50: =H50 -> 34 | J50: =I50 -> 34 | K50: =J50 -> 34 | ... AE50: =AD50 -> 34 | AF50: KPMG
B51: Vietnam | C51: 20 | D51: =C51 -> 20 | E51: =D51 -> 20 | F51: =E51 -> 20 | G51: =F51 -> 20 | H51: =G51 -> 20 | I51: =H51 -> 20 | J51: =I51 -> 20 | K51: =J51 -> 20 | ... AE51: =AD51 -> 20 | AF51: KPMG
B52: Senegal | C52: 30 | D52: =C52 -> 30 | E52: =D52 -> 30 | F52: =E52 -> 30 | G52: =F52 -> 30 | H52: =G52 -> 30 | I52: =H52 -> 30 | J52: =I52 -> 30 | K52: =J52 -> 30 | ... AE52: =AD52 -> 30 | AF52: KPMG
B53: Albania | C53: 15 | D53: =C53 -> 15 | E53: =D53 -> 15 | F53: =E53 -> 15 | G53: =F53 -> 15 | H53: =G53 -> 15 | I53: =H53 -> 15 | J53: =I53 -> 15 | K53: =J53 -> 15 | ... AE53: =AD53 -> 15 | AF53: KPMG
B54: Chile | C54: 27 | D54: =C54 -> 27 | E54: =D54 -> 27 | F54: =E54 -> 27 | G54: =F54 -> 27 | H54: =G54 -> 27 | I54: =H54 -> 27 | J54: =I54 -> 27 | K54: =J54 -> 27 | ... AE54: =AD54 -> 27 | AF54: KPMG
B55: Peru | C55: 29.5 | D55: =C55 -> 29.5 | E55: =D55 -> 29.5 | F55: =E55 -> 29.5 | G55: =F55 -> 29.5 | H55: =G55 -> 29.5 | I55: =H55 -> 29.5 | J55: =I55 -> 29.5 | K55: =J55 -> 29.5 | ... AE55: =AD55 -> 29.5 | AF55: KPMG
B56: Ghana | C56: 25 | D56: =C56 -> 25 | E56: =D56 -> 25 | F56: =E56 -> 25 | G56: =F56 -> 25 | H56: =G56 -> 25 | I56: =H56 -> 25 | J56: =I56 -> 25 | K56: =J56 -> 25 | ... AE56: =AD56 -> 25 | AF56: KPMG
B57: Austria | C57: 22.94 | D57: 22.98 | E57: 23 | F57: 23 | G57: 23 | H57: 23 | I57: 23 | J57: 23 | K57: 23 | L57: 23 | M57: 23 | N57: 23 | O57: 23 | P57: 23 | Q57: 23 | R57: 23 | S57: 23 | T57: 23 | U57: 23 | V57: 23 | W57: 23 | X57: 23 | Y57: 23 | Z57: 23 | AA57: 23 | AB57: 23 | AC57: 23 | AD57: 23 | AE57: 23 | AF57: BP tax - 2023
B58: Belgium | C58: 25 | D58: 25 | E58: 25 | F58: 25 | G58: 25 | H58: 25 | I58: 25 | J58: 25 | K58: 25 | L58: 25 | M58: 25 | N58: 25 | O58: 25 | P58: 25 | Q58: 25 | R58: 25 | S58: 25 | T58: 25 | U58: 25 | V58: 25 | W58: 25 | X58: 25 | Y58: 25 | Z58: 25 | AA58: 25 | AB58: 25 | AC58: 25 | AD58: 25 | AE58: 25 | AF58: BP tax - 2023
B59: Cyprus | C59: 12.5 | D59: =C59 -> 12.5 | E59: =D59 -> 12.5 | F59: =E59 -> 12.5 | G59: =F59 -> 12.5 | H59: =G59 -> 12.5 | I59: =H59 -> 12.5 | J59: =I59 -> 12.5 | K59: =J59 -> 12.5 | ... AE59: =AD59 -> 12.5 | AF59: KPMG
B60: Finland | C60: 20 | D60: =C60 -> 20 | E60: =D60 -> 20 | F60: =E60 -> 20 | G60: =F60 -> 20 | H60: =G60 -> 20 | I60: =H60 -> 20 | J60: =I60 -> 20 | K60: =J60 -> 20 | ... AE60: =AD60 -> 20 | AF60: KPMG
B61: France | C61: 26.5 | D61: =C61 -> 26.5 | E61: =D61 -> 26.5 | F61: =E61 -> 26.5 | G61: =F61 -> 26.5 | H61: =G61 -> 26.5 | I61: =H61 -> 26.5 | J61: =I61 -> 26.5 | K61: =J61 -> 26.5 | ... AE61: =AD61 -> 26.5 | AF61: KPMG
B62: Germany | C62: 30.02 | D62: 29.98 | E62: 31.01 | F62: 32.1 | G62: 32.1 | H62: 32.1 | I62: 32.1 | J62: 32.1 | K62: 32.1 | L62: 32.1 | M62: 32.1 | N62: 32.1 | O62: 32.1 | P62: 32.1 | Q62: 32.1 | R62: 32.1 | S62: 32.1 | T62: 32.1 | U62: 32.1 | V62: 32.1 | W62: 32.1 | X62: 32.1 | Y62: 32.1 | Z62: 32.1 | AA62: 32.1 | AB62: 32.1 | AC62: 32.1 | AD62: 32.1 | AE62: 32.1 | AF62: BP tax - 2023
B63: Greece | C63: 22 | D63: =C63 -> 22 | E63: =D63 -> 22 | F63: =E63 -> 22 | G63: =F63 -> 22 | H63: =G63 -> 22 | I63: =H63 -> 22 | J63: =I63 -> 22 | K63: =J63 -> 22 | ... AE63: =AD63 -> 22 | AF63: KPMG
B64: Ireland | C64: 12.5 | D64: =C64 -> 12.5 | E64: =D64 -> 12.5 | F64: =E64 -> 12.5 | G64: =F64 -> 12.5 | H64: =G64 -> 12.5 | I64: =H64 -> 12.5 | J64: =I64 -> 12.5 | K64: =J64 -> 12.5 | ... AE64: =AD64 -> 12.5 | AF64: KPMG
B65: Italy | C65: 27.81 | D65: =C65 -> 27.81 | E65: =D65 -> 27.81 | F65: =E65 -> 27.81 | G65: =F65 -> 27.81 | H65: =G65 -> 27.81 | I65: =H65 -> 27.81 | J65: =I65 -> 27.81 | K65: =J65 -> 27.81 | ... AE65: =AD65 -> 27.81 | AF65: KPMG
B66: Malta | C66: 35 | D66: =C66 -> 35 | E66: =D66 -> 35 | F66: =E66 -> 35 | G66: =F66 -> 35 | H66: =G66 -> 35 | I66: =H66 -> 35 | J66: =I66 -> 35 | K66: =J66 -> 35 | ... AE66: =AD66 -> 35 | AF66: KPMG
B67: Netherlands | C67: 25.8 | D67: 25.8 | E67: 25.8 | F67: 25.8 | G67: 25.8 | H67: 25.8 | I67: 25.8 | J67: 25.8 | K67: 25.8 | L67: 25.8 | M67: 25.8 | N67: 25.8 | O67: 25.8 | P67: 25.8 | Q67: 25.8 | R67: 25.8 | S67: 25.8 | T67: 25.8 | U67: 25.8 | V67: 25.8 | W67: 25.8 | X67: 25.8 | Y67: 25.8 | Z67: 25.8 | AA67: 25.8 | AB67: 25.8 | AC67: 25.8 | AD67: 25.8 | AE67: 25.8 | AF67: BP tax - 2023
B68: Portugal | C68: 21 | D68: =C68 -> 21 | E68: =D68 -> 21 | F68: =E68 -> 21 | G68: =F68 -> 21 | H68: =G68 -> 21 | I68: =H68 -> 21 | J68: =I68 -> 21 | K68: =J68 -> 21 | ... AE68: =AD68 -> 21 | AF68: KPMG
B69: Slovenia | C69: 19 | D69: =C69 -> 19 | E69: =D69 -> 19 | F69: =E69 -> 19 | G69: =F69 -> 19 | H69: =G69 -> 19 | I69: =H69 -> 19 | J69: =I69 -> 19 | K69: =J69 -> 19 | ... AE69: =AD69 -> 19 | AF69: KPMG
B70: Spain | C70: 25 | D70: =C70 -> 25 | E70: =D70 -> 25 | F70: =E70 -> 25 | G70: =F70 -> 25 | H70: =G70 -> 25 | I70: =H70 -> 25 | J70: =I70 -> 25 | K70: =J70 -> 25 | ... AE70: =AD70 -> 25 | AF70: KPMG
B71: Global average | C71: 25 | D71: 25 | E71: 25 | F71: 25 | G71: 25 | H71: 25 | I71: 25 | J71: 25 | K71: 25 | L71: 25 | M71: 25 | N71: 25 | O71: 25 | P71: 25 | Q71: 25 | R71: 25 | S71: 25 | T71: 25 | U71: 25 | V71: 25 | W71: 25 | X71: 25 | Y71: 25 | Z71: 25 | AA71: 25 | AB71: 25 | AC71: 25 | AD71: 25 | AE71: 25 | AF71: BP tax - 2023

Sheet Capex&Depr
B1: PT:
C2: Description | D2: Useful life | E2: Currency | F2: ='NPV PT'!D10 -> 2025 | G2: =F2+1 -> 2026 | H2: =G2+1 -> 2027 | I2: =H2+1 -> 2028 | J2: =I2+1 -> 2029 | K2: =J2+1 -> 2030 | L2: =K2+1 -> 2031 | M2: =L2+1 -> 2032 | N2: =M2+1 -> 2033 | ... T2: =S2+1 -> 2039 | U2: =S2+1 -> 2039
B4: Capex 1 | C4: ='Capex Estimate'!C7 -> To supply, install, testing and comissioning of 8 units of in-line labeller, OCR reader and rejection system | D4: 5 | E4: =VLOOKUP('NPV PT'!$C$2,countries!C:F,4,0) -> MYR | F4: =-'Capex Estimate'!F7*1000 -> -2250000
B5: Capex 2 | C5: ='Capex Estimate'!C8 -> LAN cable installation for 8 lines | D5: 5 | E5: =VLOOKUP('NPV PT'!$C$2,countries!C:F,4,0) -> MYR | F5: =-'Capex Estimate'!F8*1000 -> -60000
B6: Capex 3 | C6: ='Capex Estimate'!C13 -> Unallocated Provision (UAP-Contingency) | D6: 5 | E6: =VLOOKUP('NPV PT'!$C$2,countries!C:F,4,0) -> MYR | F6: =-'Capex Estimate'!F13*1000*0.5 -> -69300
B7: Capex 4 | C7: ='Capex Estimate'!C15 -> Additional Unallocated Provision (AUAP) | D7: 5 | E7: =VLOOKUP('NPV PT'!$C$2,countries!C:F,4,0) -> MYR | F7: =-'Capex Estimate'!F15*1000*0.5 -> -23100
B8: Capex 5 | D8: 10 | E8: =VLOOKUP('NPV PT'!$C$2,countries!C:F,4,0) -> MYR
B9: Capex 6 | D9: 15 | E9: =VLOOKUP('NPV PT'!$C$2,countries!C:F,4,0) -> MYR
B10: Capex 7 | D10: 20 | E10: =VLOOKUP('NPV PT'!$C$2,countries!C:F,4,0) -> MYR
B11: Capex 8 | D11: 20 | E11: =VLOOKUP('NPV PT'!$C$2,countries!C:F,4,0) -> MYR
B12: Capex 9 | D12: 25 | E12: =VLOOKUP('NPV PT'!$C$2,countries!C:F,4,0) -> MYR
B13: Capex 10 | D13: 30 | E13: =VLOOKUP('NPV PT'!$C$2,countries!C:F,4,0) -> MYR
F15: * enter the capex amounts as negative numbers
D18: Useful life | E18: Currency | F18: =F2 -> 2025 | G18: =G2 -> 2026 | H18: =H2 -> 2027 | I18: =I2 -> 2028 | J18: =J2 -> 2029 | K18: =K2 -> 2030 | L18: =L2 -> 2031 | M18: =M2 -> 2032 | ... U18: =U2 -> 2039
C20: Depr 1 | D20: =D4 -> 5 | E20: =VLOOKUP('NPV PT'!$C$2,countries!C:F,4,0) -> MYR | F20: 0 | G20: =F4/D20 -> -450000 | H20: =SUM($F4:G4)/$D20 -> -450000 | I20: =SUM($F4:H4)/$D20 -> -450000 | J20: =SUM($F4:I4)/$D20 -> -450000 | K20: =IF(D20>4,SUM($F4:J4)/$D20,SUM($G4:J4)/$D20) -> -450000 | L20: =IF($D20>5,SUM($F4:K4)/$D20,IF($D20>4,SUM(G4:K4)/$D20,SUM(H4:K4)/$D20)) -> 0 | M20: =IF($D20>5,SUM($F4:L4)/$D20,IF($D20>4,SUM(H4:L4)/$D20,SUM(I4:L4)/$D20)) -> 0 | N20: =IF($D20>5,SUM($F4:M4)/$D20,IF($D20>4,SUM(I4:M4)/$D20,SUM(J4:M4)/$D20)) -> 0 | O20: =IF($D20>5,SUM($F4:N4)/$D20,IF($D20>4,SUM(J4:N4)/$D20,SUM(K4:N4)/$D20)) -> 0 | P20: =IF($D20>5,SUM($F4:O4)/$D20,IF($D20>4,SUM(K4:O4)/$D20,SUM(L4:O4)/$D20)) -> 0 | Q20: =IF($D20>10,SUM($F4:P4)/$D20,IF($D20>5,SUM(G4:P4)/$D20,IF($D20>4,SUM(L4:P4)/$D20,SUM(M4:P4)/$D20))) -> 0 | R20: =IF($D20>10,SUM($F4:Q4)/$D20,IF($D20>5,SUM(H4:Q4)/$D20,IF($D20>4,SUM(M4:Q4)/$D20,SUM(N4:Q4)/$D20))) -> 0 | S20: =IF($D20>10,SUM($F4:R4)/$D20,IF($D20>5,SUM(I4:R4)/$D20,IF($D20>4,SUM(N4:R4)/$D20,SUM(O4:R4)/$D20))) -> 0 | T20: =IF($D20>10,SUM($F4:S4)/$D20,IF($D20>5,SUM(J4:S4)/$D20,IF($D20>4,SUM(O4:S4)/$D20,SUM(P4:S4)/$D20))) -> 0 | U20: =IF($D20>10,SUM($F4:T4)/$D20,IF($D20>5,SUM(K4:T4)/$D20,IF($D20>4,SUM(P4:T4)/$D20,SUM(Q4:T4)/$D20))) -> 0
C21: Depr 2 | D21: =D5 -> 5 | E21: =VLOOKUP('NPV PT'!$C$2,countries!C:F,4,0) -> MYR | F21: 0 | G21: =F5/D21 -> -12000 | H21: =SUM($F5:G5)/$D21 -> -12000 | I21: =SUM($F5:H5)/$D21 -> -12000 | J21: =SUM($F5:I5)/$D21 -> -12000 | K21: =IF(D21>4,SUM($F5:J5)/$D21,SUM($G5:J5)/$D21) -> -12000 | L21: =IF(D21>5,SUM($F5:K5)/$D21,IF(D21>4,SUM($G5:K5)/$D21,SUM(H5:K5)/$D21)) -> 0 | M21: =IF($D21>5,SUM($F5:L5)/$D21,IF($D21>4,SUM(H5:L5)/$D21,SUM(I5:L5)/$D21)) -> 0 | N21: =IF($D21>5,SUM($F5:M5)/$D21,IF($D21>4,SUM(I5:M5)/$D21,SUM(J5:M5)/$D21)) -> 0 | O21: =IF($D21>5,SUM($F5:N5)/$D21,IF($D21>4,SUM(J5:N5)/$D21,SUM(K5:N5)/$D21)) -> 0 | P21: =IF($D21>5,SUM($F5:O5)/$D21,IF($D21>4,SUM(K5:O5)/$D21,SUM(L5:O5)/$D21)) -> 0 | Q21: =IF($D21>10,SUM($F5:P5)/$D21,IF($D21>5,SUM(G5:P5)/$D21,IF($D21>4,SUM(L5:P5)/$D21,SUM(M5:P5)/$D21))) -> 0 | R21: =IF($D21>10,SUM($F5:Q5)/$D21,IF($D21>5,SUM(H5:Q5)/$D21,IF($D21>4,SUM(M5:Q5)/$D21,SUM(N5:Q5)/$D21))) -> 0 | S21: =IF($D21>10,SUM($F5:R5)/$D21,IF($D21>5,SUM(I5:R5)/$D21,IF($D21>4,SUM(N5:R5)/$D21,SUM(O5:R5)/$D21))) -> 0 | T21: =IF($D21>10,SUM($F5:S5)/$D21,IF($D21>5,SUM(J5:S5)/$D21,IF($D21>4,SUM(O5:S5)/$D21,SUM(P5:S5)/$D21))) -> 0 | U21: =IF($D21>10,SUM($F5:T5)/$D21,IF($D21>5,SUM(K5:T5)/$D21,IF($D21>4,SUM(P5:T5)/$D21,SUM(Q5:T5)/$D21))) -> 0
C22: Depr 3 | D22: =D6 -> 5 | E22: =VLOOKUP('NPV PT'!$C$2,countries!C:F,4,0) -> MYR | F22: 0 | G22: =F6/D22 -> -13860 | H22: =SUM($F6:G6)/$D22 -> -13860 | I22: =SUM($F6:H6)/$D22 -> -13860 | J22: =SUM($F6:I6)/$D22 -> -13860 | K22: =IF(D22>4,SUM($F6:J6)/$D22,SUM($G6:J6)/$D22) -> -13860 | L22: =IF(D22>5,SUM($F6:K6)/$D22,IF(D22>4,SUM($G6:K6)/$D22,SUM(H6:K6)/$D22)) -> 0 | M22: =IF($D22>5,SUM($F6:L6)/$D22,IF($D22>4,SUM(H6:L6)/$D22,SUM(I6:L6)/$D22)) -> 0 | N22: =IF($D22>5,SUM($F6:M6)/$D22,IF($D22>4,SUM(I6:M6)/$D22,SUM(J6:M6)/$D22)) -> 0 | O22: =IF($D22>5,SUM($F6:N6)/$D22,IF($D22>4,SUM(J6:N6)/$D22,SUM(K6:N6)/$D22)) -> 0 | P22: =IF($D22>5,SUM($F6:O6)/$D22,IF($D22>4,SUM(K6:O6)/$D22,SUM(L6:O6)/$D22)) -> 0 | Q22: =IF($D22>10,SUM($F6:P6)/$D22,IF($D22>5,SUM(G6:P6)/$D22,IF($D22>4,SUM(L6:P6)/$D22,SUM(M6:P6)/$D22))) -> 0 | R22: =IF($D22>10,SUM($F6:Q6)/$D22,IF($D22>5,SUM(H6:Q6)/$D22,IF($D22>4,SUM(M6:Q6)/$D22,SUM(N6:Q6)/$D22))) -> 0 | S22: =IF($D22>10,SUM($F6:R6)/$D22,IF($D22>5,SUM(I6:R6)/$D22,IF($D22>4,SUM(N6:R6)/$D22,SUM(O6:R6)/$D22))) -> 0 | T22: =IF($D22>10,SUM($F6:S6)/$D22,IF($D22>5,SUM(J6:S6)/$D22,IF($D22>4,SUM(O6:S6)/$D22,SUM(P6:S6)/$D22))) -> 0 | U22: =IF($D22>10,SUM($F6:T6)/$D22,IF($D22>5,SUM(K6:T6)/$D22,IF($D22>4,SUM(P6:T6)/$D22,SUM(Q6:T6)/$D22))) -> 0
C23: Depr 4 | D23: =D7 -> 5 | E23: =VLOOKUP('NPV PT'!$C$2,countries!C:F,4,0) -> MYR | F23: 0 | G23: =F7/D23 -> -4620 | H23: =SUM($F7:G7)/$D23 -> -4620 | I23: =SUM($F7:H7)/$D23 -> -4620 | J23: =SUM($F7:I7)/$D23 -> -4620 | K23: =IF(D23>4,SUM($F7:J7)/$D23,SUM($G7:J7)/$D23) -> -4620 | L23: =IF(D23>5,SUM($F7:K7)/$D23,IF(D23>4,SUM($G7:K7)/$D23,SUM(H7:K7)/$D23)) -> 0 | M23: =IF($D23>5,SUM($F7:L7)/$D23,IF($D23>4,SUM(H7:L7)/$D23,SUM(I7:L7)/$D23)) -> 0 | N23: =IF($D23>5,SUM($F7:M7)/$D23,IF($D23>4,SUM(I7:M7)/$D23,SUM(J7:M7)/$D23)) -> 0 | O23: =IF($D23>5,SUM($F7:N7)/$D23,IF($D23>4,SUM(J7:N7)/$D23,SUM(K7:N7)/$D23)) -> 0 | P23: =IF($D23>5,SUM($F7:O7)/$D23,IF($D23>4,SUM(K7:O7)/$D23,SUM(L7:O7)/$D23)) -> 0 | Q23: =IF($D23>10,SUM($F7:P7)/$D23,IF($D23>5,SUM(G7:P7)/$D23,IF($D23>4,SUM(L7:P7)/$D23,SUM(M7:P7)/$D23))) -> 0 | R23: =IF($D23>10,SUM($F7:Q7)/$D23,IF($D23>5,SUM(H7:Q7)/$D23,IF($D23>4,SUM(M7:Q7)/$D23,SUM(N7:Q7)/$D23))) -> 0 | S23: =IF($D23>10,SUM($F7:R7)/$D23,IF($D23>5,SUM(I7:R7)/$D23,IF($D23>4,SUM(N7:R7)/$D23,SUM(O7:R7)/$D23))) -> 0 | T23: =IF($D23>10,SUM($F7:S7)/$D23,IF($D23>5,SUM(J7:S7)/$D23,IF($D23>4,SUM(O7:S7)/$D23,SUM(P7:S7)/$D23))) -> 0 | U23: =IF($D23>10,SUM($F7:T7)/$D23,IF($D23>5,SUM(K7:T7)/$D23,IF($D23>4,SUM(P7:T7)/$D23,SUM(Q7:T7)/$D23))) -> 0
C24: Depr 5 | D24: =D8 -> 10 | E24: =VLOOKUP('NPV PT'!$C$2,countries!C:F,4,0) -> MYR | F24: 0 | G24: =F8/D24 -> 0 | H24: =SUM($F8:G8)/$D24 -> 0 | I24: =SUM($F8:H8)/$D24 -> 0 | J24: =SUM($F8:I8)/$D24 -> 0 | K24: =IF(D24>4,SUM($F8:J8)/$D24,SUM($G8:J8)/$D24) -> 0 | L24: =IF(D24>5,SUM($F8:K8)/$D24,IF(D24>4,SUM($G8:K8)/$D24,SUM(H8:K8)/$D24)) -> 0 | M24: =IF($D24>5,SUM($F8:L8)/$D24,IF($D24>4,SUM(H8:L8)/$D24,SUM(I8:L8)/$D24)) -> 0 | N24: =IF($D24>5,SUM($F8:M8)/$D24,IF($D24>4,SUM(I8:M8)/$D24,SUM(J8:M8)/$D24)) -> 0 | O24: =IF($D24>5,SUM($F8:N8)/$D24,IF($D24>4,SUM(J8:N8)/$D24,SUM(K8:N8)/$D24)) -> 0 | P24: =IF($D24>5,SUM($F8:O8)/$D24,IF($D24>4,SUM(K8:O8)/$D24,SUM(L8:O8)/$D24)) -> 0 | Q24: =IF($D24>10,SUM($F8:P8)/$D24,IF($D24>5,SUM(G8:P8)/$D24,IF($D24>4,SUM(L8:P8)/$D24,SUM(M8:P8)/$D24))) -> 0 | R24: =IF($D24>10,SUM($F8:Q8)/$D24,IF($D24>5,SUM(H8:Q8)/$D24,IF($D24>4,SUM(M8:Q8)/$D24,SUM(N8:Q8)/$D24))) -> 0 | S24: =IF($D24>10,SUM($F8:R8)/$D24,IF($D24>5,SUM(I8:R8)/$D24,IF($D24>4,SUM(N8:R8)/$D24,SUM(O8:R8)/$D24))) -> 0 | T24: =IF($D24>10,SUM($F8:S8)/$D24,IF($D24>5,SUM(J8:S8)/$D24,IF($D24>4,SUM(O8:S8)/$D24,SUM(P8:S8)/$D24))) -> 0 | U24: =IF($D24>10,SUM($F8:T8)/$D24,IF($D24>5,SUM(K8:T8)/$D24,IF($D24>4,SUM(P8:T8)/$D24,SUM(Q8:T8)/$D24))) -> 0
C25: Depr 6 | D25: =D9 -> 15 | E25: =VLOOKUP('NPV PT'!$C$2,countries!C:F,4,0) -> MYR | F25: 0 | G25: =F9/D25 -> 0 | H25: =SUM($F9:G9)/$D25 -> 0 | I25: =SUM($F9:H9)/$D25 -> 0 | J25: =SUM($F9:I9)/$D25 -> 0 | K25: =IF(D25>4,SUM($F9:J9)/$D25,SUM($G9:J9)/$D25) -> 0 | L25: =IF(D25>5,SUM($F9:K9)/$D25,IF(D25>4,SUM($G9:K9)/$D25,SUM(H9:K9)/$D25)) -> 0 | M25: =IF($D25>5,SUM($F9:L9)/$D25,IF($D25>4,SUM(H9:L9)/$D25,SUM(I9:L9)/$D25)) -> 0 | N25: =IF($D25>5,SUM($F9:M9)/$D25,IF($D25>4,SUM(I9:M9)/$D25,SUM(J9:M9)/$D25)) -> 0 | O25: =IF($D25>5,SUM($F9:N9)/$D25,IF($D25>4,SUM(J9:N9)/$D25,SUM(K9:N9)/$D25)) -> 0 | P25: =IF($D25>5,SUM($F9:O9)/$D25,IF($D25>4,SUM(K9:O9)/$D25,SUM(L9:O9)/$D25)) -> 0 | Q25: =IF($D25>10,SUM($F9:P9)/$D25,IF($D25>5,SUM(G9:P9)/$D25,IF($D25>4,SUM(L9:P9)/$D25,SUM(M9:P9)/$D25))) -> 0 | R25: =IF($D25>10,SUM($F9:Q9)/$D25,IF($D25>5,SUM(H9:Q9)/$D25,IF($D25>4,SUM(M9:Q9)/$D25,SUM(N9:Q9)/$D25))) -> 0 | S25: =IF($D25>10,SUM($F9:R9)/$D25,IF($D25>5,SUM(I9:R9)/$D25,IF($D25>4,SUM(N9:R9)/$D25,SUM(O9:R9)/$D25))) -> 0 | T25: =IF($D25>10,SUM($F9:S9)/$D25,IF($D25>5,SUM(J9:S9)/$D25,IF($D25>4,SUM(O9:S9)/$D25,SUM(P9:S9)/$D25))) -> 0 | U25: =IF($D25>10,SUM($F9:T9)/$D25,IF($D25>5,SUM(K9:T9)/$D25,IF($D25>4,SUM(P9:T9)/$D25,SUM(Q9:T9)/$D25))) -> 0
C26: Depr 7 | D26: =D10 -> 20 | E26: =VLOOKUP('NPV PT'!$C$2,countries!C:F,4,0) -> MYR | F26: 0 | G26: =F10/D26 -> 0 | H26: =SUM($F10:G10)/$D26 -> 0 | I26: =SUM($F10:H10)/$D26 -> 0 | J26: =SUM($F10:I10)/$D26 -> 0 | K26: =IF(D26>4,SUM($F10:J10)/$D26,SUM($G10:J10)/$D26) -> 0 | L26: =IF(D26>5,SUM($F10:K10)/$D26,IF(D26>4,SUM($G10:K10)/$D26,SUM(H10:K10)/$D26)) -> 0 | M26: =IF($D26>5,SUM($F10:L10)/$D26,IF($D26>4,SUM(H10:L10)/$D26,SUM(I10:L10)/$D26)) -> 0 | N26: =IF($D26>5,SUM($F10:M10)/$D26,IF($D26>4,SUM(I10:M10)/$D26,SUM(J10:M10)/$D26)) -> 0 | O26: =IF($D26>5,SUM($F10:N10)/$D26,IF($D26>4,SUM(J10:N10)/$D26,SUM(K10:N10)/$D26)) -> 0 | P26: =IF($D26>5,SUM($F10:O10)/$D26,IF($D26>4,SUM(K10:O10)/$D26,SUM(L10:O10)/$D26)) -> 0 | Q26: =IF($D26>10,SUM($F10:P10)/$D26,IF($D26>5,SUM(G10:P10)/$D26,IF($D26>4,SUM(L10:P10)/$D26,SUM(M10:P10)/$D26))) -> 0 | R26: =IF($D26>10,SUM($F10:Q10)/$D26,IF($D26>5,SUM(H10:Q10)/$D26,IF($D26>4,SUM(M10:Q10)/$D26,SUM(N10:Q10)/$D26))) -> 0 | S26: =IF($D26>10,SUM($F10:R10)/$D26,IF($D26>5,SUM(I10:R10)/$D26,IF($D26>4,SUM(N10:R10)/$D26,SUM(O10:R10)/$D26))) -> 0 | T26: =IF($D26>10,SUM($F10:S10)/$D26,IF($D26>5,SUM(J10:S10)/$D26,IF($D26>4,SUM(O10:S10)/$D26,SUM(P10:S10)/$D26))) -> 0 | U26: =IF($D26>10,SUM($F10:T10)/$D26,IF($D26>5,SUM(K10:T10)/$D26,IF($D26>4,SUM(P10:T10)/$D26,SUM(Q10:T10)/$D26))) -> 0
C27: Depr 8 | D27: =D11 -> 20 | E27: =VLOOKUP('NPV PT'!$C$2,countries!C:F,4,0) -> MYR | F27: 0 | G27: =F11/D27 -> 0 | H27: =SUM($F11:G11)/$D27 -> 0 | I27: =SUM($F11:H11)/$D27 -> 0 | J27: =SUM($F11:I11)/$D27 -> 0 | K27: =IF(D27>4,SUM($F11:J11)/$D27,SUM($G11:J11)/$D27) -> 0 | L27: =IF(D27>5,SUM($F11:K11)/$D27,IF(D27>4,SUM($G11:K11)/$D27,SUM(H11:K11)/$D27)) -> 0 | M27: =IF($D27>5,SUM($F11:L11)/$D27,IF($D27>4,SUM(H11:L11)/$D27,SUM(I11:L11)/$D27)) -> 0 | N27: =IF($D27>5,SUM($F11:M11)/$D27,IF($D27>4,SUM(I11:M11)/$D27,SUM(J11:M11)/$D27)) -> 0 | O27: =IF($D27>5,SUM($F11:N11)/$D27,IF($D27>4,SUM(J11:N11)/$D27,SUM(K11:N11)/$D27)) -> 0 | P27: =IF($D27>5,SUM($F11:O11)/$D27,IF($D27>4,SUM(K11:O11)/$D27,SUM(L11:O11)/$D27)) -> 0 | Q27: =IF($D27>10,SUM($F11:P11)/$D27,IF($D27>5,SUM(G11:P11)/$D27,IF($D27>4,SUM(L11:P11)/$D27,SUM(M11:P11)/$D27))) -> 0 | R27: =IF($D27>10,SUM($F11:Q11)/$D27,IF($D27>5,SUM(H11:Q11)/$D27,IF($D27>4,SUM(M11:Q11)/$D27,SUM(N11:Q11)/$D27))) -> 0 | S27: =IF($D27>10,SUM($F11:R11)/$D27,IF($D27>5,SUM(I11:R11)/$D27,IF($D27>4,SUM(N11:R11)/$D27,SUM(O11:R11)/$D27))) -> 0 | T27: =IF($D27>10,SUM($F11:S11)/$D27,IF($D27>5,SUM(J11:S11)/$D27,IF($D27>4,SUM(O11:S11)/$D27,SUM(P11:S11)/$D27))) -> 0 | U27: =IF($D27>10,SUM($F11:T11)/$D27,IF($D27>5,SUM(K11:T11)/$D27,IF($D27>4,SUM(P11:T11)/$D27,SUM(Q11:T11)/$D27))) -> 0
C28: Depr 9 | D28: =D12 -> 25 | E28: =VLOOKUP('NPV PT'!$C$2,countries!C:F,4,0) -> MYR | F28: 0 | G28: =F12/D28 -> 0 | H28: =SUM($F12:G12)/$D28 -> 0 | I28: =SUM($F12:H12)/$D28 -> 0 | J28: =SUM($F12:I12)/$D28 -> 0 | K28: =IF(D28>4,SUM($F12:J12)/$D28,SUM($G12:J12)/$D28) -> 0 | L28: =IF(D28>5,SUM($F12:K12)/$D28,IF(D28>4,SUM($G12:K12)/$D28,SUM(H12:K12)/$D28)) -> 0 | M28: =IF($D28>5,SUM($F12:L12)/$D28,IF($D28>4,SUM(H12:L12)/$D28,SUM(I12:L12)/$D28)) -> 0 | N28: =IF($D28>5,SUM($F12:M12)/$D28,IF($D28>4,SUM(I12:M12)/$D28,SUM(J12:M12)/$D28)) -> 0 | O28: =IF($D28>5,SUM($F12:N12)/$D28,IF($D28>4,SUM(J12:N12)/$D28,SUM(K12:N12)/$D28)) -> 0 | P28: =IF($D28>5,SUM($F12:O12)/$D28,IF($D28>4,SUM(K12:O12)/$D28,SUM(L12:O12)/$D28)) -> 0 | Q28: =IF($D28>10,SUM($F12:P12)/$D28,IF($D28>5,SUM(G12:P12)/$D28,IF($D28>4,SUM(L12:P12)/$D28,SUM(M12:P12)/$D28))) -> 0 | R28: =IF($D28>10,SUM($F12:Q12)/$D28,IF($D28>5,SUM(H12:Q12)/$D28,IF($D28>4,SUM(M12:Q12)/$D28,SUM(N12:Q12)/$D28))) -> 0 | S28: =IF($D28>10,SUM($F12:R12)/$D28,IF($D28>5,SUM(I12:R12)/$D28,IF($D28>4,SUM(N12:R12)/$D28,SUM(O12:R12)/$D28))) -> 0 | T28: =IF($D28>10,SUM($F12:S12)/$D28,IF($D28>5,SUM(J12:S12)/$D28,IF($D28>4,SUM(O12:S12)/$D28,SUM(P12:S12)/$D28))) -> 0 | U28: =IF($D28>10,SUM($F12:T12)/$D28,IF($D28>5,SUM(K12:T12)/$D28,IF($D28>4,SUM(P12:T12)/$D28,SUM(Q12:T12)/$D28))) -> 0
C29: Depr 10 | D29: =D13 -> 30 | E29: =VLOOKUP('NPV PT'!$C$2,countries!C:F,4,0) -> MYR | F29: 0 | G29: =F13/D29 -> 0 | H29: =SUM($F13:G13)/$D29 -> 0 | I29: =SUM($F13:H13)/$D29 -> 0 | J29: =SUM($F13:I13)/$D29 -> 0 | K29: =IF(D29>4,SUM($F13:J13)/$D29,SUM($G13:J13)/$D29) -> 0 | L29: =IF(D29>5,SUM($F13:K13)/$D29,IF(D29>4,SUM($G13:K13)/$D29,SUM(H13:K13)/$D29)) -> 0 | M29: =IF($D29>5,SUM($F13:L13)/$D29,IF($D29>4,SUM(H13:L13)/$D29,SUM(I13:L13)/$D29)) -> 0 | N29: =IF($D29>5,SUM($F13:M13)/$D29,IF($D29>4,SUM(I13:M13)/$D29,SUM(J13:M13)/$D29)) -> 0 | O29: =IF($D29>5,SUM($F13:N13)/$D29,IF($D29>4,SUM(J13:N13)/$D29,SUM(K13:N13)/$D29)) -> 0 | P29: =IF($D29>5,SUM($F13:O13)/$D29,IF($D29>4,SUM(K13:O13)/$D29,SUM(L13:O13)/$D29)) -> 0 | Q29: =IF($D29>10,SUM($F13:P13)/$D29,IF($D29>5,SUM(G13:P13)/$D29,IF($D29>4,SUM(L13:P13)/$D29,SUM(M13:P13)/$D29))) -> 0 | R29: =IF($D29>10,SUM($F13:Q13)/$D29,IF($D29>5,SUM(H13:Q13)/$D29,IF($D29>4,SUM(M13:Q13)/$D29,SUM(N13:Q13)/$D29))) -> 0 | S29: =IF($D29>10,SUM($F13:R13)/$D29,IF($D29>5,SUM(I13:R13)/$D29,IF($D29>4,SUM(N13:R13)/$D29,SUM(O13:R13)/$D29))) -> 0 | T29: =IF($D29>10,SUM($F13:S13)/$D29,IF($D29>5,SUM(J13:S13)/$D29,IF($D29>4,SUM(O13:S13)/$D29,SUM(P13:S13)/$D29))) -> 0 | U29: =IF($D29>10,SUM($F13:T13)/$D29,IF($D29>5,SUM(K13:T13)/$D29,IF($D29>4,SUM(P13:T13)/$D29,SUM(Q13:T13)/$D29))) -> 0
C31: * check the useful lives in the "List for asset useful lives" sheet, but also with Project manager, as well as with the Vendor if in doubt.
C32: * The automated Depreciation calculation works only if the useful life is 4, 5, 10, 15, 20, 25, 30 years. If you enter anything else please make your own Depr calculation for those assets
C33: * Useful lifes in column D are just examples - please enter your own rates
B35: NTE:
C36: Description | D36: Useful life | E36: Currency | F36: =F2 -> 2025 | G36: =F36+1 -> 2026 | H36: =G36+1 -> 2027 | I36: =H36+1 -> 2028 | J36: =I36+1 -> 2029 | K36: =J36+1 -> 2030 | L36: =K36+1 -> 2031 | M36: =L36+1 -> 2032 | N36: =M36+1 -> 2033 | ... T36: =S36+1 -> 2039 | U36: =S36+1 -> 2039
B38: Capex 1 | C38: =C4 -> To supply, install, testing and comissioning of 8 units of in-line labeller, OCR reader and rejection system | D38: =D4 -> 5 | E38: =VLOOKUP('NPV PT'!$C$2,countries!C:F,4,0) -> MYR | F38: =-'Capex Estimate'!F7*1000 -> -2250000
B39: Capex 2 | C39: =C5 -> LAN cable installation for 8 lines | D39: =D5 -> 5 | E39: =VLOOKUP('NPV PT'!$C$2,countries!C:F,4,0) -> MYR | F39: =-'Capex Estimate'!F8*1000 -> -60000
B40: Capex 3 | C40: =C6 -> Unallocated Provision (UAP-Contingency) | D40: =D6 -> 5 | E40: =VLOOKUP('NPV PT'!$C$2,countries!C:F,4,0) -> MYR | F40: =-'Capex Estimate'!F13*1000 -> -138600
B41: Capex 4 | C41: =C7 -> Additional Unallocated Provision (AUAP) | D41: =D7 -> 5 | E41: =VLOOKUP('NPV PT'!$C$2,countries!C:F,4,0) -> MYR | F41: =-'Capex Estimate'!F15*1000 -> -46200
B42: Capex 5 | D42: =D8 -> 10 | E42: =VLOOKUP('NPV PT'!$C$2,countries!C:F,4,0) -> MYR
B43: Capex 6 | D43: =D9 -> 15 | E43: =VLOOKUP('NPV PT'!$C$2,countries!C:F,4,0) -> MYR
B44: Capex 7 | D44: =D10 -> 20 | E44: =VLOOKUP('NPV PT'!$C$2,countries!C:F,4,0) -> MYR
B45: Capex 8 | D45: =D11 -> 20 | E45: =VLOOKUP('NPV PT'!$C$2,countries!C:F,4,0) -> MYR
B46: Capex 9 | D46: =D12 -> 25 | E46: =VLOOKUP('NPV PT'!$C$2,countries!C:F,4,0) -> MYR
B47: Capex 10 | D47: =D13 -> 30 | E47: =VLOOKUP('NPV PT'!$C$2,countries!C:F,4,0) -> MYR
F49: * enter the capex amounts as negative numbers
D52: Useful life | E52: Currency | F52: =F36 -> 2025 | G52: =G36 -> 2026 | H52: =H36 -> 2027 | I52: =I36 -> 2028 | J52: =J36 -> 2029 | K52: =K36 -> 2030 | L52: =L36 -> 2031 | M52: =M36 -> 2032 | ... U52: =U36 -> 2039
C54: Depr 1 | D54: =D38 -> 5 | E54: =VLOOKUP('NPV PT'!$C$2,countries!C:F,4,0) -> MYR | F54: 0 | G54: =F38/D54 -> -450000 | H54: =SUM($F38:G38)/$D54 -> -450000 | I54: =SUM($F38:H38)/$D54 -> -450000 | J54: =SUM($F38:I38)/$D54 -> -450000 | K54: =IF(D54>4,SUM($F38:J38)/$D54,SUM($G38:J38)/$D54) -> -450000 | L54: =IF($D54>5,SUM($F38:K38)/$D54,IF($D54>4,SUM(G38:K38)/$D54,SUM(H38:K38)/$D54)) -> 0 | M54: =IF($D54>5,SUM($F38:L38)/$D54,IF($D54>4,SUM(H38:L38)/$D54,SUM(I38:L38)/$D54)) -> 0 | N54: =IF($D54>5,SUM($F38:M38)/$D54,IF($D54>4,SUM(I38:M38)/$D54,SUM(J38:M38)/$D54)) -> 0 | O54: =IF($D54>5,SUM($F38:N38)/$D54,IF($D54>4,SUM(J38:N38)/$D54,SUM(K38:N38)/$D54)) -> 0 | P54: =IF($D54>5,SUM($F38:O38)/$D54,IF($D54>4,SUM(K38:O38)/$D54,SUM(L38:O38)/$D54)) -> 0 | Q54: =IF($D54>10,SUM($F38:P38)/$D54,IF($D54>5,SUM(G38:P38)/$D54,IF($D54>4,SUM(L38:P38)/$D54,SUM(M38:P38)/$D54))) -> 0 | R54: =IF($D54>10,SUM($F38:Q38)/$D54,IF($D54>5,SUM(H38:Q38)/$D54,IF($D54>4,SUM(M38:Q38)/$D54,SUM(N38:Q38)/$D54))) -> 0 | S54: =IF($D54>10,SUM($F38:R38)/$D54,IF($D54>5,SUM(I38:R38)/$D54,IF($D54>4,SUM(N38:R38)/$D54,SUM(O38:R38)/$D54))) -> 0 | T54: =IF($D54>10,SUM($F38:S38)/$D54,IF($D54>5,SUM(J38:S38)/$D54,IF($D54>4,SUM(O38:S38)/$D54,SUM(P38:S38)/$D54))) -> 0 | U54: =IF($D54>10,SUM($F38:T38)/$D54,IF($D54>5,SUM(K38:T38)/$D54,IF($D54>4,SUM(P38:T38)/$D54,SUM(Q38:T38)/$D54))) -> 0
C55: Depr 2 | D55: =D39 -> 5 | E55: =VLOOKUP('NPV PT'!$C$2,countries!C:F,4,0) -> MYR | F55: 0 | G55: =F39/D55 -> -12000 | H55: =SUM($F39:G39)/$D55 -> -12000 | I55: =SUM($F39:H39)/$D55 -> -12000 | J55: =SUM($F39:I39)/$D55 -> -12000 | K55: =IF(D55>4,SUM($F39:J39)/$D55,SUM($G39:J39)/$D55) -> -12000 | L55: =IF(D55>5,SUM($F39:K39)/$D55,IF(D55>4,SUM($G39:K39)/$D55,SUM(H39:K39)/$D55)) -> 0 | M55: =IF($D55>5,SUM($F39:L39)/$D55,IF($D55>4,SUM(H39:L39)/$D55,SUM(I39:L39)/$D55)) -> 0 | N55: =IF($D55>5,SUM($F39:M39)/$D55,IF($D55>4,SUM(I39:M39)/$D55,SUM(J39:M39)/$D55)) -> 0 | O55: =IF($D55>5,SUM($F39:N39)/$D55,IF($D55>4,SUM(J39:N39)/$D55,SUM(K39:N39)/$D55)) -> 0 | P55: =IF($D55>5,SUM($F39:O39)/$D55,IF($D55>4,SUM(K39:O39)/$D55,SUM(L39:O39)/$D55)) -> 0 | Q55: =IF($D55>10,SUM($F39:P39)/$D55,IF($D55>5,SUM(G39:P39)/$D55,IF($D55>4,SUM(L39:P39)/$D55,SUM(M39:P39)/$D55))) -> 0 | R55: =IF($D55>10,SUM($F39:Q39)/$D55,IF($D55>5,SUM(H39:Q39)/$D55,IF($D55>4,SUM(M39:Q39)/$D55,SUM(N39:Q39)/$D55))) -> 0 | S55: =IF($D55>10,SUM($F39:R39)/$D55,IF($D55>5,SUM(I39:R39)/$D55,IF($D55>4,SUM(N39:R39)/$D55,SUM(O39:R39)/$D55))) -> 0 | T55: =IF($D55>10,SUM($F39:S39)/$D55,IF($D55>5,SUM(J39:S39)/$D55,IF($D55>4,SUM(O39:S39)/$D55,SUM(P39:S39)/$D55))) -> 0 | U55: =IF($D55>10,SUM($F39:T39)/$D55,IF($D55>5,SUM(K39:T39)/$D55,IF($D55>4,SUM(P39:T39)/$D55,SUM(Q39:T39)/$D55))) -> 0
C56: Depr 3 | D56: =D40 -> 5 | E56: =VLOOKUP('NPV PT'!$C$2,countries!C:F,4,0) -> MYR | F56: 0 | G56: =F40/D56 -> -27720 | H56: =SUM($F40:G40)/$D56 -> -27720 | I56: =SUM($F40:H40)/$D56 -> -27720 | J56: =SUM($F40:I40)/$D56 -> -27720 | K56: =IF(D56>4,SUM($F40:J40)/$D56,SUM($G40:J40)/$D56) -> -27720 | L56: =IF(D56>5,SUM($F40:K40)/$D56,IF(D56>4,SUM($G40:K40)/$D56,SUM(H40:K40)/$D56)) -> 0 | M56: =IF($D56>5,SUM($F40:L40)/$D56,IF($D56>4,SUM(H40:L40)/$D56,SUM(I40:L40)/$D56)) -> 0 | N56: =IF($D56>5,SUM($F40:M40)/$D56,IF($D56>4,SUM(I40:M40)/$D56,SUM(J40:M40)/$D56)) -> 0 | O56: =IF($D56>5,SUM($F40:N40)/$D56,IF($D56>4,SUM(J40:N40)/$D56,SUM(K40:N40)/$D56)) -> 0 | P56: =IF($D56>5,SUM($F40:O40)/$D56,IF($D56>4,SUM(K40:O40)/$D56,SUM(L40:O40)/$D56)) -> 0 | Q56: =IF($D56>10,SUM($F40:P40)/$D56,IF($D56>5,SUM(G40:P40)/$D56,IF($D56>4,SUM(L40:P40)/$D56,SUM(M40:P40)/$D56))) -> 0 | R56: =IF($D56>10,SUM($F40:Q40)/$D56,IF($D56>5,SUM(H40:Q40)/$D56,IF($D56>4,SUM(M40:Q40)/$D56,SUM(N40:Q40)/$D56))) -> 0 | S56: =IF($D56>10,SUM($F40:R40)/$D56,IF($D56>5,SUM(I40:R40)/$D56,IF($D56>4,SUM(N40:R40)/$D56,SUM(O40:R40)/$D56))) -> 0 | T56: =IF($D56>10,SUM($F40:S40)/$D56,IF($D56>5,SUM(J40:S40)/$D56,IF($D56>4,SUM(O40:S40)/$D56,SUM(P40:S40)/$D56))) -> 0 | U56: =IF($D56>10,SUM($F40:T40)/$D56,IF($D56>5,SUM(K40:T40)/$D56,IF($D56>4,SUM(P40:T40)/$D56,SUM(Q40:T40)/$D56))) -> 0
C57: Depr 4 | D57: =D41 -> 5 | E57: =VLOOKUP('NPV PT'!$C$2,countries!C:F,4,0) -> MYR | F57: 0 | G57: =F41/D57 -> -9240 | H57: =SUM($F41:G41)/$D57 -> -9240 | I57: =SUM($F41:H41)/$D57 -> -9240 | J57: =SUM($F41:I41)/$D57 -> -9240 | K57: =IF(D57>4,SUM($F41:J41)/$D57,SUM($G41:J41)/$D57) -> -9240 | L57: =IF(D57>5,SUM($F41:K41)/$D57,IF(D57>4,SUM($G41:K41)/$D57,SUM(H41:K41)/$D57)) -> 0 | M57: =IF($D57>5,SUM($F41:L41)/$D57,IF($D57>4,SUM(H41:L41)/$D57,SUM(I41:L41)/$D57)) -> 0 | N57: =IF($D57>5,SUM($F41:M41)/$D57,IF($D57>4,SUM(I41:M41)/$D57,SUM(J41:M41)/$D57)) -> 0 | O57: =IF($D57>5,SUM($F41:N41)/$D57,IF($D57>4,SUM(J41:N41)/$D57,SUM(K41:N41)/$D57)) -> 0 | P57: =IF($D57>5,SUM($F41:O41)/$D57,IF($D57>4,SUM(K41:O41)/$D57,SUM(L41:O41)/$D57)) -> 0 | Q57: =IF($D57>10,SUM($F41:P41)/$D57,IF($D57>5,SUM(G41:P41)/$D57,IF($D57>4,SUM(L41:P41)/$D57,SUM(M41:P41)/$D57))) -> 0 | R57: =IF($D57>10,SUM($F41:Q41)/$D57,IF($D57>5,SUM(H41:Q41)/$D57,IF($D57>4,SUM(M41:Q41)/$D57,SUM(N41:Q41)/$D57))) -> 0 | S57: =IF($D57>10,SUM($F41:R41)/$D57,IF($D57>5,SUM(I41:R41)/$D57,IF($D57>4,SUM(N41:R41)/$D57,SUM(O41:R41)/$D57))) -> 0 | T57: =IF($D57>10,SUM($F41:S41)/$D57,IF($D57>5,SUM(J41:S41)/$D57,IF($D57>4,SUM(O41:S41)/$D57,SUM(P41:S41)/$D57))) -> 0 | U57: =IF($D57>10,SUM($F41:T41)/$D57,IF($D57>5,SUM(K41:T41)/$D57,IF($D57>4,SUM(P41:T41)/$D57,SUM(Q41:T41)/$D57))) -> 0
C58: Depr 5 | D58: =D42 -> 10 | E58: =VLOOKUP('NPV PT'!$C$2,countries!C:F,4,0) -> MYR | F58: 0 | G58: =F42/D58 -> 0 | H58: =SUM($F42:G42)/$D58 -> 0 | I58: =SUM($F42:H42)/$D58 -> 0 | J58: =SUM($F42:I42)/$D58 -> 0 | K58: =IF(D58>4,SUM($F42:J42)/$D58,SUM($G42:J42)/$D58) -> 0 | L58: =IF(D58>5,SUM($F42:K42)/$D58,IF(D58>4,SUM($G42:K42)/$D58,SUM(H42:K42)/$D58)) -> 0 | M58: =IF($D58>5,SUM($F42:L42)/$D58,IF($D58>4,SUM(H42:L42)/$D58,SUM(I42:L42)/$D58)) -> 0 | N58: =IF($D58>5,SUM($F42:M42)/$D58,IF($D58>4,SUM(I42:M42)/$D58,SUM(J42:M42)/$D58)) -> 0 | O58: =IF($D58>5,SUM($F42:N42)/$D58,IF($D58>4,SUM(J42:N42)/$D58,SUM(K42:N42)/$D58)) -> 0 | P58: =IF($D58>5,SUM($F42:O42)/$D58,IF($D58>4,SUM(K42:O42)/$D58,SUM(L42:O42)/$D58)) -> 0 | Q58: =IF($D58>10,SUM($F42:P42)/$D58,IF($D58>5,SUM(G42:P42)/$D58,IF($D58>4,SUM(L42:P42)/$D58,SUM(M42:P42)/$D58))) -> 0 | R58: =IF($D58>10,SUM($F42:Q42)/$D58,IF($D58>5,SUM(H42:Q42)/$D58,IF($D58>4,SUM(M42:Q42)/$D58,SUM(N42:Q42)/$D58))) -> 0 | S58: =IF($D58>10,SUM($F42:R42)/$D58,IF($D58>5,SUM(I42:R42)/$D58,IF($D58>4,SUM(N42:R42)/$D58,SUM(O42:R42)/$D58))) -> 0 | T58: =IF($D58>10,SUM($F42:S42)/$D58,IF($D58>5,SUM(J42:S42)/$D58,IF($D58>4,SUM(O42:S42)/$D58,SUM(P42:S42)/$D58))) -> 0 | U58: =IF($D58>10,SUM($F42:T42)/$D58,IF($D58>5,SUM(K42:T42)/$D58,IF($D58>4,SUM(P42:T42)/$D58,SUM(Q42:T42)/$D58))) -> 0
C59: Depr 6 | D59: =D43 -> 15 | E59: =VLOOKUP('NPV PT'!$C$2,countries!C:F,4,0) -> MYR | F59: 0 | G59: =F43/D59 -> 0 | H59: =SUM($F43:G43)/$D59 -> 0 | I59: =SUM($F43:H43)/$D59 -> 0 | J59: =SUM($F43:I43)/$D59 -> 0 | K59: =IF(D59>4,SUM($F43:J43)/$D59,SUM($G43:J43)/$D59) -> 0 | L59: =IF(D59>5,SUM($F43:K43)/$D59,IF(D59>4,SUM($G43:K43)/$D59,SUM(H43:K43)/$D59)) -> 0 | M59: =IF($D59>5,SUM($F43:L43)/$D59,IF($D59>4,SUM(H43:L43)/$D59,SUM(I43:L43)/$D59)) -> 0 | N59: =IF($D59>5,SUM($F43:M43)/$D59,IF($D59>4,SUM(I43:M43)/$D59,SUM(J43:M43)/$D59)) -> 0 | O59: =IF($D59>5,SUM($F43:N43)/$D59,IF($D59>4,SUM(J43:N43)/$D59,SUM(K43:N43)/$D59)) -> 0 | P59: =IF($D59>5,SUM($F43:O43)/$D59,IF($D59>4,SUM(K43:O43)/$D59,SUM(L43:O43)/$D59)) -> 0 | Q59: =IF($D59>10,SUM($F43:P43)/$D59,IF($D59>5,SUM(G43:P43)/$D59,IF($D59>4,SUM(L43:P43)/$D59,SUM(M43:P43)/$D59))) -> 0 | R59: =IF($D59>10,SUM($F43:Q43)/$D59,IF($D59>5,SUM(H43:Q43)/$D59,IF($D59>4,SUM(M43:Q43)/$D59,SUM(N43:Q43)/$D59))) -> 0 | S59: =IF($D59>10,SUM($F43:R43)/$D59,IF($D59>5,SUM(I43:R43)/$D59,IF($D59>4,SUM(N43:R43)/$D59,SUM(O43:R43)/$D59))) -> 0 | T59: =IF($D59>10,SUM($F43:S43)/$D59,IF($D59>5,SUM(J43:S43)/$D59,IF($D59>4,SUM(O43:S43)/$D59,SUM(P43:S43)/$D59))) -> 0 | U59: =IF($D59>10,SUM($F43:T43)/$D59,IF($D59>5,SUM(K43:T43)/$D59,IF($D59>4,SUM(P43:T43)/$D59,SUM(Q43:T43)/$D59))) -> 0
C60: Depr 7 | D60: =D44 -> 20 | E60: =VLOOKUP('NPV PT'!$C$2,countries!C:F,4,0) -> MYR | F60: 0 | G60: =F44/D60 -> 0 | H60: =SUM($F44:G44)/$D60 -> 0 | I60: =SUM($F44:H44)/$D60 -> 0 | J60: =SUM($F44:I44)/$D60 -> 0 | K60: =IF(D60>4,SUM($F44:J44)/$D60,SUM($G44:J44)/$D60) -> 0 | L60: =IF(D60>5,SUM($F44:K44)/$D60,IF(D60>4,SUM($G44:K44)/$D60,SUM(H44:K44)/$D60)) -> 0 | M60: =IF($D60>5,SUM($F44:L44)/$D60,IF($D60>4,SUM(H44:L44)/$D60,SUM(I44:L44)/$D60)) -> 0 | N60: =IF($D60>5,SUM($F44:M44)/$D60,IF($D60>4,SUM(I44:M44)/$D60,SUM(J44:M44)/$D60)) -> 0 | O60: =IF($D60>5,SUM($F44:N44)/$D60,IF($D60>4,SUM(J44:N44)/$D60,SUM(K44:N44)/$D60)) -> 0 | P60: =IF($D60>5,SUM($F44:O44)/$D60,IF($D60>4,SUM(K44:O44)/$D60,SUM(L44:O44)/$D60)) -> 0 | Q60: =IF($D60>10,SUM($F44:P44)/$D60,IF($D60>5,SUM(G44:P44)/$D60,IF($D60>4,SUM(L44:P44)/$D60,SUM(M44:P44)/$D60))) -> 0 | R60: =IF($D60>10,SUM($F44:Q44)/$D60,IF($D60>5,SUM(H44:Q44)/$D60,IF($D60>4,SUM(M44:Q44)/$D60,SUM(N44:Q44)/$D60))) -> 0 | S60: =IF($D60>10,SUM($F44:R44)/$D60,IF($D60>5,SUM(I44:R44)/$D60,IF($D60>4,SUM(N44:R44)/$D60,SUM(O44:R44)/$D60))) -> 0 | T60: =IF($D60>10,SUM($F44:S44)/$D60,IF($D60>5,SUM(J44:S44)/$D60,IF($D60>4,SUM(O44:S44)/$D60,SUM(P44:S44)/$D60))) -> 0 | U60: =IF($D60>10,SUM($F44:T44)/$D60,IF($D60>5,SUM(K44:T44)/$D60,IF($D60>4,SUM(P44:T44)/$D60,SUM(Q44:T44)/$D60))) -> 0
C61: Depr 8 | D61: =D45 -> 20 | E61: =VLOOKUP('NPV PT'!$C$2,countries!C:F,4,0) -> MYR | F61: 0 | G61: =F45/D61 -> 0 | H61: =SUM($F45:G45)/$D61 -> 0 | I61: =SUM($F45:H45)/$D61 -> 0 | J61: =SUM($F45:I45)/$D61 -> 0 | K61: =IF(D61>4,SUM($F45:J45)/$D61,SUM($G45:J45)/$D61) -> 0 | L61: =IF(D61>5,SUM($F45:K45)/$D61,IF(D61>4,SUM($G45:K45)/$D61,SUM(H45:K45)/$D61)) -> 0 | M61: =IF($D61>5,SUM($F45:L45)/$D61,IF($D61>4,SUM(H45:L45)/$D61,SUM(I45:L45)/$D61)) -> 0 | N61: =IF($D61>5,SUM($F45:M45)/$D61,IF($D61>4,SUM(I45:M45)/$D61,SUM(J45:M45)/$D61)) -> 0 | O61: =IF($D61>5,SUM($F45:N45)/$D61,IF($D61>4,SUM(J45:N45)/$D61,SUM(K45:N45)/$D61)) -> 0 | P61: =IF($D61>5,SUM($F45:O45)/$D61,IF($D61>4,SUM(K45:O45)/$D61,SUM(L45:O45)/$D61)) -> 0 | Q61: =IF($D61>10,SUM($F45:P45)/$D61,IF($D61>5,SUM(G45:P45)/$D61,IF($D61>4,SUM(L45:P45)/$D61,SUM(M45:P45)/$D61))) -> 0 | R61: =IF($D61>10,SUM($F45:Q45)/$D61,IF($D61>5,SUM(H45:Q45)/$D61,IF($D61>4,SUM(M45:Q45)/$D61,SUM(N45:Q45)/$D61))) -> 0 | S61: =IF($D61>10,SUM($F45:R45)/$D61,IF($D61>5,SUM(I45:R45)/$D61,IF($D61>4,SUM(N45:R45)/$D61,SUM(O45:R45)/$D61))) -> 0 | T61: =IF($D61>10,SUM($F45:S45)/$D61,IF($D61>5,SUM(J45:S45)/$D61,IF($D61>4,SUM(O45:S45)/$D61,SUM(P45:S45)/$D61))) -> 0 | U61: =IF($D61>10,SUM($F45:T45)/$D61,IF($D61>5,SUM(K45:T45)/$D61,IF($D61>4,SUM(P45:T45)/$D61,SUM(Q45:T45)/$D61))) -> 0
C62: Depr 9 | D62: =D46 -> 25 | E62: =VLOOKUP('NPV PT'!$C$2,countries!C:F,4,0) -> MYR | F62: 0 | G62: =F46/D62 -> 0 | H62: =SUM($F46:G46)/$D62 -> 0 | I62: =SUM($F46:H46)/$D62 -> 0 | J62: =SUM($F46:I46)/$D62 -> 0 | K62: =IF(D62>4,SUM($F46:J46)/$D62,SUM($G46:J46)/$D62) -> 0 | L62: =IF(D62>5,SUM($F46:K46)/$D62,IF(D62>4,SUM($G46:K46)/$D62,SUM(H46:K46)/$D62)) -> 0 | M62: =IF($D62>5,SUM($F46:L46)/$D62,IF($D62>4,SUM(H46:L46)/$D62,SUM(I46:L46)/$D62)) -> 0 | N62: =IF($D62>5,SUM($F46:M46)/$D62,IF($D62>4,SUM(I46:M46)/$D62,SUM(J46:M46)/$D62)) -> 0 | O62: =IF($D62>5,SUM($F46:N46)/$D62,IF($D62>4,SUM(J46:N46)/$D62,SUM(K46:N46)/$D62)) -> 0 | P62: =IF($D62>5,SUM($F46:O46)/$D62,IF($D62>4,SUM(K46:O46)/$D62,SUM(L46:O46)/$D62)) -> 0 | Q62: =IF($D62>10,SUM($F46:P46)/$D62,IF($D62>5,SUM(G46:P46)/$D62,IF($D62>4,SUM(L46:P46)/$D62,SUM(M46:P46)/$D62))) -> 0 | R62: =IF($D62>10,SUM($F46:Q46)/$D62,IF($D62>5,SUM(H46:Q46)/$D62,IF($D62>4,SUM(M46:Q46)/$D62,SUM(N46:Q46)/$D62))) -> 0 | S62: =IF($D62>10,SUM($F46:R46)/$D62,IF($D62>5,SUM(I46:R46)/$D62,IF($D62>4,SUM(N46:R46)/$D62,SUM(O46:R46)/$D62))) -> 0 | T62: =IF($D62>10,SUM($F46:S46)/$D62,IF($D62>5,SUM(J46:S46)/$D62,IF($D62>4,SUM(O46:S46)/$D62,SUM(P46:S46)/$D62))) -> 0 | U62: =IF($D62>10,SUM($F46:T46)/$D62,IF($D62>5,SUM(K46:T46)/$D62,IF($D62>4,SUM(P46:T46)/$D62,SUM(Q46:T46)/$D62))) -> 0
C63: Depr 10 | D63: =D47 -> 30 | E63: =VLOOKUP('NPV PT'!$C$2,countries!C:F,4,0) -> MYR | F63: 0 | G63: =F47/D63 -> 0 | H63: =SUM($F47:G47)/$D63 -> 0 | I63: =SUM($F47:H47)/$D63 -> 0 | J63: =SUM($F47:I47)/$D63 -> 0 | K63: =IF(D63>4,SUM($F47:J47)/$D63,SUM($G47:J47)/$D63) -> 0 | L63: =IF(D63>5,SUM($F47:K47)/$D63,IF(D63>4,SUM($G47:K47)/$D63,SUM(H47:K47)/$D63)) -> 0 | M63: =IF($D63>5,SUM($F47:L47)/$D63,IF($D63>4,SUM(H47:L47)/$D63,SUM(I47:L47)/$D63)) -> 0 | N63: =IF($D63>5,SUM($F47:M47)/$D63,IF($D63>4,SUM(I47:M47)/$D63,SUM(J47:M47)/$D63)) -> 0 | O63: =IF($D63>5,SUM($F47:N47)/$D63,IF($D63>4,SUM(J47:N47)/$D63,SUM(K47:N47)/$D63)) -> 0 | P63: =IF($D63>5,SUM($F47:O47)/$D63,IF($D63>4,SUM(K47:O47)/$D63,SUM(L47:O47)/$D63)) -> 0 | Q63: =IF($D63>10,SUM($F47:P47)/$D63,IF($D63>5,SUM(G47:P47)/$D63,IF($D63>4,SUM(L47:P47)/$D63,SUM(M47:P47)/$D63))) -> 0 | R63: =IF($D63>10,SUM($F47:Q47)/$D63,IF($D63>5,SUM(H47:Q47)/$D63,IF($D63>4,SUM(M47:Q47)/$D63,SUM(N47:Q47)/$D63))) -> 0 | S63: =IF($D63>10,SUM($F47:R47)/$D63,IF($D63>5,SUM(I47:R47)/$D63,IF($D63>4,SUM(N47:R47)/$D63,SUM(O47:R47)/$D63))) -> 0 | T63: =IF($D63>10,SUM($F47:S47)/$D63,IF($D63>5,SUM(J47:S47)/$D63,IF($D63>4,SUM(O47:S47)/$D63,SUM(P47:S47)/$D63))) -> 0 | U63: =IF($D63>10,SUM($F47:T47)/$D63,IF($D63>5,SUM(K47:T47)/$D63,IF($D63>4,SUM(P47:T47)/$D63,SUM(Q47:T47)/$D63))) -> 0

Sheet Capex Estimate
B1: ESTIMATE: | E1: Enter Data in Grey cells
B3: Estimate Accuracy: | D3: 1 USD = | E3: 4.56 | F3: MYR | G3: Conversion
B4: + or - 20% to 30% - for dFM
B5: + or - 10% - for eFM | E5: =F3 -> MYR | F5: =E5 -> MYR | G5: USD
B6: Sr.No | C6: DESCRIPTION | D6: ITEM | E6: Unit PRICE in LOCAL (K) | F6: PRICE in LOCAL (K) | G6: PRICE in USD (K) | H6: REMARKS
B7: 1 | C7: To supply, install, testing and comissioning of 8 units of in-line labeller, OCR reader and rejection system | D7: 1 | E7: 2250 | F7: =E7*D7 -> 2250 | G7: =E7*D7/E$3 -> 493.42105
B8: 2 | C8: LAN cable installation for 8 lines | D8: 1 | E8: 60 | F8: =E8*D8 -> 60 | G8: =E8*D8/E$3 -> 13.157895
B9: 1 | C9: Sub Total (Gross) | F9: =SUM(F7:F8) -> 2310 | G9: =SUM(G7:G8) -> 506.57895
B10: 2.1 | C10: VAT Or Tax | D10: 0 | F10: =F9*D10 -> 0 | G10: =F10/E$3 -> 0 | H10: ASEAN countries exempted Country Specific
B11: 2.2 | C11: Allocated Provision (Allowances) | D11: 0 | F11: =F9*D11 -> 0 | G11: =F11/E$3 -> 0 | H11: MTO allowance, Risks, Cut and watse
B12: 2 | C12: Sub Total (Base Cost) | F12: =SUM(F9:F11) -> 2310 | G12: =SUM(G9:G11) -> 506.57895 | H12: Base cost (BC)
B13: 3.1 | C13: Unallocated Provision (UAP-Contingency) | D13: 0.06 | F13: =F9*D13 -> 138.6 | G13: =F13/E$3 -> 30.394737 | H13: Max 10% eFM& 30% for dFM Scope uncetanity, pricing etc
B14: 3 | C14: Sub Total (Project Expecetd Cost) | F14: =SUM(F12:F13) -> 2448.6 | G14: =SUM(G12:G13) -> 536.97368 | H14: Performace Target (PT)
B15: 3.2 | C15: Additional Unallocated Provision (AUAP) | D15: 0.02 | F15: =F9*D15 -> 46.2 | G15: =F15/E$3 -> 10.131579 | H15: Escalation, weather, HiPot Incidents, Risk
B16: 3 | C16: TOTAL (Not To Exceed) | F16: =SUM(F14:F15) -> 2494.8 | G16: =SUM(G14:G15) -> 547.10526 | H16: Not To Exceed (NTE)
C17: Round Up - TOTAL | F17: 2493 | G17: 547 | H17: Manual entry
F18: .
F19: Amount in USD (K)
C20: CASHFLOW | D20: YEAR | E20: Distribution | F20: =F3 -> MYR | G20: Amount in USD (K)
D21: 2025 | E21: Q1 | G21: =F21/E$3 -> 0
E22: Q2 | G22: 0
E23: Q3 | F23: 1000 | G23: 220
E24: Q4 | F24: 1449 | G24: 317
C25: TOTAL | F25: =SUM(F21:F24) -> 2449 | G25: =SUM(G21:G24) -> 537
B53: SGD
B54: MYR
B55: AUD
B56: THB
B57: IDY
B58: DONG

Sheet Working - MY OU 5% Imrpovement
B2: MY Auto Business | C2: 2024 | D2: =C2+1 -> 2025 | E2: =D2+1 -> 2026 | F2: =E2+1 -> 2027 | G2: =F2+1 -> 2028 | H2: =G2+1 -> 2029 | I2: =H2+1 -> 2030
B3: Sales Volume | C3: =30238204/1000000 -> 30.238204 | D3: =C3 -> 30.238204 | E3: =D3 -> 30.238204 | F3: =E3 -> 30.238204 | G3: =F3 -> 30.238204 | H3: =G3 -> 30.238204 | I3: =H3 -> 30.238204
B4: Volume Improvement | E4: 0.05 | F4: 0.05 | G4: 0.05 | H4: 0.05 | I4: 0.05
B6: Additional Volume | E6: =E3*E4*1000000 -> 1511910.2 | F6: =F3*F4*1000000 -> 1511910.2 | G6: =G3*G4*1000000 -> 1511910.2 | H6: =H3*H4*1000000 -> 1511910.2 | I6: =I3*I4*1000000 -> 1511910.2
B7: USD GM/Litre | E7: 0.9 | F7: 0.9 | G7: 0.9 | H7: 0.9 | I7: 0.9
B8: RCOP Improvement | E8: =E6*E7 -> 1360719.2 | F8: =F6*F7 -> 1360719.2 | G8: =G6*G7 -> 1360719.2 | H8: =H6*H7 -> 1360719.2 | I8: =I6*I7 -> 1360719.2
B9: Coporate Tax @ 24% | E9: =-0.24*E8 -> -326572.6 | F9: =-0.24*F8 -> -326572.6 | G9: =-0.24*G8 -> -326572.6 | H9: =-0.24*H8 -> -326572.6 | I9: =-0.24*I8 -> -326572.6
B10: Profit After Tax | E10: =E8+E9 -> 1034146.6 | F10: =F8+F9 -> 1034146.6 | G10: =G8+G9 -> 1034146.6 | H10: =H8+H9 -> 1034146.6 | I10: =I8+I9 -> 1034146.6
B12: Capex | D12: =-0.547*1000000 -> -547000
B14: JV Interest @ 37%

Sheet List for asset Useful lives
A1: Lubricants SPU: Component List - Revised 4Q2013 | F1: 1Q-2024
B3: LUBRICANTS | C3: Fixed Asset Component
A4: Component | B4: Lubricants SPU Sub-component | C4: Asset Description | D4: Useful Life (Years) | F4: New Useful Life (Years)
A5: Containment System | B5: Bunding/earthworks | C5: Containment/Bund/earthworks | D5: 20 | F5: 30
B6: Fencing | C6: Containment/Fencing | D6: 10 | F6: 10
B7: Transfer Pump with driver | C7: Containment/Fencing | D7: 10 | F7: 10
B8: Stormwater/Containment Piping | C8: Containment/SW/Containment Piping | D8: 10 | F8: 10
B9: Instrumentation | C9: Containment/Instrumentation | D9: 5 | F9: 5
B10: Isolation/Diversion Valves | C10: Containment/Isolation/Diversion Valves | D10: 5 | F10: 5
B11: Fire Protection Systems | C11: Containment/Fire Protection | D11: 10 | F11: 10
A12: Raw Material Storage/Delivery System | B12: Storage Tank with associated foundations | C12: RM Storage/Delivery /Storage Tanks | D12: 20 | F12: 30
B13: Instrumentation | C13: RM Storage/Instrumentation | D13: 5 | F13: 5
B14: Transfer Pump with driver | C14: RM Storage/Transfer Pump | D14: 10 | F14: 10
B15: Unloading Systems/Hoses | C15: RM Storage/Unloading Systems | D15: 5 | F15: 5
B16: Inline Specialties (filters, magnetic boxes, mixers, etc.) | C16: RM Storage/Inline Specialties | D16: 10 | F16: 10
B17: Pipe Lines e.g. base oil / additive supply | C17: RM Storage/Pipe Lines | D17: 10 | F17: 25
A18: Finished Product Storage/Delivery System | B18: Storage Tank with associated foundations | C18: FP Storage/Delivery /Storage Tanks | D18: 20 | F18: 30
B19: Instrumentation | C19: FP Storage/Instrumentation | D19: 5 | F19: 5
B20: Transfer/LoadingPump with driver | C20: FP Storage/Transfer Pump | D20: 10 | F20: 10
B21: Inline Specialties (filters, magnetic boxes, mixers, etc.) | C21: FP Storage/Inline Specialties | D21: 10 | F21: 10
B22: Loading Arms /Hoses | C22: FP Storage/Loading Systems | D22: 5 | F22: 5
B23: Pipe lines e.g. Finished product supply | C23: FP Storage/Pipe Lines | D23: 10 | F23: 25
A24: Blending System | B24: Blending Vessel (with internals) | C24: Blending/Blending Vessels | D24: 20 | F24: 30
B25: Holding Tanks (with internals) | C25: Blending/Holding Tanks | D25: 20 | F25: 30
B26: Heating Units, including hot boxes | C26: Blending/Heating Units | D26: 10 | F26: 10
B27: Instrumentation | C27: Blending/Instrumentation | D27: 5 | F27: 5
B28: Control System | C28: Blending/Control Systems | D28: 5 | F28: 5
B29: Decanting Unit | C29: Blending/Decanting Units | D29: 10 | F29: 10
B30: Transfer/Circulation Pumps | C30: Blending/Transfer Pumps | D30: 10 | F30: 10
B31: Manifold Systems | C31: Blending/Manifold Systems | D31: 10 | F31: 20
A32: Filling/Packaging Line | B32: Filling Machine | C32: Filling/Packaging Line/Filling Machines | D32: 10 | F32: 20
B33: Cappers and Sealer | C33: Filling/Packaging Line/Cappers & Sealers | D33: 10 | F33: 20
B34: Packaging Machine | C34: Filling/Packaging Line/Packaging Machine | D34: 15 | F34: 20
B35: Palletizer | C35: Filling/Packaging Line/Palletizer | D35: 15 | F35: 20
B36: De-Palletizer | C36: Filling/Packaging Line/De-Palletizer | D36: 15 | F36: 20
B37: Labelling Machine | C37: Filling/Packaging Line/Labelling Machine | D37: 10 | F37: 20
B38: Checkweigher | C38: Filling/Packaging Line/Checkweigher | D38: 10 | F38: 10
B39: Case Sealer, e.g. glue sealer / tape sealer | C39: Filling/Packaging Line/Control Sealer | D39: 10 | F39: 10
B40: Coders (case, bottle, ink jet, etc.) | C40: Filling/Packaging Line/Coder | D40: 5 | F40: 5
B41: Shrink Wrapper | C41: Filling/Packaging Line/Shrink Wrapper | D41: 10 | F41: 20
B42: Control System | C42: Filling/Packaging Line/Control Systems | D42: 5 | F42: 5
B43: Inline Specialties (filters, injection systems, mixers, etc.) | C43: Filling/Packaging Line/Inline Specialties | D43: 10 | F43: 10
B44: Large Pack Filling (drums, pails, IBC) | C44: Filling/Packaging Line/Large Pack Filling | D44: 10 | F44: 20
... B47: Holding Tanks | C47: Filling/Packaging Line/Holding Tanks | D47: 20 | F47: 30
A48: Warehouse and storage | B48: Conveyer Belts etc | C48: Whse & Storage/Conveyer Belts etc | D48: 10 | F48: 10
B49: Jetties/Pontoons | C49: Whse & Storage/Jetties | D49: 20 | F49: 30
B50: Loading Ramps | C50: Whse & Storage/Loading Ramps | D50: 10 | F50: 10
B51: Vehicle Flushing/Cleaning systems | C51: Whse & Storage/Vehicle Flush/Clean sys | D51: 10 | F51: 10
B52: Warehouse Racking | C52: Whse & Storage/Warehouse Racking | D52: 10 | F52: 10
A53: General Site | B53: Fencing/Gates | C53: General Site/Fencing/Gates | D53: 10 | F53: 10
B54: General Ventilation | C54: General Site/General Ventilation | D54: 10 | F54: 10
B55: Fume Extraction | C55: General Site/Fume Extraction | D55: 10 | F55: 10
B56: Laboratory Extraction systems | C56: General Site/Laboratory Extraction systems | D56: 10 | F56: 10
B57: Building, e.g. guardhouse, control rooms, offices | C57: General Site/Building | D57: 20 | F57: 30
B58: Platforms/Loading Racks/Fall Arrest Systems | C58: General Site/Platforms | D58: 10 | F58: 10
B59: Comunications, e.g. PA systems, telecommunications | C59: General Site/Communications | D59: 5 | F59: 5
B60: Electrical Distribution( includes MCC/PCC/Transformers) | C60: General Site/Electrical Distribution | D60: 10 | F60: 10
B61: Lighting/Emergency Lighting | C61: General Site/Lighting | D61: 10 | F61: 10
B62: Fire Protection | C62: General Site/Fire Protection | D62: 10 | F62: 10
B63: Security Systems (alarms, access control, CCTV, etc.) | C63: General Site/Security Systems | D63: 5 | F63: 5
B64: Furniture/Internal Fitout | C64: General Site/Furniture | D64: 5 | F64: 5
B65: Water Waste Treatment Plant | C65: General Site/Water Waste Treatment Plant | D65: 10 | F65: 10
B66: Water Purification System | C66: General Site/Water Purification System | D66: 10 | F66: 10
B68: Below are some examples of 'assets in their own right' which are not components. This is not an exhaustive list
B69: Stand alone units | C69: Asset Description | D69: Useful Life (Years) | F69: Useful Life (Years)
A70: Assets in own right/not components | B70: Fired Heaters with stack | C70: Fires Heater | D70: 10 | F70: 10
B71: Steam boilers with stack | C71: Steam Boiler | D71: 10 | F71: 10
B72: Air-Compressors with air receivers and air dryers | C72: Air Compressor | D72: 10 | F72: 10
B73: Oil Water Separators | C73: Oil Water Separator | D73: 10 | F73: 10
B74: Cooling water towers and associated pumps | C74: Cooling Tower | D74: 10 | F74: 10
B75: Diesel generator with stack(captive power generation) | C75: Generator | D75: 10 | F75: 10
B76: Refrigeration Skids | C76: Refrigeration Skid | D76: 10 | F76: 10
B77: Mobile equipment (forktrucks, lifts, cranes, etc.) | C77: Mobile Equipment | D77: 5 | F77: 5
B78: Laboratory Equipment | C78: Lab Equipment | D78: 5 | F78: 5
B79: Uninterupted Power Supply (UPS) | C79: UPS | D79: 5 | F79: 5
B80: Safety/Environmental Speciaties | C80: HSSE Specialties | D80: 5 | F80: 5

Sheet FM Common mistakes 
B2: Common mistakes to avoid during ATN/FM preparation by CLT/embedded finance
B4: S No. | C4: Common mistakes
B5: 1 | C5: Issues relating to ATN/FM formats a) All sections are not properly populated (ATN/FM Header, authority request, why this project, expected impact on external bp metrics,economics, risks, authorities). b) Appropriate notes are not included (for e.g GHG, break-even etc.) in line with ATN/FM instructions c) Formatting issues (Header, footer, date stamp, font to be used, ATN/FM to fit in 2 pages with minimum appendices etc.) d) Authority requested is not stated on a NTE basis & doesn't tally with financial request in the Economics section e) Readiness to execute doesn't contain timelines for the next steps including agreement to be executed f) Delivery SPA is not identified g) Mitigations are not provided for risks h) Risks are not rated for both worst credible & Net basis
B6: 2 | C6: Issues relating to EEM guidance notes a) Project Life - Incorrect project life is considered b) Working capital - Release of working capital is not considered in the last year & additional working capital impact is not considered c) Lease - Cash flows are not aligned with EEM GN 35 d) Terminal value computation is improper, limitation is not considered (Terminal Value should account for 20% or less of the value of the project inclusive of the Terminal Value itself) e) Disposal - ISP (Indifferent Sales Price) computation is improper (If bp retains some value even after sale, that can be netted off to get ISP & tax engrossment should be done in consultation with tax.
B7: 3 | C7: Other issues a) Blue book rates - Plan Forex used instead of Blue Book rate, latest Blue book rates not used (Blue book rates are updated twice a year in Mar & Sep) b) Incorrect selection of an endorser as all the applicable authorities are not considered c) Long Term Capital Commitments - Net Exposure computation - Net exposure is a feasible (1 in 20 – ‘P5’ i.e. 5%) downside risk to bp arising from entering into the agreement/arrangement. However observed post tax discounted gross exposure is incorrectly considered as Net exposure d) RCOP in Expected impact on external bp metrics should be before tax & Cash flow after tax. Observed RCOP incorrectly reported as net of tax e) 'Expected Impact on external bp metrics table' should contain underlying RCOP (i.e excluding adjusting Items (NOI)). Observed incorrect RCOP considered (i.e, inclusive of adjusting items) f) When calculating the COGS difference between two scenarious it is not the full PCTP to be used but only the RM portions
C9: * prepared by Grover
